Workbook

Sheet post-audit-active-backlog-statu
A1: BacklogId | B1: SourceId | C1: Category | D1: System | E1: Files | F1: HistoricalStatus | G1: ActiveStatus | H1: PostAuditBatch | I1: ReviewRowId | J1: ReviewStatus | K1: Action | L1: ReviewArtifact | M1: SourceEvidence | N1: Commit | O1: UpdatedAt | P1: Notes
A2: RB-03235 | B2: P10-F03235 | C2: Packet handlers | D2: XMLSpawner | E2: Data/Scripts/Custom/XMLSpawner/PacketHandlerOverrides.cs | F2: Ready | G2: Fixed | H2: POST-BATCH-A | I2: PHA-001 | J2: Fixed | K2: Patched XmlTextEntryBook.ContentChange and BaseContentChange to enforce writable/range/accessibility before accepting client page edits. | L2: docs/codebase-audit/outputs/post-batch-a-packet-handler-review.csv | M2: PacketHandlerOverrides.cs:41-57; XmlTextEntryBook.cs:194-317; BaseBook.cs:399-447 | N2: 3259f43b fix: harden packet handler paths | O2: 2026-06-06T16:41:26.8957053-05:00 | P2: Active post-audit overlay; canonical Phase 13 repair-backlog.csv is preserved as historical generated evidence.
A3: RB-03236 | B3: P10-F03236 | C3: Packet handlers | D3: XMLSpawner | E3: Data/Scripts/Custom/XMLSpawner/PacketHandlerOverrides.cs | F3: Ready | G3: Fixed | H3: POST-BATCH-A | I3: PHA-002 | J3: Fixed | K3: Patched XmlAttach.UseReq to restore core NextActionTime update after accepted use requests and core Counselor bypass threshold. | L3: docs/codebase-audit/outputs/post-batch-a-packet-handler-review.csv | M3: PacketHandlerOverrides.cs:59-64; XmlAttach.cs:2463-2567; PacketHandlers.cs:1487-1525 | N3: 3259f43b fix: harden packet handler paths | O3: 2026-06-06T16:41:26.8957053-05:00 | P3: Active post-audit overlay; canonical Phase 13 repair-backlog.csv is preserved as historical generated evidence.
A4: RB-03237 | B4: P10-F03237 | C4: Packet handlers | D4: XMLSpawner | E4: Data/Scripts/Custom/XMLSpawner/XmlTextEntryBook.cs | F4: Ready | G4: ReviewedNoChange | H4: POST-BATCH-A | I4: PHA-003 | J4: ReviewedNoChange | K4: Kept commented registration unchanged; active 0x66 review and fixes are recorded in PHA-001. | L4: docs/codebase-audit/outputs/post-batch-a-packet-handler-review.csv | M4: XmlTextEntryBook.cs:186-194; PacketHandlerOverrides.cs:41-57 | N4: 3259f43b fix: harden packet handler paths | O4: 2026-06-06T16:41:26.8957053-05:00 | P4: Active post-audit overlay; canonical Phase 13 repair-backlog.csv is preserved as historical generated evidence.
A5: RB-03238 | B5: P10-F03238 | C5: Packet handlers | D5: Items:Books | E5: Data/Scripts/Items/Books/BaseBook.cs | F5: Ready | G5: ReviewedNoChange | H5: POST-BATCH-A | I5: PHA-004 | J5: ReviewedNoChange | K5: No source change; guards match the expected BaseBook header edit path. | L5: docs/codebase-audit/outputs/post-batch-a-packet-handler-review.csv | M5: BaseBook.cs:337-397 | N5: 3259f43b fix: harden packet handler paths | O5: 2026-06-06T16:41:26.8957053-05:00 | P5: Active post-audit overlay; canonical Phase 13 repair-backlog.csv is preserved as historical generated evidence.
A6: RB-03239 | B6: P10-F03239 | C6: Packet handlers | D6: Items:Books | E6: Data/Scripts/Items/Books/BaseBook.cs | F6: Ready | G6: ReviewedNoChange | H6: POST-BATCH-A | I6: PHA-005 | J6: ReviewedNoChange | K6: No direct BaseBook source change; XMLSpawner delegate parity is fixed in PHA-001. | L6: docs/codebase-audit/outputs/post-batch-a-packet-handler-review.csv | M6: BaseBook.cs:337-447; PacketHandlerOverrides.cs:41-57 | N6: 3259f43b fix: harden packet handler paths | O6: 2026-06-06T16:41:26.8957053-05:00 | P6: Active post-audit overlay; canonical Phase 13 repair-backlog.csv is preserved as historical generated evidence.
A7: RB-03240 | B7: P10-F03240 | C7: Packet handlers | D7: Items:Books | E7: Data/Scripts/Items/Books/BaseBook.cs | F7: Ready | G7: ReviewedNoChange | H7: POST-BATCH-A | I7: PHA-006 | J7: ReviewedNoChange | K7: No source change; legacy handler has the same core access/range guard shape as HeaderChange. | L7: docs/codebase-audit/outputs/post-batch-a-packet-handler-review.csv | M7: BaseBook.cs:337-364 | N7: 3259f43b fix: harden packet handler paths | O7: 2026-06-06T16:41:26.8957053-05:00 | P7: Active post-audit overlay; canonical Phase 13 repair-backlog.csv is preserved as historical generated evidence.
A8: RB-03241 | B8: P10-F03241 | C8: Packet handlers | D8: Housing | E8: Data/Scripts/Items/Houses/Monopoly/Misc/GumpResponse.cs | F8: Ready | G8: Fixed | H8: POST-BATCH-A | I8: PHA-007 | J8: Fixed | K8: Patched DisplayGumpResponse to save and restore PacketReader position before m_Successor or core fallback. Deferred exact switch/text maximum parity because core Gump.m_Switches and m_TextEntries are internal to ServerCore. | L8: docs/codebase-audit/outputs/post-batch-a-packet-handler-review.csv | M8: GumpResponse.cs:19-101; PacketReader.cs:71-87; PacketHandlers.cs:1267-1365; Gump.cs:35-36 | N8: 3259f43b fix: harden packet handler paths | O8: 2026-06-06T16:41:26.8957053-05:00 | P8: Active post-audit overlay; canonical Phase 13 repair-backlog.csv is preserved as historical generated evidence.
A9: RB-03242 | B9: P10-F03242 | C9: Packet handlers | D9: Items:Misc | E9: Data/Scripts/Items/Misc/BulletinBoards.cs | F9: Ready | G9: ReviewedNoChange | H9: POST-BATCH-A | I9: PHA-008 | J9: ReviewedNoChange | K9: No source change; retained for later broader bulletin-board content/rate-limit review if needed. | L9: docs/codebase-audit/outputs/post-batch-a-packet-handler-review.csv | M9: BulletinBoards.cs:228-344 | N9: 3259f43b fix: harden packet handler paths | O9: 2026-06-06T16:41:26.8957053-05:00 | P9: Active post-audit overlay; canonical Phase 13 repair-backlog.csv is preserved as historical generated evidence.
A10: RB-03243 | B10: P10-F03243 | C10: Packet handlers | D10: Items:Misc | E10: Data/Scripts/Items/Misc/Games/Mahjong/MahjongPacketHandlers.cs | F10: Ready | G10: ReviewedNoChange | H10: POST-BATCH-A | I10: PHA-009 | J10: ReviewedNoChange | K10: No source change; review records game-state authorization as the controlling guard. | L10: docs/codebase-audit/outputs/post-batch-a-packet-handler-review.csv | M10: MahjongPacketHandlers.cs:36-267 | N10: 3259f43b fix: harden packet handler paths | O10: 2026-06-06T16:41:26.8957053-05:00 | P10: Active post-audit overlay; canonical Phase 13 repair-backlog.csv is preserved as historical generated evidence.
A11: RB-03244 | B11: P10-F03244 | C11: Packet handlers | D11: Items:Trades | E11: Data/Scripts/Items/Trades/Maps/MapItem.cs | F11: Ready | G11: ReviewedNoChange | H11: POST-BATCH-A | I11: PHA-010 | J11: ReviewedNoChange | K11: No source change; existing command methods provide the meaningful access/range gates. | L11: docs/codebase-audit/outputs/post-batch-a-packet-handler-review.csv | M11: MapItem.cs:394-435; MapItem.cs:545-585 | N11: 3259f43b fix: harden packet handler paths | O11: 2026-06-06T16:41:26.8957053-05:00 | P11: Active post-audit overlay; canonical Phase 13 repair-backlog.csv is preserved as historical generated evidence.
A12: RB-03245 | B12: P10-F03245 | C12: Packet handlers | D12: System:Chat | E12: Data/Scripts/System/Chat/General/Chat3Guild.cs | F12: Ready | G12: ReviewedNoChange | H12: POST-BATCH-A | I12: PHA-011 | J12: ReviewedNoChange | K12: No source change; downstream Channel.OnChat enforces CanChat for the ASCII guild path. | L12: docs/codebase-audit/outputs/post-batch-a-packet-handler-review.csv | M12: Chat3Guild.cs:15-40; Channel.cs:423-457; Guild.cs:69-79 | N12: 3259f43b fix: harden packet handler paths | O12: 2026-06-06T16:41:26.8957053-05:00 | P12: Active post-audit overlay; canonical Phase 13 repair-backlog.csv is preserved as historical generated evidence.
... A123: RB-00193 | B123: SERIAL-0132 | C123: Save compatibility | D123: Custom:Mobiles | E123: Data/Scripts/Custom/Mobiles/Spiders/SpiderQueen.cs | F123: Ready | G123: SafeNoChange | H123: POST-BATCH-B-03M | I123: SERIAL-0132 | J123: SafeNoChange | K123: No source change; SpiderQueen calls base Serialize/Deserialize, writes version 0, reads the same version integer, and has no custom serialized fields. | L123: docs/codebase-audit/outputs/post-batch-b-save-compatibility-triage.csv | M123: Data/Scripts/Custom/Mobiles/Spiders/SpiderQueen.cs:34-43 | N123: Recorded by current POST-BATCH-B-03M audit artifact commit | O123: 2026-06-06T22:53:28.9794767-05:00 | P123: Active post-audit overlay; canonical Phase 13 repair-backlog.csv is preserved as historical generated evidence.
A124: RB-00195 | B124: SERIAL-0134 | C124: WriteReadAlignment | D124: Custom:Mobiles | E124: Data/Scripts/Custom/Mobiles/Titans/FalseEarthGod.cs | F124: Ready | G124: SafeNoChange | H124: POST-BATCH-B-03N | I124: SERIAL-0134 | J124: Reviewed | K124: No source change; serializer already writes and reads only the version after base serialization. | L124: docs/codebase-audit/outputs/post-batch-b-save-compatibility-triage.csv | M124: Data/Scripts/Custom/Mobiles/Titans/FalseEarthGod.cs:38-47 | O124: 2026-06-06T23:00:23.0394448-05:00 | P124: Version-only mobile serializer; base Serialize/Deserialize calls and version write/read are aligned.
A125: RB-00197 | B125: SERIAL-0136 | C125: WriteReadAlignment | D125: Custom:Mobiles | E125: Data/Scripts/Custom/Mobiles/Titans/FalseFireGod.cs | F125: Ready | G125: SafeNoChange | H125: POST-BATCH-B-03N | I125: SERIAL-0136 | J125: Reviewed | K125: No source change; serializer already writes and reads only the version after base serialization. | L125: docs/codebase-audit/outputs/post-batch-b-save-compatibility-triage.csv | M125: Data/Scripts/Custom/Mobiles/Titans/FalseFireGod.cs:36-45 | O125: 2026-06-06T23:00:23.0394448-05:00 | P125: Version-only mobile serializer; base Serialize/Deserialize calls and version write/read are aligned.
A126: RB-00199 | B126: SERIAL-0138 | C126: WriteReadAlignment | D126: Custom:Mobiles | E126: Data/Scripts/Custom/Mobiles/Titans/FalseSeaGod.cs | F126: Ready | G126: SafeNoChange | H126: POST-BATCH-B-03N | I126: SERIAL-0138 | J126: Reviewed | K126: No source change; serializer already writes and reads only the version after base serialization. | L126: docs/codebase-audit/outputs/post-batch-b-save-compatibility-triage.csv | M126: Data/Scripts/Custom/Mobiles/Titans/FalseSeaGod.cs:36-45 | O126: 2026-06-06T23:00:23.0394448-05:00 | P126: Version-only mobile serializer; base Serialize/Deserialize calls and version write/read are aligned.
A127: RB-00201 | B127: SERIAL-0140 | C127: WriteReadAlignment | D127: Custom:Mobiles | E127: Data/Scripts/Custom/Mobiles/Titans/FalseWindGod.cs | F127: Ready | G127: SafeNoChange | H127: POST-BATCH-B-03N | I127: SERIAL-0140 | J127: Reviewed | K127: No source change; serializer already writes and reads only the version after base serialization. | L127: docs/codebase-audit/outputs/post-batch-b-save-compatibility-triage.csv | M127: Data/Scripts/Custom/Mobiles/Titans/FalseWindGod.cs:36-45 | O127: 2026-06-06T23:00:23.0394448-05:00 | P127: Version-only mobile serializer; base Serialize/Deserialize calls and version write/read are aligned.
A128: RB-00203 | B128: SERIAL-0142 | C128: WriteReadAlignment | D128: Custom:Mobiles | E128: Data/Scripts/Custom/Mobiles/Titans/Herculian.cs | F128: Ready | G128: SafeNoChange | H128: POST-BATCH-B-03N | I128: SERIAL-0142 | J128: Reviewed | K128: No source change; serializer already writes and reads only the version after base serialization. | L128: docs/codebase-audit/outputs/post-batch-b-save-compatibility-triage.csv | M128: Data/Scripts/Custom/Mobiles/Titans/Herculian.cs:36-45 | O128: 2026-06-06T23:00:23.0394448-05:00 | P128: Version-only mobile serializer; base Serialize/Deserialize calls and version write/read are aligned.
A129: RB-00205 | B129: SERIAL-0144 | C129: WriteReadAlignment | D129: Custom:Mobiles | E129: Data/Scripts/Custom/Mobiles/Undead/Beholder.cs | F129: Ready | G129: SafeNoChange | H129: POST-BATCH-B-03O | I129: SERIAL-0144 | J129: Reviewed | K129: No source change; serializer already writes and reads only the version after base serialization. | L129: docs/codebase-audit/outputs/post-batch-b-save-compatibility-triage.csv | M129: Data/Scripts/Custom/Mobiles/Undead/Beholder.cs:61-70 | O129: 2026-06-06T23:06:40.4235492-05:00 | P129: Version-only mobile serializer; base Serialize/Deserialize calls and version write/read are aligned.
A130: RB-00207 | B130: SERIAL-0146 | C130: WriteReadAlignment | D130: Custom:Mobiles | E130: Data/Scripts/Custom/Mobiles/Undead/CryptKeeper.cs | F130: Ready | G130: SafeNoChange | H130: POST-BATCH-B-03O | I130: SERIAL-0146 | J130: Reviewed | K130: No source change; serializer already writes and reads only the version after base serialization. | L130: docs/codebase-audit/outputs/post-batch-b-save-compatibility-triage.csv | M130: Data/Scripts/Custom/Mobiles/Undead/CryptKeeper.cs:55-64 | O130: 2026-06-06T23:06:40.4235492-05:00 | P130: Version-only mobile serializer; base Serialize/Deserialize calls and version write/read are aligned.
A131: RB-00209 | B131: SERIAL-0148 | C131: WriteReadAlignment | D131: Custom:Mobiles | E131: Data/Scripts/Custom/Mobiles/Undead/EvilDruid.cs | F131: Ready | G131: SafeNoChange | H131: POST-BATCH-B-03O | I131: SERIAL-0148 | J131: Reviewed | K131: No source change; serializer already writes and reads only the version after base serialization. | L131: docs/codebase-audit/outputs/post-batch-b-save-compatibility-triage.csv | M131: Data/Scripts/Custom/Mobiles/Undead/EvilDruid.cs:35-44 | O131: 2026-06-06T23:06:40.4235492-05:00 | P131: Version-only mobile serializer; base Serialize/Deserialize calls and version write/read are aligned.
A132: RB-00211 | B132: SERIAL-0150 | C132: WriteReadAlignment | D132: Custom:Mobiles | E132: Data/Scripts/Custom/Mobiles/Undead/GhostOfLadyEverdear.cs | F132: Ready | G132: SafeNoChange | H132: POST-BATCH-B-03O | I132: SERIAL-0150 | J132: Reviewed | K132: No source change; serializer already writes and reads only the version after base serialization. | L132: docs/codebase-audit/outputs/post-batch-b-save-compatibility-triage.csv | M132: Data/Scripts/Custom/Mobiles/Undead/GhostOfLadyEverdear.cs:50-59 | O132: 2026-06-06T23:06:40.4235492-05:00 | P132: Version-only mobile serializer; base Serialize/Deserialize calls and version write/read are aligned.
A133: RB-00213 | B133: SERIAL-0152 | C133: WriteReadAlignment | D133: Custom:Mobiles | E133: Data/Scripts/Custom/Mobiles/Undead/Honorguard.cs | F133: Ready | G133: SafeNoChange | H133: POST-BATCH-B-03O | I133: SERIAL-0152 | J133: Reviewed | K133: No source change; serializer already writes and reads only the version after base serialization. | L133: docs/codebase-audit/outputs/post-batch-b-save-compatibility-triage.csv | M133: Data/Scripts/Custom/Mobiles/Undead/Honorguard.cs:77-86 | O133: 2026-06-06T23:06:40.4235492-05:00 | P133: Version-only mobile serializer; base Serialize/Deserialize calls and version write/read are aligned.
A134: RB-00215 | B134: SERIAL-0154 | C134: WriteReadAlignment | D134: Custom:Mobiles | E134: Data/Scripts/Custom/Mobiles/Undead/OldKingWolfgang.cs | F134: Ready | G134: SafeNoChange | H134: POST-BATCH-B-03O | I134: SERIAL-0154 | J134: Reviewed | K134: No source change; serializer already writes and reads only the version after base serialization. | L134: docs/codebase-audit/outputs/post-batch-b-save-compatibility-triage.csv | M134: Data/Scripts/Custom/Mobiles/Undead/OldKingWolfgang.cs:38-47 | O134: 2026-06-06T23:06:40.4235492-05:00 | P134: Version-only mobile serializer; base Serialize/Deserialize calls and version write/read are aligned.
A135: RB-00217 | B135: SERIAL-0156 | C135: WriteReadAlignment | D135: Custom:Mobiles | E135: Data/Scripts/Custom/Mobiles/Undead/Rattlebones.cs | F135: Ready | G135: SafeNoChange | H135: POST-BATCH-B-03O | I135: SERIAL-0156 | J135: Reviewed | K135: No source change; serializer already writes and reads only the version after base serialization. | L135: docs/codebase-audit/outputs/post-batch-b-save-compatibility-triage.csv | M135: Data/Scripts/Custom/Mobiles/Undead/Rattlebones.cs:56-65 | O135: 2026-06-06T23:06:40.4235492-05:00 | P135: Version-only mobile serializer; base Serialize/Deserialize calls and version write/read are aligned.
... A303: RB-01557 | B303: SERIAL-1496 | C303: WriteReadAlignment | D303: System:Regions | E303: Data/Scripts/System/Regions/Spawning/SpawnEntry.cs | F303: Ready | G303: FalsePositive | H303: POST-BATCH-B-33A | I303: SERIAL-1496 | J303: Reviewed | K303: No source change; generated finding is extractor noise for a SpawnEntry helper serializer. SpawnPersistence writes the parent version and calls SpawnEntry.Serialize, and SpawnEntry.Deserialize(reader, version) or SpawnEntry.Remove(reader, version) consumes the paired helper payload. | L303: docs/codebase-audit/outputs/post-batch-b-save-compatibility-triage.csv | M303: Data/Scripts/System/Regions/Spawning/SpawnPersistence.cs:39-70; Data/Scripts/System/Regions/Spawning/SpawnEntry.cs:277-361 | O303: 2026-06-08T01:51:02.7822737-05:00 | P303: SpawnEntry is not an Item/Mobile override serializer; base-call and missing-reader findings are not applicable to this helper persistence shape.
A304: RB-01877 | B304: P10-F01877 | C304: Runtime hooks | D304: XMLSpawner | E304: Data/Scripts/Custom/XMLSpawner/PacketHandlerOverrides.cs | F304: Ready | G304: Fixed | H304: POST-BATCH-C-01A | I304: PHC-001 | J304: Fixed | K304: No new source change; prior POST-BATCH-A source fix already addressed this runtime hook row: Patched XmlTextEntryBook.ContentChange and BaseContentChange to enforce writable/range/accessibility before accepting client page edits. | L304: docs/codebase-audit/outputs/post-batch-c-runtime-hooks-player-mobile-review.csv | M304: PacketHandlerOverrides.cs:41-57; XmlTextEntryBook.cs:194-317; BaseBook.cs:399-447 | N304: Recorded by current POST-BATCH-C-01A audit artifact commit | O304: 2026-06-08T15:41:13.9877742-05:00 | P304: Mapped to PHA-001 in POST-BATCH-A.
A305: RB-01878 | B305: P10-F01878 | C305: Runtime hooks | D305: XMLSpawner | E305: Data/Scripts/Custom/XMLSpawner/PacketHandlerOverrides.cs | F305: Ready | G305: Fixed | H305: POST-BATCH-C-01A | I305: PHC-002 | J305: Fixed | K305: No new source change; prior POST-BATCH-A source fix already addressed this runtime hook row: Patched XmlAttach.UseReq to restore core NextActionTime update after accepted use requests and core Counselor bypass threshold. | L305: docs/codebase-audit/outputs/post-batch-c-runtime-hooks-player-mobile-review.csv | M305: PacketHandlerOverrides.cs:59-64; XmlAttach.cs:2463-2567; PacketHandlers.cs:1487-1525 | N305: Recorded by current POST-BATCH-C-01A audit artifact commit | O305: 2026-06-08T15:41:13.9877742-05:00 | P305: Mapped to PHA-002 in POST-BATCH-A.
A306: RB-01879 | B306: P10-F01879 | C306: Runtime hooks | D306: XMLSpawner | E306: Data/Scripts/Custom/XMLSpawner/XmlTextEntryBook.cs | F306: Ready | G306: ReviewedNoChange | H306: POST-BATCH-C-01A | I306: PHC-003 | J306: ReviewedNoChange | K306: No source change; prior POST-BATCH-A packet-handler review found existing guards acceptable for this runtime hook row: Kept commented registration unchanged; active 0x66 review and fixes are recorded in PHA-001. | L306: docs/codebase-audit/outputs/post-batch-c-runtime-hooks-player-mobile-review.csv | M306: XmlTextEntryBook.cs:186-194; PacketHandlerOverrides.cs:41-57 | N306: Recorded by current POST-BATCH-C-01A audit artifact commit | O306: 2026-06-08T15:41:13.9877742-05:00 | P306: Mapped to PHA-003 in POST-BATCH-A.
A307: RB-01880 | B307: P10-F01880 | C307: Runtime hooks | D307: Items:Books | E307: Data/Scripts/Items/Books/BaseBook.cs | F307: Ready | G307: ReviewedNoChange | H307: POST-BATCH-C-01A | I307: PHC-004 | J307: ReviewedNoChange | K307: No source change; prior POST-BATCH-A packet-handler review found existing guards acceptable for this runtime hook row: No source change; guards match the expected BaseBook header edit path. | L307: docs/codebase-audit/outputs/post-batch-c-runtime-hooks-player-mobile-review.csv | M307: BaseBook.cs:337-397 | N307: Recorded by current POST-BATCH-C-01A audit artifact commit | O307: 2026-06-08T15:41:13.9877742-05:00 | P307: Mapped to PHA-004 in POST-BATCH-A.
A308: RB-01881 | B308: P10-F01881 | C308: Runtime hooks | D308: Items:Books | E308: Data/Scripts/Items/Books/BaseBook.cs | F308: Ready | G308: ReviewedNoChange | H308: POST-BATCH-C-01A | I308: PHC-005 | J308: ReviewedNoChange | K308: No source change; prior POST-BATCH-A packet-handler review found existing guards acceptable for this runtime hook row: No direct BaseBook source change; XMLSpawner delegate parity is fixed in PHA-001. | L308: docs/codebase-audit/outputs/post-batch-c-runtime-hooks-player-mobile-review.csv | M308: BaseBook.cs:337-447; PacketHandlerOverrides.cs:41-57 | N308: Recorded by current POST-BATCH-C-01A audit artifact commit | O308: 2026-06-08T15:41:13.9877742-05:00 | P308: Mapped to PHA-005 in POST-BATCH-A.
A309: RB-01882 | B309: P10-F01882 | C309: Runtime hooks | D309: Items:Books | E309: Data/Scripts/Items/Books/BaseBook.cs | F309: Ready | G309: ReviewedNoChange | H309: POST-BATCH-C-01A | I309: PHC-006 | J309: ReviewedNoChange | K309: No source change; prior POST-BATCH-A packet-handler review found existing guards acceptable for this runtime hook row: No source change; legacy handler has the same core access/range guard shape as HeaderChange. | L309: docs/codebase-audit/outputs/post-batch-c-runtime-hooks-player-mobile-review.csv | M309: BaseBook.cs:337-364 | N309: Recorded by current POST-BATCH-C-01A audit artifact commit | O309: 2026-06-08T15:41:13.9877742-05:00 | P309: Mapped to PHA-006 in POST-BATCH-A.
A310: RB-01883 | B310: P10-F01883 | C310: Runtime hooks | D310: Housing | E310: Data/Scripts/Items/Houses/Monopoly/Misc/GumpResponse.cs | F310: Ready | G310: Fixed | H310: POST-BATCH-E-94A | I310: PHE-282 | J310: Fixed | K310: Patched Monopoly DisplayGumpResponse to complete the deferred exact switch/text maximum parity repair: it still saves and restores PacketReader position before m_Successor or core fallback, and now rejects switch counts above the matched gump's check/radio entry count, rejects text counts above the matched gump's text-entry count, and disconnects oversized text-entry payloads before relay allocation or OnResponse. | L310: docs/codebase-audit/outputs/post-batch-e-hooks-gumps-commands-regions-review.csv | M310: Data/Scripts/Items/Houses/Monopoly/Misc/GumpResponse.cs:19-142; Data/System/Source/Network/PacketHandlers.cs:1267-1327; Data/System/Source/Gumps/Gump.cs:35-36;530-531; Data/System/Source/Gumps/GumpCheck.cs:103-114; Data/System/Source/Gumps/GumpRadio.cs:103-114; Data/System/Source/Gumps/GumpTextEntry.cs:113-124; Data/System/Source/Gumps/GumpTextEntryLimited.cs:123-135 | N310: d75479ea and current POST-BATCH-E-94A source fix commit | O310: 2026-06-09T23:04:31.0536900-05:00 | P310: Supersedes the POST-BATCH-C-01A active overlay row for RB-01883; mapped to PHA-007 in POST-BATCH-A.
A311: RB-01884 | B311: P10-F01884 | C311: Runtime hooks | D311: Items:Misc | E311: Data/Scripts/Items/Misc/BulletinBoards.cs | F311: Ready | G311: ReviewedNoChange | H311: POST-BATCH-C-01A | I311: PHC-008 | J311: ReviewedNoChange | K311: No source change; prior POST-BATCH-A packet-handler review found existing guards acceptable for this runtime hook row: No source change; retained for later broader bulletin-board content/rate-limit review if needed. | L311: docs/codebase-audit/outputs/post-batch-c-runtime-hooks-player-mobile-review.csv | M311: BulletinBoards.cs:228-344 | N311: Recorded by current POST-BATCH-C-01A audit artifact commit | O311: 2026-06-08T15:41:13.9877742-05:00 | P311: Mapped to PHA-008 in POST-BATCH-A.
A312: RB-01885 | B312: P10-F01885 | C312: Runtime hooks | D312: Items:Misc | E312: Data/Scripts/Items/Misc/Games/Mahjong/MahjongPacketHandlers.cs | F312: Ready | G312: ReviewedNoChange | H312: POST-BATCH-C-01A | I312: PHC-009 | J312: ReviewedNoChange | K312: No source change; prior POST-BATCH-A packet-handler review found existing guards acceptable for this runtime hook row: No source change; review records game-state authorization as the controlling guard. | L312: docs/codebase-audit/outputs/post-batch-c-runtime-hooks-player-mobile-review.csv | M312: MahjongPacketHandlers.cs:36-267 | N312: Recorded by current POST-BATCH-C-01A audit artifact commit | O312: 2026-06-08T15:41:13.9877742-05:00 | P312: Mapped to PHA-009 in POST-BATCH-A.
A313: RB-01886 | B313: P10-F01886 | C313: Runtime hooks | D313: Items:Trades | E313: Data/Scripts/Items/Trades/Maps/MapItem.cs | F313: Ready | G313: ReviewedNoChange | H313: POST-BATCH-C-01A | I313: PHC-010 | J313: ReviewedNoChange | K313: No source change; prior POST-BATCH-A packet-handler review found existing guards acceptable for this runtime hook row: No source change; existing command methods provide the meaningful access/range gates. | L313: docs/codebase-audit/outputs/post-batch-c-runtime-hooks-player-mobile-review.csv | M313: MapItem.cs:394-435; MapItem.cs:545-585 | N313: Recorded by current POST-BATCH-C-01A audit artifact commit | O313: 2026-06-08T15:41:13.9877742-05:00 | P313: Mapped to PHA-010 in POST-BATCH-A.
A314: RB-01887 | B314: P10-F01887 | C314: Runtime hooks | D314: System:Chat | E314: Data/Scripts/System/Chat/General/Chat3Guild.cs | F314: Ready | G314: ReviewedNoChange | H314: POST-BATCH-C-01A | I314: PHC-011 | J314: ReviewedNoChange | K314: No source change; prior POST-BATCH-A packet-handler review found existing guards acceptable for this runtime hook row: No source change; downstream Channel.OnChat enforces CanChat for the ASCII guild path. | L314: docs/codebase-audit/outputs/post-batch-c-runtime-hooks-player-mobile-review.csv | M314: Chat3Guild.cs:15-40; Channel.cs:423-457; Guild.cs:69-79 | N314: Recorded by current POST-BATCH-C-01A audit artifact commit | O314: 2026-06-08T15:41:13.9877742-05:00 | P314: Mapped to PHA-011 in POST-BATCH-A.
A315: RB-01888 | B315: P10-F01888 | C315: Runtime hooks | D315: System:Chat | E315: Data/Scripts/System/Chat/General/Chat3Guild.cs | F315: Ready | G315: ReviewedNoChange | H315: POST-BATCH-C-01A | I315: PHC-012 | J315: ReviewedNoChange | K315: No source change; prior POST-BATCH-A packet-handler review found existing guards acceptable for this runtime hook row: No source change; explicit CanChat and downstream Channel.OnChat checks both protect guild chat. | L315: docs/codebase-audit/outputs/post-batch-c-runtime-hooks-player-mobile-review.csv | M315: Chat3Guild.cs:15-123; Channel.cs:423-457; Guild.cs:69-79 | N315: Recorded by current POST-BATCH-C-01A audit artifact commit | O315: 2026-06-08T15:41:13.9877742-05:00 | P315: Mapped to PHA-012 in POST-BATCH-A.
... A320: RB-01893 | B320: P10-F01893 | C320: Runtime hooks | D320: Regions | E320: Data/Scripts/System/Obsolete/Obsolete.cs | F320: Ready | G320: ReviewedNoChange | H320: POST-BATCH-C-01A | I320: PHC-017 | J320: ReviewedNoChange | K320: No source change; prior POST-BATCH-A packet-handler review found existing guards acceptable for this runtime hook row: No source change; broad legacy chat behavior remains deferred to chat-system review after P0 packet pass. | L320: docs/codebase-audit/outputs/post-batch-c-runtime-hooks-player-mobile-review.csv | M320: Obsolete.cs:6101-6153 | N320: Recorded by current POST-BATCH-C-01A audit artifact commit | O320: 2026-06-08T15:41:13.9877742-05:00 | P320: Mapped to PHA-017 in POST-BATCH-A.
A321: RB-05228 | B321: P10-F05228 | C321: PlayerMobile coupling | D321: Custom:Skill Stone | F321: Ready | G321: SafeNoChange | H321: POST-BATCH-C-01A | I321: PHC-018 | J321: SafeNoChange | K321: No source change; SkillStone writes a PlayerMobile reference through the Mobile writer overload and reads it back with reader.ReadMobile() cast to PlayerMobile, preserving the saved object-reference format. | L321: docs/codebase-audit/outputs/post-batch-c-runtime-hooks-player-mobile-review.csv | M321: Data/Scripts/Custom/Skill Stone/SkillStone.cs:168-199; serialization-register.csv Server.Items.SkillStone Writes/Reads | N321: Recorded by current POST-BATCH-C-01A audit artifact commit | O321: 2026-06-08T15:41:13.9877742-05:00 | P321: Keep namespace/type stable; future SkillStone changes should preserve assigned-player reference semantics.
A322: RB-05352 | B322: P10-F05352 | C322: PlayerMobile coupling | D322: Mobiles:Base | F322: Ready | G322: ReviewedNoChange | H322: POST-BATCH-C-01A | I322: PHC-019 | J322: ReviewedNoChange | K322: No source change; source review found current PlayerMobile version 37 fall-through mirrors Serialize. The generated count mismatch is conservative noise around helper serializers, conditional collection loops, and versioned legacy branches, not a source-confirmed stream mismatch. | L322: docs/codebase-audit/outputs/post-batch-c-runtime-hooks-player-mobile-review.csv | M322: Data/Scripts/Mobiles/Base/PlayerMobile.cs:4539-4937; Data/Scripts/Mobiles/Base/PlayerMobile.cs:5004-5221; comment-target-register.csv P10-COM-2671 | N322: Recorded by current POST-BATCH-C-01A audit artifact commit | O322: 2026-06-08T15:41:13.9877742-05:00 | P322: Existing Phase 11 comment at PlayerMobile.cs:4544 documents this risk.
A323: RB-05362 | B323: P10-F05362 | C323: PlayerMobile coupling | D323: PlayerMobile Core | F323: Ready | G323: ReviewedNoChange | H323: POST-BATCH-C-01A | I323: PHC-020 | J323: ReviewedNoChange | K323: No source change; PlayerMobile item-object graph coupling is expected for a core Mobile serializer and remains protected by the save-order warning and POST-BATCH-B closeout. | L323: docs/codebase-audit/outputs/post-batch-c-runtime-hooks-player-mobile-review.csv | M323: Data/Scripts/Mobiles/Base/PlayerMobile.cs:4539-4937; Data/Scripts/Mobiles/Base/PlayerMobile.cs:5004-5221; dependency-graph.csv PlayerMobile v37 serialization edges | N323: Recorded by current POST-BATCH-C-01A audit artifact commit | O323: 2026-06-08T15:41:13.9877742-05:00 | P323: Review dependent item policies before future PlayerMobile edits.
A324: RB-05363 | B324: P10-F05363 | C324: PlayerMobile coupling | D324: PlayerMobile Core | F324: Ready | G324: ReviewedNoChange | H324: POST-BATCH-C-01A | I324: PHC-021 | J324: ReviewedNoChange | K324: No source change; PlayerMobile mobile-object graph coupling is expected for player state and stable/perma-flag/justice lists. | L324: docs/codebase-audit/outputs/post-batch-c-runtime-hooks-player-mobile-review.csv | M324: Data/Scripts/Mobiles/Base/PlayerMobile.cs:4539-4937; Data/Scripts/Mobiles/Base/PlayerMobile.cs:5004-5221; dependency-graph.csv PlayerMobile v37 serialization edges | N324: Recorded by current POST-BATCH-C-01A audit artifact commit | O324: 2026-06-08T15:41:13.9877742-05:00 | P324: Review save-load behavior before changing player-owned Mobile references.
A325: RB-05368 | B325: P10-F05368 | C325: PlayerMobile coupling | D325: PlayerMobile Core | F325: Ready | G325: ReviewedNoChange | H325: POST-BATCH-C-01A | I325: PHC-022 | J325: ReviewedNoChange | K325: No source change; PlayerMobile world-save loader coupling is expected because PlayerMobile is a serialized Mobile subclass and central save surface. | L325: docs/codebase-audit/outputs/post-batch-c-runtime-hooks-player-mobile-review.csv | M325: Data/Scripts/Mobiles/Base/PlayerMobile.cs:4539-4937; Data/Scripts/Mobiles/Base/PlayerMobile.cs:5004-5221; serialization-register.csv Server.Mobiles.PlayerMobile | N325: Recorded by current POST-BATCH-C-01A audit artifact commit | O325: 2026-06-08T15:41:13.9877742-05:00 | P325: Keep PlayerMobile DoNotMove until a full migration plan exists.
A326: RB-05382 | B326: P10-F05382 | C326: PlayerMobile coupling | D326: PvP Consent | F326: Ready | G326: ReviewedNoChange | H326: POST-BATCH-C-01A | I326: PHC-023 | J326: ReviewedNoChange | K326: No source change; PvP Consent item-object graph coupling through PlayerMobile is expected shared player policy state and not a standalone source defect in this review. | L326: docs/codebase-audit/outputs/post-batch-c-runtime-hooks-player-mobile-review.csv | M326: Data/Scripts/Mobiles/Base/PlayerMobile.cs:4539-4937; Data/Scripts/Mobiles/Base/PlayerMobile.cs:5004-5221; dependency-graph.csv PvP Consent PlayerMobile edges | N326: Recorded by current POST-BATCH-C-01A audit artifact commit | O326: 2026-06-08T15:41:13.9877742-05:00 | P326: Handle PvP behavior in later targeted policy batches, not by changing PlayerMobile save layout here.
A327: RB-05383 | B327: P10-F05383 | C327: PlayerMobile coupling | D327: PvP Consent | F327: Ready | G327: ReviewedNoChange | H327: POST-BATCH-C-01A | I327: PHC-024 | J327: ReviewedNoChange | K327: No source change; PvP Consent mobile-object graph coupling through PlayerMobile is expected shared player policy state and not a standalone source defect in this review. | L327: docs/codebase-audit/outputs/post-batch-c-runtime-hooks-player-mobile-review.csv | M327: Data/Scripts/Mobiles/Base/PlayerMobile.cs:4539-4937; Data/Scripts/Mobiles/Base/PlayerMobile.cs:5004-5221; dependency-graph.csv PvP Consent PlayerMobile edges | N327: Recorded by current POST-BATCH-C-01A audit artifact commit | O327: 2026-06-08T15:41:13.9877742-05:00 | P327: Do not rename PlayerMobile or PvP-related serialized types without migration approval.
A328: RB-05403 | B328: P10-F05403 | C328: PlayerMobile coupling | D328: PvP Consent | F328: Ready | G328: ReviewedNoChange | H328: POST-BATCH-C-01A | I328: PHC-025 | J328: ReviewedNoChange | K328: No source change; PvP Consent world-save loader coupling through PlayerMobile is expected and remains migration-gated. | L328: docs/codebase-audit/outputs/post-batch-c-runtime-hooks-player-mobile-review.csv | M328: Data/Scripts/Mobiles/Base/PlayerMobile.cs:4539-4937; Data/Scripts/Mobiles/Base/PlayerMobile.cs:5004-5221; dependency-graph.csv PvP Consent PlayerMobile edges | N328: Recorded by current POST-BATCH-C-01A audit artifact commit | O328: 2026-06-08T15:41:13.9877742-05:00 | P328: Future PvP Consent source fixes must avoid serialization changes unless separately approved.
A329: RB-04689 | B329: P10-F04689 | C329: Pooled enumerables | D329: Custom:Champions | E329: Data/Scripts/Custom/Champions/Mobiles/Champs-UO/Barracoon.cs | F329: Ready | G329: Fixed | H329: POST-BATCH-D-01A | I329: PHD-001 | J329: Fixed | K329: Replaced direct foreach over this.GetMobilesInRange(10) with IPooledEnumerable eable plus try/finally Free while preserving rat count logic. | L329: docs/codebase-audit/outputs/post-batch-d-pooled-enumerable-review.csv | M329: Data/Scripts/Custom/Champions/Mobiles/Champs-UO/Barracoon.cs:201-213 | N329: Recorded by current POST-BATCH-D-01A source/audit commit | O329: 2026-06-08T16:38:18.0434300-05:00 | P329: Confirmed pooled enumerable ownership leak; fixed with try/finally Free and no behavior, serialization, namespace, type, or file-location changes.
A330: RB-04690 | B330: P10-F04690 | C330: Pooled enumerables | D330: Custom:Champions | E330: Data/Scripts/Custom/Champions/Mobiles/Champs-UO/Ilhenir.cs | F330: Ready | G330: Fixed | H330: POST-BATCH-D-01A | I330: PHD-002 | J330: Fixed | K330: Replaced direct foreach over Map.GetItemsInRange(p, 0) with IPooledEnumerable eable plus try/finally Free while preserving StainedOoze detection and break behavior. | L330: docs/codebase-audit/outputs/post-batch-d-pooled-enumerable-review.csv | M330: Data/Scripts/Custom/Champions/Mobiles/Champs-UO/Ilhenir.cs:320-335 | N330: Recorded by current POST-BATCH-D-01A source/audit commit | O330: 2026-06-08T16:38:18.0434300-05:00 | P330: Confirmed pooled enumerable ownership leak; fixed with try/finally Free and no behavior, serialization, namespace, type, or file-location changes.
A331: RB-04691 | B331: P10-F04691 | C331: Pooled enumerables | D331: Custom:Champions | E331: Data/Scripts/Custom/Champions/Mobiles/Champs-UO/Ilhenir.cs | F331: Ready | G331: Fixed | H331: POST-BATCH-D-01A | I331: PHD-003 | J331: Fixed | K331: Replaced direct foreach over GetMobilesInRange(0) with IPooledEnumerable eable plus try/finally Free while preserving filtering and damage target collection. | L331: docs/codebase-audit/outputs/post-batch-d-pooled-enumerable-review.csv | M331: Data/Scripts/Custom/Champions/Mobiles/Champs-UO/Ilhenir.cs:419-443 | N331: Recorded by current POST-BATCH-D-01A source/audit commit | O331: 2026-06-08T16:38:18.0434300-05:00 | P331: Confirmed pooled enumerable ownership leak; fixed with try/finally Free and no behavior, serialization, namespace, type, or file-location changes.
A332: RB-04692 | B332: P10-F04692 | C332: Pooled enumerables | D332: Custom:Champions | E332: Data/Scripts/Custom/Champions/Mobiles/Champs-UO/Rikktor.cs | F332: Ready | G332: Fixed | H332: POST-BATCH-D-01A | I332: PHD-004 | J332: Fixed | K332: Replaced direct foreach over this.GetMobilesInRange(8) with IPooledEnumerable eable plus try/finally Free while preserving target selection. | L332: docs/codebase-audit/outputs/post-batch-d-pooled-enumerable-review.csv | M332: Data/Scripts/Custom/Champions/Mobiles/Champs-UO/Rikktor.cs:129-153 | N332: Recorded by current POST-BATCH-D-01A source/audit commit | O332: 2026-06-08T16:38:18.0434300-05:00 | P332: Confirmed pooled enumerable ownership leak; fixed with try/finally Free and no behavior, serialization, namespace, type, or file-location changes.
A333: RB-04693 | B333: P10-F04693 | C333: Pooled enumerables | D333: Custom:Champions | E333: Data/Scripts/Custom/Champions/Mobiles/Champs-UO/Semidar.cs | F333: Ready | G333: Fixed | H333: POST-BATCH-D-01A | I333: PHD-005 | J333: Fixed | K333: Replaced direct foreach over this.GetMobilesInRange(2) with IPooledEnumerable eable plus try/finally Free while preserving target selection. | L333: docs/codebase-audit/outputs/post-batch-d-pooled-enumerable-review.csv | M333: Data/Scripts/Custom/Champions/Mobiles/Champs-UO/Semidar.cs:114-138 | N333: Recorded by current POST-BATCH-D-01A source/audit commit | O333: 2026-06-08T16:38:18.0434300-05:00 | P333: Confirmed pooled enumerable ownership leak; fixed with try/finally Free and no behavior, serialization, namespace, type, or file-location changes.
A334: RB-04694 | B334: P10-F04694 | C334: Pooled enumerables | D334: Custom:Champions | E334: Data/Scripts/Custom/Champions/Mobiles/Champs-UO/Serado.cs | F334: Ready | G334: Fixed | H334: POST-BATCH-D-01A | I334: PHD-006 | J334: Fixed | K334: Replaced direct foreach over target.GetMobilesInRange(8) with IPooledEnumerable eable plus try/finally Free while preserving counterattack target selection. | L334: docs/codebase-audit/outputs/post-batch-d-pooled-enumerable-review.csv | M334: Data/Scripts/Custom/Champions/Mobiles/Champs-UO/Serado.cs:190-214 | N334: Recorded by current POST-BATCH-D-01A source/audit commit | O334: 2026-06-08T16:38:18.0434300-05:00 | P334: Confirmed pooled enumerable ownership leak; fixed with try/finally Free and no behavior, serialization, namespace, type, or file-location changes.
A335: RB-04695 | B335: P10-F04695 | C335: Pooled enumerables | D335: Custom:Champions | E335: Data/Scripts/Custom/Champions/Mobiles/Minions/InterredGrizzle .cs | F335: Ready | G335: Fixed | H335: POST-BATCH-D-01A | I335: PHD-007 | J335: Fixed | K335: Replaced direct foreach over Map.GetItemsInRange(p, 0) with IPooledEnumerable eable plus try/finally Free while preserving StainedOoze detection and break behavior. | L335: docs/codebase-audit/outputs/post-batch-d-pooled-enumerable-review.csv | M335: Data/Scripts/Custom/Champions/Mobiles/Minions/InterredGrizzle .cs:132-147 | N335: Recorded by current POST-BATCH-D-01A source/audit commit | O335: 2026-06-08T16:38:18.0434300-05:00 | P335: Confirmed pooled enumerable ownership leak; fixed with try/finally Free and no behavior, serialization, namespace, type, or file-location changes.
A336: RB-04696 | B336: P10-F04696 | C336: Pooled enumerables | D336: Custom:Champions | E336: Data/Scripts/Custom/Champions/Mobiles/Minions/PlagueBeastLord.cs | F336: Ready | G336: Fixed | H336: POST-BATCH-D-01A | I336: PHD-008 | J336: Fixed | K336: Replaced direct foreach over GetClientsInRange(12) with IPooledEnumerable eable plus try/finally Free while preserving overhead-message delivery. | L336: docs/codebase-audit/outputs/post-batch-d-pooled-enumerable-review.csv | M336: Data/Scripts/Custom/Champions/Mobiles/Minions/PlagueBeastLord.cs:232-252 | N336: Recorded by current POST-BATCH-D-01A source/audit commit | O336: 2026-06-08T16:38:18.0434300-05:00 | P336: Confirmed pooled enumerable ownership leak; fixed with try/finally Free and no behavior, serialization, namespace, type, or file-location changes.
A337: RB-04697 | B337: P10-F04697 | C337: Pooled enumerables | D337: Custom:ClearDeckCommand | E337: Data/Scripts/Custom/ClearDeckCommand/ClearDeckCommand.cs | F337: Ready | G337: Fixed | H337: POST-BATCH-D-02A | I337: PHD-009 | J337: Fixed | K337: Replaced direct foreach over playerBoat.GetItemsInRange(18) with IPooledEnumerable eable plus try/finally Free while preserving corpse collection and deletion behavior. | L337: docs/codebase-audit/outputs/post-batch-d-pooled-enumerable-review.csv | M337: Data/Scripts/Custom/ClearDeckCommand/ClearDeckCommand.cs:38-65 | N337: Recorded by current POST-BATCH-D-02A source/audit commit | O337: 2026-06-08T16:42:46.5194703-05:00 | P337: Confirmed pooled enumerable ownership leak; fixed with try/finally Free and no behavior, serialization, namespace, type, or file-location changes.
A338: RB-04698 | B338: P10-F04698 | C338: Pooled enumerables | D338: Custom:Government System | E338: Data/Scripts/Custom/Government System/Items/Deeds/CityDeed.cs | F338: Ready | G338: Fixed | H338: POST-BATCH-D-03A | I338: PHD-010 | J338: Fixed | K338: Replaced direct foreach over spwn.GetMobilesInRange(0) with IPooledEnumerable spawnerMobiles plus try/finally Free while preserving landlord lookup, initialization, and break behavior. | L338: docs/codebase-audit/outputs/post-batch-d-pooled-enumerable-review.csv | M338: Data/Scripts/Custom/Government System/Items/Deeds/CityDeed.cs:3129-3146 | N338: Recorded by current POST-BATCH-D-03A source/audit commit | O338: 2026-06-08T16:50:54.6607029-05:00 | P338: Confirmed pooled enumerable ownership leak; fixed with try/finally Free and no behavior, serialization, namespace, type, or file-location changes.
A339: RB-04699 | B339: P10-F04699 | C339: Pooled enumerables | D339: Custom:Government System | E339: Data/Scripts/Custom/Government System/Items/Deeds/CityDeed.cs | F339: Ready | G339: Fixed | H339: POST-BATCH-D-03A | I339: PHD-011 | J339: Fixed | K339: Replaced direct foreach over spwn.GetMobilesInRange(0) with IPooledEnumerable spawnerMobiles plus try/finally Free while preserving landlord lookup, initialization, and break behavior. | L339: docs/codebase-audit/outputs/post-batch-d-pooled-enumerable-review.csv | M339: Data/Scripts/Custom/Government System/Items/Deeds/CityDeed.cs:3193-3210 | N339: Recorded by current POST-BATCH-D-03A source/audit commit | O339: 2026-06-08T16:50:54.6607029-05:00 | P339: Confirmed pooled enumerable ownership leak; fixed with try/finally Free and no behavior, serialization, namespace, type, or file-location changes.
A340: RB-04700 | B340: P10-F04700 | C340: Pooled enumerables | D340: Custom:Government System | E340: Data/Scripts/Custom/Government System/Items/Deeds/CityDeed.cs | F340: Ready | G340: Fixed | H340: POST-BATCH-D-03A | I340: PHD-012 | J340: Fixed | K340: Replaced direct foreach over spwn.GetMobilesInRange(0) with IPooledEnumerable spawnerMobiles plus try/finally Free while preserving landlord lookup, initialization, and break behavior. | L340: docs/codebase-audit/outputs/post-batch-d-pooled-enumerable-review.csv | M340: Data/Scripts/Custom/Government System/Items/Deeds/CityDeed.cs:3257-3274 | N340: Recorded by current POST-BATCH-D-03A source/audit commit | O340: 2026-06-08T16:50:54.6607029-05:00 | P340: Confirmed pooled enumerable ownership leak; fixed with try/finally Free and no behavior, serialization, namespace, type, or file-location changes.
... A887: RB-01749 | B887: P10-F01749 | C887: Runtime hooks | D887: Spell Framework | E887: Data/Scripts/Magic/Ninjitsu/AnimalForm.cs | F887: Ready | G887: Fixed | H887: POST-BATCH-E-36A | I887: PHE-151 | J887: Fixed | K887: Added null LoginEventArgs and null/deleted mobile guards before animal-form context lookup and speed-control packet send. | L887: docs/codebase-audit/outputs/post-batch-e-hooks-gumps-commands-regions-review.csv | M887: Data/Scripts/Magic/Ninjitsu/AnimalForm.cs:20-31 | N887: Recorded by current POST-BATCH-E-36A source/audit commit | O887: 2026-06-09T11:52:53.8033110-05:00 | P887: Valid animal-form speed boost restoration on login was preserved; serialization, public APIs, namespaces, type names, save versions, file location, and project files were unchanged.
A888: RB-01750 | B888: P10-F01750 | C888: Runtime hooks | D888: Spell Framework | E888: Data/Scripts/Magic/Research/Spells/Enchanting/ResearchEnchant.cs | F888: Ready | G888: Fixed | H888: POST-BATCH-RESEARCH-LOGOUT | I888: RLO-01 | J888: Fixed | K888: Register one static Logout handler during Initialize; select active owner orbs and use World.FindItem; bind expiry/load cleanup to individual orbs. | L888: docs/codebase-audit/outputs/post-batch-research-logout-review.csv | M888: Data/Scripts/Magic/Research/Spells/Enchanting/ResearchEnchant.cs; ResearchEnchant.Initialize:L54;OnLogout:L65;EndEffects:L227;EndEffect:L236;ResearchEnchantStone.FindByOwner:L268;OnAfterDelete:L292;Deserialize:L318;RunTime:L334 | N888: Recorded by POST-BATCH-RESEARCH-LOGOUT source/audit commit | O888: 46312 | P888: Fixes per-cast retained callbacks and two world-item scans per callback. Saved fields/version/order unchanged; RB-01376 remains separate. Supersedes POST-BATCH-E-37A guard-only closeout for this defect. Verification: docs/codebase-audit/outputs/post-batch-research-logout-closeout.md
A889: RB-01751 | B889: P10-F01751 | C889: Runtime hooks | D889: Spell Framework | E889: Data/Scripts/Magic/Research/Spells/Enchanting/ResearchSneak.cs | F889: Ready | G889: Fixed | H889: POST-BATCH-RESEARCH-LOGOUT | I889: RLO-02 | J889: Fixed | K889: Register one static Logout handler during Initialize and remove Sneak only for a logging-out mobile with an active effect. | L889: docs/codebase-audit/outputs/post-batch-research-logout-review.csv | M889: Data/Scripts/Magic/Research/Spells/Enchanting/ResearchSneak.cs; ResearchSneak.Initialize:L48;OnCast:L54;OnLogout:L62;HasEffect:L82;RemoveEffect:L87 | N889: Recorded by POST-BATCH-RESEARCH-LOGOUT source/audit commit | O889: 46312 | P889: Fixes per-cast retained callbacks and prevents revealing unrelated hidden players. Recipient cleanup remains intact. Supersedes POST-BATCH-E-38A guard-only closeout for this defect. Verification: docs/codebase-audit/outputs/post-batch-research-logout-closeout.md
A890: RB-01752 | B890: P10-F01752 | C890: Runtime hooks | D890: Vendor Core | E890: Data/Scripts/Mobiles/Base/Behavior.cs | F890: Ready | G890: ReviewedNoChange | H890: POST-BATCH-E-39A | I890: PHE-154 | J890: ReviewedNoChange | K890: Reviewed StunRequest invocation; no source change because the AI owner is already required by the action method and the subscribed Fists handler guards null event args and null/deleted mobiles. | L890: docs/codebase-audit/outputs/post-batch-e-hooks-gumps-commands-regions-review.csv | M890: Data/Scripts/Mobiles/Base/Behavior.cs:14127-14200; Data/Scripts/Items/Weapons/Hands/Fists.cs:13-14;270-328; Data/System/Source/EventSink.cs:654-681;1357-1367 | N890: Recorded by current POST-BATCH-E-39A review-only audit commit | O890: 2026-06-09T19:17:48.2720365-05:00 | P890: Source review only; source build and compile-only verification were not required because no source files changed.
A891: RB-01753 | B891: P10-F01753 | C891: Runtime hooks | D891: Vendor Core | E891: Data/Scripts/Mobiles/Base/Behavior.cs | F891: Ready | G891: ReviewedNoChange | H891: POST-BATCH-E-39A | I891: PHE-155 | J891: ReviewedNoChange | K891: Reviewed DisarmRequest invocation; no source change because the AI owner is already required by the action method and the subscribed Fists handler guards null event args and null/deleted mobiles. | L891: docs/codebase-audit/outputs/post-batch-e-hooks-gumps-commands-regions-review.csv | M891: Data/Scripts/Mobiles/Base/Behavior.cs:15058-15092; Data/Scripts/Items/Weapons/Hands/Fists.cs:13-14;270-328; Data/System/Source/EventSink.cs:654-681;1357-1367 | N891: Recorded by current POST-BATCH-E-39A review-only audit commit | O891: 2026-06-09T19:17:48.2720365-05:00 | P891: Source review only; source build and compile-only verification were not required because no source files changed.
A892: RB-01754 | B892: P10-F01754 | C892: Runtime hooks | D892: PvP Consent | E892: Data/Scripts/Mobiles/Base/PlayerMobile.cs | F892: Ready | G892: Fixed | H892: POST-BATCH-E-40A | I892: PHE-156 | J892: Fixed | K892: Added null LoginEventArgs and null/deleted mobile guards before atrophy checks, lockdown notice handling, disconnect scheduling, and auto-stabled pet claim. | L892: docs/codebase-audit/outputs/post-batch-e-hooks-gumps-commands-regions-review.csv | M892: Data/Scripts/Mobiles/Base/PlayerMobile.cs:1003-1054 | N892: Recorded by current POST-BATCH-E-40A source/audit commit | O892: 2026-06-09T19:21:50.9852241-05:00 | P892: Valid login behavior was preserved; serialization, public APIs, namespaces, type names, save versions, file location, and project files were unchanged.
A893: RB-01755 | B893: P10-F01755 | C893: Runtime hooks | D893: PvP Consent | E893: Data/Scripts/Mobiles/Base/PlayerMobile.cs | F893: Ready | G893: Fixed | H893: POST-BATCH-E-40A | I893: PHE-157 | J893: Fixed | K893: Added null LogoutEventArgs and null/deleted mobile guards before PlayerMobile auto-stabled pet cleanup. | L893: docs/codebase-audit/outputs/post-batch-e-hooks-gumps-commands-regions-review.csv | M893: Data/Scripts/Mobiles/Base/PlayerMobile.cs:1328-1340 | N893: Recorded by current POST-BATCH-E-40A source/audit commit | O893: 2026-06-09T19:21:50.9852241-05:00 | P893: Valid logout auto-stabling behavior was preserved; serialization, public APIs, namespaces, type names, save versions, file location, and project files were unchanged.
A894: RB-01756 | B894: P10-F01756 | C894: Runtime hooks | D894: PvP Consent | E894: Data/Scripts/Mobiles/Base/PlayerMobile.cs | F894: Ready | G894: Fixed | H894: POST-BATCH-E-40A | I894: PHE-158 | J894: Fixed | K894: Added null ConnectedEventArgs and null/deleted mobile guards before session tracking, quest timer start, disguise timer start, and special-move clearing. | L894: docs/codebase-audit/outputs/post-batch-e-hooks-gumps-commands-regions-review.csv | M894: Data/Scripts/Mobiles/Base/PlayerMobile.cs:1342-1372 | N894: Recorded by current POST-BATCH-E-40A source/audit commit | O894: 2026-06-09T19:21:50.9852241-05:00 | P894: Valid connect behavior was preserved for live mobiles; serialization, public APIs, namespaces, type names, save versions, file location, and project files were unchanged.
A895: RB-01757 | B895: P10-F01757 | C895: Runtime hooks | D895: PvP Consent | E895: Data/Scripts/Mobiles/Base/PlayerMobile.cs | F895: Ready | G895: Fixed | H895: POST-BATCH-E-40A | I895: PHE-159 | J895: Fixed | K895: Added null DisconnectedEventArgs and null/deleted mobile guards before design-context cleanup, session accounting, quest timer stop, speech-log cleanup, last-online update, and disguise timer stop. | L895: docs/codebase-audit/outputs/post-batch-e-hooks-gumps-commands-regions-review.csv | M895: Data/Scripts/Mobiles/Base/PlayerMobile.cs:1381-1430 | N895: Recorded by current POST-BATCH-E-40A source/audit commit | O895: 2026-06-09T19:21:50.9852241-05:00 | P895: Valid disconnect behavior was preserved for live mobiles; serialization, public APIs, namespaces, type names, save versions, file location, and project files were unchanged.
A896: RB-01764 | B896: P10-F01764 | C896: Runtime hooks | D896: System:Commands | E896: Data/Scripts/System/Commands/Logging.cs | F896: Ready | G896: Fixed | H896: POST-BATCH-E-41A | I896: PHE-160 | J896: Fixed | K896: Added null CommandEventArgs and null/deleted mobile guards before command log formatting and WriteLine dispatch. | L896: docs/codebase-audit/outputs/post-batch-e-hooks-gumps-commands-regions-review.csv | M896: Data/Scripts/System/Commands/Logging.cs:157-175 | N896: Recorded by current POST-BATCH-E-41A source/audit commit | O896: 2026-06-09T19:30:31.1738917-05:00 | P896: Valid command logging behavior was preserved for live mobiles; serialization, public APIs, namespaces, type names, save versions, file location, and project files were unchanged.
A897: RB-01765 | B897: P10-F01765 | C897: Runtime hooks | D897: System:Commands | E897: Data/Scripts/System/Commands/VisibilityList.cs | F897: Ready | G897: Fixed | H897: POST-BATCH-E-42A | I897: PHE-161 | J897: Fixed | K897: Added null LoginEventArgs and null/deleted mobile guards before PlayerMobile visibility-list login cleanup. | L897: docs/codebase-audit/outputs/post-batch-e-hooks-gumps-commands-regions-review.csv | M897: Data/Scripts/System/Commands/VisibilityList.cs:34-50 | N897: Recorded by current POST-BATCH-E-42A source/audit commit | O897: 2026-06-09T19:34:14.4161032-05:00 | P897: Valid login visibility-list reset behavior was preserved; serialization, public APIs, namespaces, type names, save versions, file location, and project files were unchanged.
A898: RB-01766 | B898: P10-F01766 | C898: Runtime hooks | D898: System:Commands | E898: Data/Scripts/System/Commands/Player/Afk.cs | F898: Ready | G898: Fixed | H898: POST-BATCH-E-43A | I898: PHE-162 | J898: Fixed | K898: Added null LogoutEventArgs and null mobile guards before AFK table lookup and wake-up cleanup. | L898: docs/codebase-audit/outputs/post-batch-e-hooks-gumps-commands-regions-review.csv | M898: Data/Scripts/System/Commands/Player/Afk.cs:55-75 | N898: Recorded by current POST-BATCH-E-43A source/audit commit | O898: 2026-06-09T19:38:51.1881605-05:00 | P898: Valid logout AFK cleanup was preserved for valid mobiles; serialization, public APIs, namespaces, type names, save versions, file location, and project files were unchanged.
A899: RB-01767 | B899: P10-F01767 | C899: Runtime hooks | D899: System:Commands | E899: Data/Scripts/System/Commands/Player/Afk.cs | F899: Ready | G899: Fixed | H899: POST-BATCH-E-43A | I899: PHE-163 | J899: Fixed | K899: Added null SpeechEventArgs and null mobile guards before AFK table lookup and wake-up cleanup. | L899: docs/codebase-audit/outputs/post-batch-e-hooks-gumps-commands-regions-review.csv | M899: Data/Scripts/System/Commands/Player/Afk.cs:77-97 | N899: Recorded by current POST-BATCH-E-43A source/audit commit | O899: 2026-06-09T19:38:51.1881605-05:00 | P899: Valid speech AFK wake-up behavior was preserved; serialization, public APIs, namespaces, type names, save versions, file location, and project files were unchanged.
A900: RB-01768 | B900: P10-F01768 | C900: Runtime hooks | D900: System:Commands | E900: Data/Scripts/System/Commands/Player/Afk.cs | F900: Ready | G900: Fixed | H900: POST-BATCH-E-43A | I900: PHE-164 | J900: Fixed | K900: Added null PlayerDeathEventArgs and null mobile guards before AFK table lookup, death sound, and wake-up cleanup. | L900: docs/codebase-audit/outputs/post-batch-e-hooks-gumps-commands-regions-review.csv | M900: Data/Scripts/System/Commands/Player/Afk.cs:32-53 | N900: Recorded by current POST-BATCH-E-43A source/audit commit | O900: 2026-06-09T19:38:51.1881605-05:00 | P900: Valid death AFK wake-up behavior was preserved for valid mobiles; serialization, public APIs, namespaces, type names, save versions, file location, and project files were unchanged.
A901: RB-01978 | B901: P10-F01978 | C901: Runtime hooks | D901: System:Commands | E901: Data/Scripts/System/Commands/Player/Afk.cs | F901: Ready | G901: Fixed | H901: POST-BATCH-E-43A | I901: PHE-165 | J901: Fixed | K901: Resolved duplicate speech-method marker with the same null SpeechEventArgs and null mobile guards added to AFK.OnSpeech. | L901: docs/codebase-audit/outputs/post-batch-e-hooks-gumps-commands-regions-review.csv | M901: Data/Scripts/System/Commands/Player/Afk.cs:77-97 | N901: Recorded by current POST-BATCH-E-43A source/audit commit | O901: 2026-06-09T19:38:51.1881605-05:00 | P901: Duplicate speech-method marker shares the RB-01767 source fix; valid speech AFK wake-up behavior was preserved.
... A1011: RB-01876 | B1011: P10-F01876 | C1011: Runtime hooks | D1011: ServerCore | E1011: Data/System/Source/Network/PacketHandlers.cs | F1011: Ready | G1011: ReviewedNoChange | H1011: POST-BATCH-E-91A | I1011: PHE-275 | J1011: ReviewedNoChange | K1011: Reviewed server-list event invocation; no source change because AccountLogin_ReplyAck constructs ServerListEventArgs after successful account login, and the ServerList subscriber guards null args plus null state/socket and rejects invalid state or endpoint exceptions. | L1011: docs/codebase-audit/outputs/post-batch-e-hooks-gumps-commands-regions-review.csv | M1011: Data/System/Source/Network/PacketHandlers.cs:2721-2730; Data/System/Source/EventSink.cs:800-840;1148;1399-1402; Data/Scripts/System/Misc/ServerList.cs:46-58;63-97 | N1011: Recorded by current POST-BATCH-E-91A review-only audit commit | O1011: 2026-06-09T22:47:41.9419923-05:00 | P1011: Valid account-login server-list behavior remains unchanged.
A1012: RB-05603 | B1012: P10-F05603 | C1012: Economy and reward loops | D1012: Character Level <-> Offline Skill Training | F1012: Open | G1012: AcceptedFence | H1012: POST-BATCH-Y | I1012: PBY-0001 | J1012: PreserveCurrentBalancePolicy | K1012: Source changes may proceed outside economy/reward tuning. Edits inside a listed pair must preserve current gameplay balance unless a later design batch approves tuning. Excluded surface: Gameplay economy, reward rates, progression coupling, spawn reward, vendor/economy, crafting/harvest/gardening loop, and paired-system tuning for this relationship. | L1012: docs/codebase-audit/outputs/post-batch-y-source-change-gate-register.csv | M1012: PriorOverlayEvidence: Labels=BalanceRisk;Bypasses;DocRisk;Supports; RiskKind=DocumentationRisk;ProgressionBalance; Evidence=Character Level:docs/wiki/Character_Level_Recon_Report.md;Character Level:docs/wiki/Confictura_Introduction.md;Offline Skill Training:docs/wiki/offline-skill-training.md;Offline Skill Training:docs/wiki/offline-skill-training.md:L38;Phase 9 balance review: bypass intended danger or grants permanent power too quickly. || PriorNotes: Balance risk is intentionally separated from code correctness in POST-BATCH-F. | N1012: Pending: docs: publish source change readiness gates | O1012: 2026-06-15T11:56:52.1526354-05:00 | P1012: PreviousStatus=DeferredBalanceDecision; GateOutcome=Preserve current balance/reward behavior.; RequiredApproval=Required before changing balance, rewards, progression incentives, economy loops, or paired-system gameplay tuning.
A1013: RB-05604 | B1013: P10-F05604 | C1013: Economy and reward loops | D1013: Random Encounters <-> XMLSpawner | F1013: Open | G1013: AcceptedFence | H1013: POST-BATCH-Y | I1013: PBY-0002 | J1013: PreserveCurrentBalancePolicy | K1013: Source changes may proceed outside economy/reward tuning. Edits inside a listed pair must preserve current gameplay balance unless a later design batch approves tuning. Excluded surface: Gameplay economy, reward rates, progression coupling, spawn reward, vendor/economy, crafting/harvest/gardening loop, and paired-system tuning for this relationship. | L1013: docs/codebase-audit/outputs/post-batch-y-source-change-gate-register.csv | M1013: PriorOverlayEvidence: Labels=BalanceRisk;Conflicts;DependsOn;DocRisk;StaffDependency; RiskKind=DocumentationRisk;MaintenanceCoupling;PvEBalance; Evidence=Phase 9 conflict checklist: staff-spawned events versus automated PvE systems.;Random Encounters->XMLSpawner:DirectReference:Data/Scripts/Custom/RandomEncounters/EncounterEngine.cs:L16:XmlSpawner;Random Encounters->XMLSpawner:DirectReference:Data/Scripts/Custom/RandomEncounters/Helpers.cs:L15:XmlSpawner;Random Encounters->XMLSpawner:DirectReference:Data/Scripts/C... || PriorNotes: Balance risk is intentionally separated from code correctness in POST-BATCH-F. | N1013: Pending: docs: publish source change readiness gates | O1013: 2026-06-15T11:56:52.1526354-05:00 | P1013: PreviousStatus=DeferredBalanceDecision; GateOutcome=Preserve current balance/reward behavior.; RequiredApproval=Required before changing balance, rewards, progression incentives, economy loops, or paired-system gameplay tuning.
A1014: RB-05605 | B1014: P10-F05605 | C1014: Economy and reward loops | D1014: Random Encounters <-> Invasion | F1014: Open | G1014: AcceptedFence | H1014: POST-BATCH-Y | I1014: PBY-0003 | J1014: PreserveCurrentBalancePolicy | K1014: Source changes may proceed outside economy/reward tuning. Edits inside a listed pair must preserve current gameplay balance unless a later design batch approves tuning. Excluded surface: Gameplay economy, reward rates, progression coupling, spawn reward, vendor/economy, crafting/harvest/gardening loop, and paired-system tuning for this relationship. | L1014: docs/codebase-audit/outputs/post-batch-y-source-change-gate-register.csv | M1014: PriorOverlayEvidence: Labels=BalanceRisk;DocRisk;StaffDependency; RiskKind=DocumentationRisk;PvEBalance; Evidence=Invasion:docs/wiki/Invasion_System.md;Invasion:docs/wiki/SystemAudit.md:L21;Phase 9 conflict checklist: staff-spawned events versus automated PvE systems.;Random Encounters:docs/wiki/Random_Encounter_Engine.md;Random Encounters:docs/wiki/Search_System.md;Random Encounters:docs/wiki/SystemAudit.md:L20 || PriorNotes: Balance risk is intentionally separated from code correctness in POST-BATCH-F. | N1014: Pending: docs: publish source change readiness gates | O1014: 2026-06-15T11:56:52.1526354-05:00 | P1014: PreviousStatus=DeferredBalanceDecision; GateOutcome=Preserve current balance/reward behavior.; RequiredApproval=Required before changing balance, rewards, progression incentives, economy loops, or paired-system gameplay tuning.
A1015: RB-05606 | B1015: P10-F05606 | C1015: Economy and reward loops | D1015: Random Encounters <-> Champions | F1015: Open | G1015: AcceptedFence | H1015: POST-BATCH-Y | I1015: PBY-0004 | J1015: PreserveCurrentBalancePolicy | K1015: Source changes may proceed outside economy/reward tuning. Edits inside a listed pair must preserve current gameplay balance unless a later design batch approves tuning. Excluded surface: Gameplay economy, reward rates, progression coupling, spawn reward, vendor/economy, crafting/harvest/gardening loop, and paired-system tuning for this relationship. | L1015: docs/codebase-audit/outputs/post-batch-y-source-change-gate-register.csv | M1015: PriorOverlayEvidence: Labels=BalanceRisk;DocRisk;Duplicates; RiskKind=DocumentationRisk;PvEBalance; Evidence=Champions:docs/wiki/Champion_Spawns.md;Champions:docs/wiki/Champion_Spawns.md:L82;Champions:docs/wiki/SystemAudit.md:L34;Champions:docs/wiki/wikibacklog.md;Phase 9 conflict checklist: staff-spawned events versus automated PvE systems.;Random Encounters:docs/wiki/Random_Encounter_Engine.md;Random Encounters:docs/wiki/Search_System.md;Random Encounters:docs/wiki/SystemAudit.md:L20 || PriorNotes: Balance risk is intentionally separated from code correctness in POST-BATCH-F. | N1015: Pending: docs: publish source change readiness gates | O1015: 2026-06-15T11:56:52.1526354-05:00 | P1015: PreviousStatus=DeferredBalanceDecision; GateOutcome=Preserve current balance/reward behavior.; RequiredApproval=Required before changing balance, rewards, progression incentives, economy loops, or paired-system gameplay tuning.
A1016: RB-05607 | B1016: P10-F05607 | C1016: Economy and reward loops | D1016: Random Encounters <-> Monster Nests | F1016: Open | G1016: AcceptedFence | H1016: POST-BATCH-Y | I1016: PBY-0005 | J1016: PreserveCurrentBalancePolicy | K1016: Source changes may proceed outside economy/reward tuning. Edits inside a listed pair must preserve current gameplay balance unless a later design batch approves tuning. Excluded surface: Gameplay economy, reward rates, progression coupling, spawn reward, vendor/economy, crafting/harvest/gardening loop, and paired-system tuning for this relationship. | L1016: docs/codebase-audit/outputs/post-batch-y-source-change-gate-register.csv | M1016: PriorOverlayEvidence: Labels=BalanceRisk;DocRisk;Duplicates; RiskKind=DocumentationRisk;PvEBalance; Evidence=Monster Nests:docs/wiki/Monster_Nest_System.md;Phase 9 player objective review: exploration goals.;Random Encounters:docs/wiki/Random_Encounter_Engine.md;Random Encounters:docs/wiki/Search_System.md;Random Encounters:docs/wiki/SystemAudit.md:L20 || PriorNotes: Balance risk is intentionally separated from code correctness in POST-BATCH-F. | N1016: Pending: docs: publish source change readiness gates | O1016: 2026-06-15T11:56:52.1526354-05:00 | P1016: PreviousStatus=DeferredBalanceDecision; GateOutcome=Preserve current balance/reward behavior.; RequiredApproval=Required before changing balance, rewards, progression incentives, economy loops, or paired-system gameplay tuning.
A1017: RB-05608 | B1017: P10-F05608 | C1017: Economy and reward loops | D1017: Random Encounters <-> Offline Skill Training | F1017: Open | G1017: AcceptedFence | H1017: POST-BATCH-Y | I1017: PBY-0006 | J1017: PreserveCurrentBalancePolicy | K1017: Source changes may proceed outside economy/reward tuning. Edits inside a listed pair must preserve current gameplay balance unless a later design batch approves tuning. Excluded surface: Gameplay economy, reward rates, progression coupling, spawn reward, vendor/economy, crafting/harvest/gardening loop, and paired-system tuning for this relationship. | L1017: docs/codebase-audit/outputs/post-batch-y-source-change-gate-register.csv | M1017: PriorOverlayEvidence: Labels=BalanceRisk;Bypasses;DocRisk; RiskKind=DocumentationRisk;ProgressionBalance; Evidence=Offline Skill Training:docs/wiki/offline-skill-training.md;Offline Skill Training:docs/wiki/offline-skill-training.md:L38;Phase 9 balance review: bypass intended danger.;Random Encounters:docs/wiki/Random_Encounter_Engine.md;Random Encounters:docs/wiki/Search_System.md;Random Encounters:docs/wiki/SystemAudit.md:L20 || PriorNotes: Balance risk is intentionally separated from code correctness in POST-BATCH-F. | N1017: Pending: docs: publish source change readiness gates | O1017: 2026-06-15T11:56:52.1526354-05:00 | P1017: PreviousStatus=DeferredBalanceDecision; GateOutcome=Preserve current balance/reward behavior.; RequiredApproval=Required before changing balance, rewards, progression incentives, economy loops, or paired-system gameplay tuning.
A1018: RB-05609 | B1018: P10-F05609 | C1018: Economy and reward loops | D1018: PvP Consent <-> Government | F1018: Open | G1018: AcceptedFence | H1018: POST-BATCH-Y | I1018: PBY-0007 | J1018: PreserveCurrentBalancePolicy | K1018: Source changes may proceed outside economy/reward tuning. Edits inside a listed pair must preserve current gameplay balance unless a later design batch approves tuning. Excluded surface: Gameplay economy, reward rates, progression coupling, spawn reward, vendor/economy, crafting/harvest/gardening loop, and paired-system tuning for this relationship. | L1018: docs/codebase-audit/outputs/post-batch-y-source-change-gate-register.csv | M1018: PriorOverlayEvidence: Labels=BalanceRisk;Conflicts;DocRisk;Overrides; RiskKind=DocumentationRisk;PolicyConflict; Evidence=Government:docs/wiki/Government_System.md;Government:docs/wiki/Player_Government_System_Guide.md;Government:docs/wiki/SystemAudit.md:L24;Phase 9 conflict checklist: PvP Consent versus Government war and city-ban rules.;PvP Consent:docs/wiki/pvp-consent-system.md || PriorNotes: Balance risk is intentionally separated from code correctness in POST-BATCH-F. | N1018: Pending: docs: publish source change readiness gates | O1018: 2026-06-15T11:56:52.1526354-05:00 | P1018: PreviousStatus=DeferredBalanceDecision; GateOutcome=Preserve current balance/reward behavior.; RequiredApproval=Required before changing balance, rewards, progression incentives, economy loops, or paired-system gameplay tuning.
A1019: RB-05610 | B1019: P10-F05610 | C1019: Economy and reward loops | D1019: PvP Consent <-> XMLSpawner | F1019: Open | G1019: AcceptedFence | H1019: POST-BATCH-Y | I1019: PBY-0008 | J1019: PreserveCurrentBalancePolicy | K1019: Source changes may proceed outside economy/reward tuning. Edits inside a listed pair must preserve current gameplay balance unless a later design batch approves tuning. Excluded surface: Gameplay economy, reward rates, progression coupling, spawn reward, vendor/economy, crafting/harvest/gardening loop, and paired-system tuning for this relationship. | L1019: docs/codebase-audit/outputs/post-batch-y-source-change-gate-register.csv | M1019: PriorOverlayEvidence: Labels=BalanceRisk;Bypasses;Conflicts;DependsOn;DocRisk;StaffDependency; RiskKind=DocumentationRisk;MaintenanceCoupling;PolicyConflict; Evidence=Phase 9 conflict checklist: XMLPoints event overrides versus normal PvP consent.;PvP Consent->XMLSpawner:DirectReference:Data/Scripts/Mobiles/Base/PlayerMobile.cs:L12:XmlSpawner;PvP Consent:docs/wiki/pvp-consent-system.md;XMLSpawner:docs/wiki/AI_OVERHAUL_AUDIT.md;XMLSpawner:docs/wiki/SystemAudit.md:L22;XMLSpawner:docs/wiki/XML_Spawner_Enhancements.md || PriorNotes: Balance risk is intentionally separated from code correctness in POST-BATCH-F. | N1019: Pending: docs: publish source change readiness gates | O1019: 2026-06-15T11:56:52.1526354-05:00 | P1019: PreviousStatus=DeferredBalanceDecision; GateOutcome=Preserve current balance/reward behavior.; RequiredApproval=Required before changing balance, rewards, progression incentives, economy loops, or paired-system gameplay tuning.
A1020: RB-05611 | B1020: P10-F05611 | C1020: Economy and reward loops | D1020: Government <-> Homestead | F1020: Open | G1020: AcceptedFence | H1020: POST-BATCH-Y | I1020: PBY-0009 | J1020: PreserveCurrentBalancePolicy | K1020: Source changes may proceed outside economy/reward tuning. Edits inside a listed pair must preserve current gameplay balance unless a later design batch approves tuning. Excluded surface: Gameplay economy, reward rates, progression coupling, spawn reward, vendor/economy, crafting/harvest/gardening loop, and paired-system tuning for this relationship. | L1020: docs/codebase-audit/outputs/post-batch-y-source-change-gate-register.csv | M1020: PriorOverlayEvidence: Labels=BalanceRisk;DocRisk;Supports; RiskKind=DocumentationRisk;EconomyBalance; Evidence=Government:docs/wiki/Government_System.md;Government:docs/wiki/Player_Government_System_Guide.md;Government:docs/wiki/SystemAudit.md:L24;Homestead:docs/wiki/Farmable_Crops_System.md;Homestead:docs/wiki/Homestead_System.md;Homestead:docs/wiki/Standard_Crafting.md:L234;Homestead:docs/wiki/SystemAudit.md:L27;Phase 9 synergy checklist: Homestead deepening non-combat economy. || PriorNotes: Balance risk is intentionally separated from code correctness in POST-BATCH-F. | N1020: Pending: docs: publish source change readiness gates | O1020: 2026-06-15T11:56:52.1526354-05:00 | P1020: PreviousStatus=DeferredBalanceDecision; GateOutcome=Preserve current balance/reward behavior.; RequiredApproval=Required before changing balance, rewards, progression incentives, economy loops, or paired-system gameplay tuning.
A1021: RB-05612 | B1021: P10-F05612 | C1021: Economy and reward loops | D1021: Government <-> Vendor Core | F1021: Open | G1021: AcceptedFence | H1021: POST-BATCH-Y | I1021: PBY-0010 | J1021: PreserveCurrentBalancePolicy | K1021: Source changes may proceed outside economy/reward tuning. Edits inside a listed pair must preserve current gameplay balance unless a later design batch approves tuning. Excluded surface: Gameplay economy, reward rates, progression coupling, spawn reward, vendor/economy, crafting/harvest/gardening loop, and paired-system tuning for this relationship. | L1021: docs/codebase-audit/outputs/post-batch-y-source-change-gate-register.csv | M1021: PriorOverlayEvidence: Labels=BalanceRisk;DependsOn;DocRisk;Supports; RiskKind=DocumentationRisk;EconomyBalance;MaintenanceCoupling; Evidence=Government->Vendor Core:DirectReference:Data/Scripts/Custom/Government System/CityUpgradeSystem.cs:L93:Vendor;Government->Vendor Core:DirectReference:Data/Scripts/Custom/Government System/Gumps/CityManagementGump.cs:L184:Vendor;Government->Vendor Core:DirectReference:Data/Scripts/Custom/Government System/Gumps/CityMarketGump.cs:L30:Vendor;Government->Vendor Core:DirectReferen... || PriorNotes: Balance risk is intentionally separated from code correctness in POST-BATCH-F. | N1021: Pending: docs: publish source change readiness gates | O1021: 2026-06-15T11:56:52.1526354-05:00 | P1021: PreviousStatus=DeferredBalanceDecision; GateOutcome=Preserve current balance/reward behavior.; RequiredApproval=Required before changing balance, rewards, progression incentives, economy loops, or paired-system gameplay tuning.
A1022: RB-05613 | B1022: P10-F05613 | C1022: Economy and reward loops | D1022: Homestead <-> Crafting Core | F1022: Open | G1022: AcceptedFence | H1022: POST-BATCH-Y | I1022: PBY-0011 | J1022: PreserveCurrentBalancePolicy | K1022: Source changes may proceed outside economy/reward tuning. Edits inside a listed pair must preserve current gameplay balance unless a later design batch approves tuning. Excluded surface: Gameplay economy, reward rates, progression coupling, spawn reward, vendor/economy, crafting/harvest/gardening loop, and paired-system tuning for this relationship. | L1022: docs/codebase-audit/outputs/post-batch-y-source-change-gate-register.csv | M1022: PriorOverlayEvidence: Labels=BalanceRisk;DependsOn;DocRisk;Supports; RiskKind=DocumentationRisk;EconomyBalance;MaintenanceCoupling; Evidence=Crafting Core:docs/wiki/Apiculture_Beekeeping.md;Crafting Core:docs/wiki/Crafting_Core.md;Crafting Core:docs/wiki/Standard_Crafting.md:L234;Crafting Core:docs/wiki/Standard_Crafting.md:L235;Homestead->Crafting Core:DirectReference:Data/Scripts/Custom/Vhaerun's CRL Homestead System [2.0]/Dracana's Winecrafting [2.0]/Craft/DefWinecrafting.cs:L11:CraftSystem;Homestead->Crafting ... || PriorNotes: Balance risk is intentionally separated from code correctness in POST-BATCH-F. | N1022: Pending: docs: publish source change readiness gates | O1022: 2026-06-15T11:56:52.1526354-05:00 | P1022: PreviousStatus=DeferredBalanceDecision; GateOutcome=Preserve current balance/reward behavior.; RequiredApproval=Required before changing balance, rewards, progression incentives, economy loops, or paired-system gameplay tuning.
A1023: RB-05614 | B1023: P10-F05614 | C1023: Economy and reward loops | D1023: Homestead <-> Harvest System | F1023: Open | G1023: AcceptedFence | H1023: POST-BATCH-Y | I1023: PBY-0012 | J1023: PreserveCurrentBalancePolicy | K1023: Source changes may proceed outside economy/reward tuning. Edits inside a listed pair must preserve current gameplay balance unless a later design batch approves tuning. Excluded surface: Gameplay economy, reward rates, progression coupling, spawn reward, vendor/economy, crafting/harvest/gardening loop, and paired-system tuning for this relationship. | L1023: docs/codebase-audit/outputs/post-batch-y-source-change-gate-register.csv | M1023: PriorOverlayEvidence: Labels=BalanceRisk;DocRisk;Supports; RiskKind=DocumentationRisk;EconomyBalance; Evidence=Harvest System:docs/wiki/Apiculture_Beekeeping.md:L307;Harvest System:docs/wiki/Farmable_Crops_System.md;Harvest System:docs/wiki/Gardening_System.md;Harvest System:docs/wiki/Standard_Crafting.md:L235;Homestead:docs/wiki/Farmable_Crops_System.md;Homestead:docs/wiki/Homestead_System.md;Homestead:docs/wiki/Standard_Crafting.md:L234;Homestead:docs/wiki/SystemAudit.md:L27;Phase 9 conflict checklist: crafting/... || PriorNotes: Balance risk is intentionally separated from code correctness in POST-BATCH-F. | N1023: Pending: docs: publish source change readiness gates | O1023: 2026-06-15T11:56:52.1526354-05:00 | P1023: PreviousStatus=DeferredBalanceDecision; GateOutcome=Preserve current balance/reward behavior.; RequiredApproval=Required before changing balance, rewards, progression incentives, economy loops, or paired-system gameplay tuning.
... A1069: RB-05660 | B1069: P10-F05660 | C1069: Staff tooling | D1069: Static Gump Tool | F1069: Open | G1069: AcceptedFence | H1069: POST-BATCH-Y | I1069: PBY-0058 | J1069: PreserveCurrentStaffWorkflow | K1069: Non-staff workflow source maintenance may proceed. Staff tooling source edits may proceed only when they preserve command names, access levels, gump behavior, event workflow, and existing staff operations. Excluded surface: Staff workflow, staff-event operations, command names/access levels, generated gump tooling behavior, and XMLSpawner/Invasion/Static Gump Tool workflow semantics. | L1069: docs/codebase-audit/outputs/post-batch-y-source-change-gate-register.csv | M1069: PriorOverlayEvidence: Systems=Static Gump Tool <-> Obsolete Scripts; Labels=DependsOn;StaffDependency; Evidence=Obsolete Scripts->Static Gump Tool:DirectReference:Data/Scripts/System/Obsolete/PlantHerbalism.cs:L179:STool;Obsolete Scripts:docs/wiki/AI_OVERHAUL_AUDIT.md;Obsolete Scripts:docs/wiki/Magery_Spell_Color_Setting.md;Obsolete Scripts:docs/wiki/SystemAudit.md:L103;Static Gump Tool:docs/wiki/Static_Gump_Tool.md;Static Gump Tool:docs/wiki/SystemAudit.md:L102;Static Gump Tool:docs/wiki/wikibacklog.md:L23 || PriorNotes: Relationship-level staff dependency needs explicit owner policy before runtime changes. | N1069: Pending: docs: publish source change readiness gates | O1069: 2026-06-15T11:56:52.1526354-05:00 | P1069: PreviousStatus=NeedsHumanDecision; GateOutcome=Preserve current staff workflow/access policy.; RequiredApproval=Required before changing staff command access, event workflow, generated tool behavior, or staff-facing operation semantics.
A1070: RB-05661 | B1070: P10-F05661 | C1070: Staff tooling | D1070: Custom:ChangeSeason | E1070: Data/Scripts/Custom/ChangeSeason/ChangeSeason.cs | F1070: Ready | G1070: Fixed | H1070: POST-BATCH-Q | I1070: PBQ-0001 | J1070: Fixed | K1070: Added scoped custom command handler guard(s) for null/deleted mobile state before existing command work. | L1070: docs/codebase-audit/outputs/post-batch-q-staff-command-metadata-source-review.csv | M1070: POST-BATCH-N lane=POST-BATCH-N-STAFF-COMMAND-METADATA; FileProofStatus=CurrentPathConfirmed; Command=; Access=; L12; Registration=CommandSystem.Register(; CurrentRegistrationLine=12; CurrentCommand=ChangeSeason; CurrentAccess=AccessLevel.Administrator; CurrentHandler=ChangeSeason_OnCommand; CurrentRegistration=CommandSystem.Register( "ChangeSeason", AccessLevel.Administrator, new CommandEventHandler(ChangeSeason_OnCommand) );; POST-BATCH-Q direct source review=CustomCommandGuardFixed | N1070: Pending: fix: harden staff command metadata queue | O1070: 2026-06-14T16:16:57.8542018-05:00 | P1070: POST-BATCH-Q staff command metadata source review. Previous active row was PBN-0134/PBF-059. Public APIs, command names, access levels, namespaces, type names, file locations, project files, XML/config, serialization layout, and staff/player workflow semantics were preserved.
A1071: RB-05662 | B1071: P10-F05662 | C1071: Staff tooling | D1071: Custom:Character Swap | E1071: Data/Scripts/Custom/Character Swap/CharacterSwap.cs | F1071: Ready | G1071: Fixed | H1071: POST-BATCH-Q | I1071: PBQ-0002 | J1071: Fixed | K1071: Added scoped custom command handler guard(s) for null/deleted mobile state before existing command work. | L1071: docs/codebase-audit/outputs/post-batch-q-staff-command-metadata-source-review.csv | M1071: POST-BATCH-N lane=POST-BATCH-N-STAFF-COMMAND-METADATA; FileProofStatus=CurrentPathConfirmed; Command=; Access=; L14; Registration=CommandSystem.Register(; CurrentRegistrationLine=14; CurrentCommand=CharControl; CurrentAccess=AccessLevel.Administrator; CurrentHandler=CharControl_OnCommand; CurrentRegistration=CommandSystem.Register( "CharControl", AccessLevel.Administrator, new CommandEventHandler(CharControl_OnCommand) );; POST-BATCH-Q direct source review=CustomCommandGuardFixed | N1071: Pending: fix: harden staff command metadata queue | O1071: 2026-06-14T16:16:57.8542018-05:00 | P1071: POST-BATCH-Q staff command metadata source review. Previous active row was PBN-0135/PBF-060. Public APIs, command names, access levels, namespaces, type names, file locations, project files, XML/config, serialization layout, and staff/player workflow semantics were preserved.
A1072: RB-05663 | B1072: P10-F05663 | C1072: Staff tooling | D1072: Static Gump Tool | E1072: Data/Scripts/Custom/StaffTools/StaticGumpTool/StaticGump(Alternative).cs | F1072: Ready | G1072: Fixed | H1072: POST-BATCH-Q | I1072: PBQ-0003 | J1072: Fixed | K1072: Added shared Static Gump Tool command mobile guard before closing or sending staff gumps. | L1072: docs/codebase-audit/outputs/post-batch-q-staff-command-metadata-source-review.csv | M1072: POST-BATCH-N lane=POST-BATCH-N-STAFF-COMMAND-METADATA; FileProofStatus=PathNeedsReview; Command=; Access=; L13; Registration=CommandSystem.Register(; CurrentRegistrationLine=13; CurrentCommand=StaticsTool; CurrentAccess=AccessLevel.GameMaster; CurrentHandler=OzThothsStatic_OnCommand; CurrentRegistration=CommandSystem.Register( "StaticsTool", AccessLevel.GameMaster, new CommandEventHandler(OzThothsStatic_OnCommand) );; POST-BATCH-Q direct source review=StaticGumpCommandGuardFixed | N1072: Pending: fix: harden staff command metadata queue | O1072: 2026-06-14T16:16:57.8542018-05:00 | P1072: POST-BATCH-Q staff command metadata source review. Previous active row was PBN-0136/PBF-061. Public APIs, command names, access levels, namespaces, type names, file locations, project files, XML/config, serialization layout, and staff/player workflow semantics were preserved.
A1073: RB-05664 | B1073: P10-F05664 | C1073: Staff tooling | D1073: Static Gump Tool | E1073: Data/Scripts/Custom/StaffTools/StaticGumpTool/StaticGump(Alternative).cs | F1073: Ready | G1073: Fixed | H1073: POST-BATCH-Q | I1073: PBQ-0004 | J1073: Fixed | K1073: Added shared Static Gump Tool command mobile guard before closing or sending staff gumps. | L1073: docs/codebase-audit/outputs/post-batch-q-staff-command-metadata-source-review.csv | M1073: POST-BATCH-N lane=POST-BATCH-N-STAFF-COMMAND-METADATA; FileProofStatus=PathNeedsReview; Command=; Access=; L18; Registration=CommandSystem.Register(; CurrentRegistrationLine=18; CurrentCommand=STool; CurrentAccess=AccessLevel.GameMaster; CurrentHandler=OzThothsStatic_OnCommand; CurrentRegistration=CommandSystem.Register( "STool", AccessLevel.GameMaster, new CommandEventHandler(OzThothsStatic_OnCommand) );; POST-BATCH-Q direct source review=StaticGumpCommandGuardFixed | N1073: Pending: fix: harden staff command metadata queue | O1073: 2026-06-14T16:16:57.8542018-05:00 | P1073: POST-BATCH-Q staff command metadata source review. Previous active row was PBN-0137/PBF-062. Public APIs, command names, access levels, namespaces, type names, file locations, project files, XML/config, serialization layout, and staff/player workflow semantics were preserved.
A1074: RB-05665 | B1074: P10-F05665 | C1074: Staff tooling | D1074: Static Gump Tool | E1074: Data/Scripts/Custom/StaffTools/StaticGumpTool/StaticGump(Alternative).cs | F1074: Ready | G1074: Fixed | H1074: POST-BATCH-Q | I1074: PBQ-0005 | J1074: Fixed | K1074: Added shared Static Gump Tool command mobile guard before closing or sending staff gumps. | L1074: docs/codebase-audit/outputs/post-batch-q-staff-command-metadata-source-review.csv | M1074: POST-BATCH-N lane=POST-BATCH-N-STAFF-COMMAND-METADATA; FileProofStatus=PathNeedsReview; Command=; Access=; L23; Registration=CommandSystem.Register(; CurrentRegistrationLine=23; CurrentCommand=ST; CurrentAccess=AccessLevel.GameMaster; CurrentHandler=OzThothsStatic_OnCommand; CurrentRegistration=CommandSystem.Register( "ST", AccessLevel.GameMaster, new CommandEventHandler(OzThothsStatic_OnCommand) );; POST-BATCH-Q direct source review=StaticGumpCommandGuardFixed | N1074: Pending: fix: harden staff command metadata queue | O1074: 2026-06-14T16:16:57.8542018-05:00 | P1074: POST-BATCH-Q staff command metadata source review. Previous active row was PBN-0138/PBF-063. Public APIs, command names, access levels, namespaces, type names, file locations, project files, XML/config, serialization layout, and staff/player workflow semantics were preserved.
A1075: RB-05666 | B1075: P10-F05666 | C1075: Staff tooling | D1075: Static Gump Tool | E1075: Data/Scripts/Custom/StaffTools/StaticGumpTool/Side Gumps/AddAnimation.cs | F1075: Ready | G1075: Fixed | H1075: POST-BATCH-Q | I1075: PBQ-0006 | J1075: Fixed | K1075: Added shared Static Gump Tool command mobile guard before closing or sending staff gumps. | L1075: docs/codebase-audit/outputs/post-batch-q-staff-command-metadata-source-review.csv | M1075: POST-BATCH-N lane=POST-BATCH-N-STAFF-COMMAND-METADATA; FileProofStatus=PathNeedsReview; Command=; Access=; L18; Registration=CommandSystem.Register(; CurrentRegistrationLine=18; CurrentCommand=AddAnimationStatic; CurrentAccess=AccessLevel.GameMaster; CurrentHandler=AddAnimation_OnCommand; CurrentRegistration=CommandSystem.Register( "AddAnimationStatic", AccessLevel.GameMaster, new CommandEventHandler(AddAnimation_OnCommand) );; POST-BATCH-Q direct source review=StaticGumpCommandGuardFixed | N1075: Pending: fix: harden staff command metadata queue | O1075: 2026-06-14T16:16:57.8542018-05:00 | P1075: POST-BATCH-Q staff command metadata source review. Previous active row was PBN-0139/PBF-064. Public APIs, command names, access levels, namespaces, type names, file locations, project files, XML/config, serialization layout, and staff/player workflow semantics were preserved.
A1076: RB-05667 | B1076: P10-F05667 | C1076: Staff tooling | D1076: Static Gump Tool | E1076: Data/Scripts/Custom/StaffTools/StaticGumpTool/Side Gumps/AddArch.cs | F1076: Ready | G1076: Fixed | H1076: POST-BATCH-Q | I1076: PBQ-0007 | J1076: Fixed | K1076: Added shared Static Gump Tool command mobile guard before closing or sending staff gumps. | L1076: docs/codebase-audit/outputs/post-batch-q-staff-command-metadata-source-review.csv | M1076: POST-BATCH-N lane=POST-BATCH-N-STAFF-COMMAND-METADATA; FileProofStatus=PathNeedsReview; Command=; Access=; L18; Registration=CommandSystem.Register(; CurrentRegistrationLine=18; CurrentCommand=AddArch; CurrentAccess=AccessLevel.GameMaster; CurrentHandler=AddArch_OnCommand; CurrentRegistration=CommandSystem.Register( "AddArch", AccessLevel.GameMaster, new CommandEventHandler(AddArch_OnCommand) );; POST-BATCH-Q direct source review=StaticGumpCommandGuardFixed | N1076: Pending: fix: harden staff command metadata queue | O1076: 2026-06-14T16:16:57.8542018-05:00 | P1076: POST-BATCH-Q staff command metadata source review. Previous active row was PBN-0140/PBF-065. Public APIs, command names, access levels, namespaces, type names, file locations, project files, XML/config, serialization layout, and staff/player workflow semantics were preserved.
A1077: RB-05668 | B1077: P10-F05668 | C1077: Staff tooling | D1077: Static Gump Tool | E1077: Data/Scripts/Custom/StaffTools/StaticGumpTool/Side Gumps/AddCustom.cs | F1077: Ready | G1077: Fixed | H1077: POST-BATCH-Q | I1077: PBQ-0008 | J1077: Fixed | K1077: Added shared Static Gump Tool command mobile guard before closing or sending staff gumps. | L1077: docs/codebase-audit/outputs/post-batch-q-staff-command-metadata-source-review.csv | M1077: POST-BATCH-N lane=POST-BATCH-N-STAFF-COMMAND-METADATA; FileProofStatus=PathNeedsReview; Command=; Access=; L18; Registration=CommandSystem.Register(; CurrentRegistrationLine=18; CurrentCommand=AddCustomStatic; CurrentAccess=AccessLevel.GameMaster; CurrentHandler=AddCustomStatic_OnCommand; CurrentRegistration=CommandSystem.Register( "AddCustomStatic", AccessLevel.GameMaster, new CommandEventHandler(AddCustomStatic_OnCommand) );; POST-BATCH-Q direct source review=StaticGumpCommandGuardFixed | N1077: Pending: fix: harden staff command metadata queue | O1077: 2026-06-14T16:16:57.8542018-05:00 | P1077: POST-BATCH-Q staff command metadata source review. Previous active row was PBN-0141/PBF-066. Public APIs, command names, access levels, namespaces, type names, file locations, project files, XML/config, serialization layout, and staff/player workflow semantics were preserved.
A1078: RB-05669 | B1078: P10-F05669 | C1078: Staff tooling | D1078: Static Gump Tool | E1078: Data/Scripts/Custom/StaffTools/StaticGumpTool/Side Gumps/AddDeco.cs | F1078: Ready | G1078: Fixed | H1078: POST-BATCH-Q | I1078: PBQ-0009 | J1078: Fixed | K1078: Added shared Static Gump Tool command mobile guard before closing or sending staff gumps. | L1078: docs/codebase-audit/outputs/post-batch-q-staff-command-metadata-source-review.csv | M1078: POST-BATCH-N lane=POST-BATCH-N-STAFF-COMMAND-METADATA; FileProofStatus=PathNeedsReview; Command=; Access=; L18; Registration=CommandSystem.Register(; CurrentRegistrationLine=18; CurrentCommand=AddDecoStatic; CurrentAccess=AccessLevel.GameMaster; CurrentHandler=AddDecoStatic_OnCommand; CurrentRegistration=CommandSystem.Register( "AddDecoStatic", AccessLevel.GameMaster, new CommandEventHandler(AddDecoStatic_OnCommand) );; POST-BATCH-Q direct source review=StaticGumpCommandGuardFixed | N1078: Pending: fix: harden staff command metadata queue | O1078: 2026-06-14T16:16:57.8542018-05:00 | P1078: POST-BATCH-Q staff command metadata source review. Previous active row was PBN-0142/PBF-067. Public APIs, command names, access levels, namespaces, type names, file locations, project files, XML/config, serialization layout, and staff/player workflow semantics were preserved.
A1079: RB-05670 | B1079: P10-F05670 | C1079: Staff tooling | D1079: Static Gump Tool | E1079: Data/Scripts/Custom/StaffTools/StaticGumpTool/Side Gumps/AddDungeon.cs | F1079: Ready | G1079: Fixed | H1079: POST-BATCH-Q | I1079: PBQ-0010 | J1079: Fixed | K1079: Added shared Static Gump Tool command mobile guard before closing or sending staff gumps. | L1079: docs/codebase-audit/outputs/post-batch-q-staff-command-metadata-source-review.csv | M1079: POST-BATCH-N lane=POST-BATCH-N-STAFF-COMMAND-METADATA; FileProofStatus=PathNeedsReview; Command=; Access=; L18; Registration=CommandSystem.Register(; CurrentRegistrationLine=18; CurrentCommand=AddDungStatic; CurrentAccess=AccessLevel.GameMaster; CurrentHandler=AddDungStatic_OnCommand; CurrentRegistration=CommandSystem.Register( "AddDungStatic", AccessLevel.GameMaster, new CommandEventHandler(AddDungStatic_OnCommand) );; POST-BATCH-Q direct source review=StaticGumpCommandGuardFixed | N1079: Pending: fix: harden staff command metadata queue | O1079: 2026-06-14T16:16:57.8542018-05:00 | P1079: POST-BATCH-Q staff command metadata source review. Previous active row was PBN-0143/PBF-068. Public APIs, command names, access levels, namespaces, type names, file locations, project files, XML/config, serialization layout, and staff/player workflow semantics were preserved.
A1080: RB-05671 | B1080: P10-F05671 | C1080: Staff tooling | D1080: Static Gump Tool | E1080: Data/Scripts/Custom/StaffTools/StaticGumpTool/Side Gumps/addfence.cs | F1080: Ready | G1080: Fixed | H1080: POST-BATCH-Q | I1080: PBQ-0011 | J1080: Fixed | K1080: Added shared Static Gump Tool command mobile guard before closing or sending staff gumps. | L1080: docs/codebase-audit/outputs/post-batch-q-staff-command-metadata-source-review.csv | M1080: POST-BATCH-N lane=POST-BATCH-N-STAFF-COMMAND-METADATA; FileProofStatus=PathNeedsReview; Command=; Access=; L13; Registration=CommandSystem.Register(; CurrentRegistrationLine=13; CurrentCommand=AddFence; CurrentAccess=AccessLevel.GameMaster; CurrentHandler=AddFence_OnCommand; CurrentRegistration=CommandSystem.Register( "AddFence", AccessLevel.GameMaster, new CommandEventHandler(AddFence_OnCommand) );; POST-BATCH-Q direct source review=StaticGumpCommandGuardFixed | N1080: Pending: fix: harden staff command metadata queue | O1080: 2026-06-14T16:16:57.8542018-05:00 | P1080: POST-BATCH-Q staff command metadata source review. Previous active row was PBN-0144/PBF-069. Public APIs, command names, access levels, namespaces, type names, file locations, project files, XML/config, serialization layout, and staff/player workflow semantics were preserved.
A1081: RB-05672 | B1081: P10-F05672 | C1081: Staff tooling | D1081: Static Gump Tool | E1081: Data/Scripts/Custom/StaffTools/StaticGumpTool/Side Gumps/addfloor.cs | F1081: Ready | G1081: Fixed | H1081: POST-BATCH-Q | I1081: PBQ-0012 | J1081: Fixed | K1081: Added shared Static Gump Tool command mobile guard before closing or sending staff gumps. | L1081: docs/codebase-audit/outputs/post-batch-q-staff-command-metadata-source-review.csv | M1081: POST-BATCH-N lane=POST-BATCH-N-STAFF-COMMAND-METADATA; FileProofStatus=PathNeedsReview; Command=; Access=; L18; Registration=CommandSystem.Register(; CurrentRegistrationLine=18; CurrentCommand=AddFloor; CurrentAccess=AccessLevel.GameMaster; CurrentHandler=AddFloor_OnCommand; CurrentRegistration=CommandSystem.Register( "AddFloor", AccessLevel.GameMaster, new CommandEventHandler(AddFloor_OnCommand) );; POST-BATCH-Q direct source review=StaticGumpCommandGuardFixed | N1081: Pending: fix: harden staff command metadata queue | O1081: 2026-06-14T16:16:57.8542018-05:00 | P1081: POST-BATCH-Q staff command metadata source review. Previous active row was PBN-0145/PBF-070. Public APIs, command names, access levels, namespaces, type names, file locations, project files, XML/config, serialization layout, and staff/player workflow semantics were preserved.
...

Sheet Audit Dashboard
B1: POST-AUDIT | INSIGHTS DASHBOARD
B3: 2026-10-25 | FIX-09–15 code/regression complete; all three foundation batches await in-game Qwen acceptance. No deployment.
B5: RECORDS | F5: FIXED | J5: NO-CHANGE OUTCOMES | N5: DOMAIN-ONLY BLOCKERS
B6: =COUNTA('post-audit-active-backlog-statu'!$A$2:$A$6832) -> 6831 | F6: =COUNTIF('post-audit-active-backlog-statu'!$G$2:$G$6832,"Fixed") -> 957 | J6: =COUNTIF('post-audit-active-backlog-statu'!$G$2:$G$6832,"ReviewedNoChange")+COUNTIF('post-audit-active-backlog-statu'!$G$2:$G$6832,"SafeNoChange")+COUNTIF('post-audit-active-backlog-statu'!$G$2:$G$6832,"PolicyResolvedNoChange") -> 3700 | N6: =COUNTIF('post-audit-active-backlog-statu'!$G$2:$G$6832,"BlocksOnlyThisDomain") -> 7
B8: =COUNTA('Audit Analysis'!M5:M209)&" systems covered" -> 205 systems covered | F8: =TEXT(F6/B6,"0.0%")&" of all records" -> 14.0% of all records | J8: =TEXT(J6/B6,"0.0%")&" of all records" -> 54.2% of all records | N8: =TEXT(N6/B6,"0.0%")&" • scope-limited" -> 0.1% • scope-limited
B9: READOUT | Where to focus
B10: ="CONCENTRATION | "&'Audit Analysis'!F5&" + "&'Audit Analysis'!F6&" account for "&TEXT(SUM('Audit Analysis'!G5:G6)/B6,"0.0%")&" of records; prioritize these review surfaces." -> CONCENTRATION | Runtime hooks + Save compatibility account for 44.0% of records; prioritize these review surfaces.
B11: ="OUTCOMES | "&TEXT(J6/B6,"0.0%")&" are explicit no-change outcomes; "&TEXT(F6/B6,"0.0%")&" are Fixed. These are dispositions, not a closure rate." -> OUTCOMES | 54.2% are explicit no-change outcomes; 14.0% are Fixed. These are dispositions, not a closure rate.
B12: ="APPROVAL GATES | "&COUNTIF('post-audit-active-backlog-statu'!$J$2:$J$6832,"BlockedForReorganizationOnly")&" move/reorganization + "&COUNTIF('post-audit-active-backlog-statu'!$J$2:$J$6832,"BlockedForSerializerMigrationOnly")&" serializer-migration blockers. See linked records below." -> APPROVAL GATES | 6 move/reorganization + 1 serializer-migration blockers. See linked records below.
B13: ="SNAPSHOT TIMING | "&TEXT(SUMIFS('Audit Analysis'!U5:U16,'Audit Analysis'!T5:T16,"<"&DATE(2026,10,1)),"#,##0")&" records last updated before October; latest source date "&TEXT(MAX('Audit Analysis'!T5:T16),"mmm d, yyyy")&"." -> SNAPSHOT TIMING | 6,813 records last updated before October; latest source date Oct 25, 2026.
B14: ="DATA CHECKS | "&IF(COUNTIF('Audit Analysis'!C19:C27,"REVIEW")=0,"All 9 reconciliation / completeness checks pass.",COUNTIF('Audit Analysis'!C19:C27,"REVIEW")&" checks require review; see Audit Analysis.") -> DATA CHECKS | All 9 reconciliation / completeness checks pass.
B52: APPROVAL GATES | Click a record to inspect the source
B53: Blockers apply only to the named domain; ordinary maintenance may proceed within the source-defined boundaries.
B55: =HYPERLINK("#'post-audit-active-backlog-statu'!A1620",'post-audit-active-backlog-statu'!A1620&" | "&'post-audit-active-backlog-statu'!D1620&" | "&'post-audit-active-backlog-statu'!J1620) -> RB-06806 | PvP Consent | BlockedForReorganizationOnly
B56: =HYPERLINK("#'post-audit-active-backlog-statu'!A1622",'post-audit-active-backlog-statu'!A1622&" | "&'post-audit-active-backlog-statu'!D1622&" | "&'post-audit-active-backlog-statu'!J1622) -> RB-06808 | Invasion | BlockedForReorganizationOnly
B57: =HYPERLINK("#'post-audit-active-backlog-statu'!A1623",'post-audit-active-backlog-statu'!A1623&" | "&'post-audit-active-backlog-statu'!D1623&" | "&'post-audit-active-backlog-statu'!J1623) -> RB-06813 | XMLSpawner | BlockedForReorganizationOnly
B58: =HYPERLINK("#'post-audit-active-backlog-statu'!A1624",'post-audit-active-backlog-statu'!A1624&" | "&'post-audit-active-backlog-statu'!D1624&" | "&'post-audit-active-backlog-statu'!J1624) -> RB-06807 | Government | BlockedForReorganizationOnly
B59: =HYPERLINK("#'post-audit-active-backlog-statu'!A1625",'post-audit-active-backlog-statu'!A1625&" | "&'post-audit-active-backlog-statu'!D1625&" | "&'post-audit-active-backlog-statu'!J1625) -> RB-06803 | Offline Skill Training | BlockedForReorganizationOnly
B60: =HYPERLINK("#'post-audit-active-backlog-statu'!A1626",'post-audit-active-backlog-statu'!A1626&" | "&'post-audit-active-backlog-statu'!D1626&" | "&'post-audit-active-backlog-statu'!J1626) -> RB-06814 | Homestead | BlockedForReorganizationOnly
B61: =HYPERLINK("#'post-audit-active-backlog-statu'!A2137",'post-audit-active-backlog-statu'!A2137&" | "&'post-audit-active-backlog-statu'!D2137&" | "&'post-audit-active-backlog-statu'!J2137) -> RB-00724 | Items:Houses | BlockedForSerializerMigrationOnly
B63: INTERPRETATION & MAINTENANCE
B64: No-change = ReviewedNoChange + SafeNoChange + PolicyResolvedNoChange. Fixed uses ActiveStatus exactly; no closure rate is inferred.
B65: IntentionalLegacy, AcceptedFence, Documented and FalsePositive remain separate outcomes; a record is not necessarily a unique file.
B66: Update chart counts each record’s last timestamp—not daily throughput. Dates use the written calendar date; numeric Excel dates are included.
B67: Source: post-audit-active-backlog-status.csv | 6,831 records. Repair reports distinguish local verification from deployment.
B68: Audit Analysis contains all 17 categories, 205 systems, status definitions, history comparisons and visible quality checks. Source records are untouched.
B70: Workbook: post-audit-active-backlog-statu | Dashboard built 2026-10-17 | No owner, SLA or creation date supplied; no overdue metric inferred.

Sheet Audit Analysis
A1: AUDIT ANALYSIS | Live source-linked summaries
A2: 2026-10-25 | Native formulas, charts and filters preserved; counts and cached results reconciled against the CSV.
A4: Active status | B4: Records | C4: Share | D4: Interpretation | F4: Category | G4: Records | H4: Fixed | I4: No change | J4: Domain blockers | K4: Fixed share | M4: System | N4: Records | O4: Fixed | P4: No change | Q4: Domain blockers | R4: Fixed share | T4: Last update date | U4: Records
B5: =COUNTIF('post-audit-active-backlog-statu'!$G$2:$G$6832,A5) -> 2650 | C5: =B5/'Audit Dashboard'!$B$6 -> 0.38793734 | D5: Reviewed; no change | F5: Runtime hooks | G5: =COUNTIF('post-audit-active-backlog-statu'!$C$2:$C$6832,F5) -> 1557 | H5: =COUNTIFS('post-audit-active-backlog-statu'!$C$2:$C$6832,F5,'post-audit-active-backlog-statu'!$G$2:$G$6832,"Fixed") -> 252 | I5: =COUNTIFS('post-audit-active-backlog-statu'!$C$2:$C$6832,F5,'post-audit-active-backlog-statu'!$G$2:$G$6832,"ReviewedNoChange")+COUNTIFS('post-audit-active-backlog-statu'!$C$2:$C$6832,F5,'post-audit-active-backlog-statu'!$G$2:$G$6832,"SafeNoChange")+COUNTIFS('post-audit-active-backlog-statu'!$C$2:$C$6832,F5,'post-audit-active-backlog-statu'!$G$2:$G$6832,"PolicyResolvedNoChange") -> 1284 | J5: =COUNTIFS('post-audit-active-backlog-statu'!$C$2:$C$6832,F5,'post-audit-active-backlog-statu'!$G$2:$G$6832,"BlocksOnlyThisDomain") -> 0 | K5: =H5/G5 -> 0.16184971 | M5: Items:Magical | N5: =COUNTIF('post-audit-active-backlog-statu'!$D$2:$D$6832,M5) -> 999 | O5: =COUNTIFS('post-audit-active-backlog-statu'!$D$2:$D$6832,M5,'post-audit-active-backlog-statu'!$G$2:$G$6832,"Fixed") -> 8 | P5: =COUNTIFS('post-audit-active-backlog-statu'!$D$2:$D$6832,M5,'post-audit-active-backlog-statu'!$G$2:$G$6832,"ReviewedNoChange")+COUNTIFS('post-audit-active-backlog-statu'!$D$2:$D$6832,M5,'post-audit-active-backlog-statu'!$G$2:$G$6832,"SafeNoChange")+COUNTIFS('post-audit-active-backlog-statu'!$D$2:$D$6832,M5,'post-audit-active-backlog-statu'!$G$2:$G$6832,"PolicyResolvedNoChange") -> 216 | Q5: =COUNTIFS('post-audit-active-backlog-statu'!$D$2:$D$6832,M5,'post-audit-active-backlog-statu'!$G$2:$G$6832,"BlocksOnlyThisDomain") -> 0 | R5: =O5/N5 -> 0.008008008 | T5: 46179 | U5: =COUNTIF('post-audit-active-backlog-statu'!$O$2:$O$6832,TEXT(T5,"yyyy-mm-dd")&"*")+COUNTIFS('post-audit-active-backlog-statu'!$O$2:$O$6832,">="&T5,'post-audit-active-backlog-statu'!$O$2:$O$6832,"<"&T5+1) -> 203 | A5: ReviewedNoChange
B6: =COUNTIF('post-audit-active-backlog-statu'!$G$2:$G$6832,A6) -> 1395 | C6: =B6/'Audit Dashboard'!$B$6 -> 0.20421607 | D6: Legacy retained intentionally | F6: Save compatibility | G6: =COUNTIF('post-audit-active-backlog-statu'!$C$2:$C$6832,F6) -> 1446 | H6: =COUNTIFS('post-audit-active-backlog-statu'!$C$2:$C$6832,F6,'post-audit-active-backlog-statu'!$G$2:$G$6832,"Fixed") -> 1 | I6: =COUNTIFS('post-audit-active-backlog-statu'!$C$2:$C$6832,F6,'post-audit-active-backlog-statu'!$G$2:$G$6832,"ReviewedNoChange")+COUNTIFS('post-audit-active-backlog-statu'!$C$2:$C$6832,F6,'post-audit-active-backlog-statu'!$G$2:$G$6832,"SafeNoChange")+COUNTIFS('post-audit-active-backlog-statu'!$C$2:$C$6832,F6,'post-audit-active-backlog-statu'!$G$2:$G$6832,"PolicyResolvedNoChange") -> 500 | J6: =COUNTIFS('post-audit-active-backlog-statu'!$C$2:$C$6832,F6,'post-audit-active-backlog-statu'!$G$2:$G$6832,"BlocksOnlyThisDomain") -> 1 | K6: =H6/G6 -> 0.00069156293 | M6: System:Commands | N6: =COUNTIF('post-audit-active-backlog-statu'!$D$2:$D$6832,M6) -> 424 | O6: =COUNTIFS('post-audit-active-backlog-statu'!$D$2:$D$6832,M6,'post-audit-active-backlog-statu'!$G$2:$G$6832,"Fixed") -> 21 | P6: =COUNTIFS('post-audit-active-backlog-statu'!$D$2:$D$6832,M6,'post-audit-active-backlog-statu'!$G$2:$G$6832,"ReviewedNoChange")+COUNTIFS('post-audit-active-backlog-statu'!$D$2:$D$6832,M6,'post-audit-active-backlog-statu'!$G$2:$G$6832,"SafeNoChange")+COUNTIFS('post-audit-active-backlog-statu'!$D$2:$D$6832,M6,'post-audit-active-backlog-statu'!$G$2:$G$6832,"PolicyResolvedNoChange") -> 366 | Q6: =COUNTIFS('post-audit-active-backlog-statu'!$D$2:$D$6832,M6,'post-audit-active-backlog-statu'!$G$2:$G$6832,"BlocksOnlyThisDomain") -> 0 | R6: =O6/N6 -> 0.049528302 | T6: 46180 | U6: =COUNTIF('post-audit-active-backlog-statu'!$O$2:$O$6832,TEXT(T6,"yyyy-mm-dd")&"*")+COUNTIFS('post-audit-active-backlog-statu'!$O$2:$O$6832,">="&T6,'post-audit-active-backlog-statu'!$O$2:$O$6832,"<"&T6+1) -> 92 | A6: IntentionalLegacy
B7: =COUNTIF('post-audit-active-backlog-statu'!$G$2:$G$6832,A7) -> 957 | C7: =B7/'Audit Dashboard'!$B$6 -> 0.14009662 | D7: Fixed per active status | F7: Gump guards | G7: =COUNTIF('post-audit-active-backlog-statu'!$C$2:$C$6832,F7) -> 939 | H7: =COUNTIFS('post-audit-active-backlog-statu'!$C$2:$C$6832,F7,'post-audit-active-backlog-statu'!$G$2:$G$6832,"Fixed") -> 111 | I7: =COUNTIFS('post-audit-active-backlog-statu'!$C$2:$C$6832,F7,'post-audit-active-backlog-statu'!$G$2:$G$6832,"ReviewedNoChange")+COUNTIFS('post-audit-active-backlog-statu'!$C$2:$C$6832,F7,'post-audit-active-backlog-statu'!$G$2:$G$6832,"SafeNoChange")+COUNTIFS('post-audit-active-backlog-statu'!$C$2:$C$6832,F7,'post-audit-active-backlog-statu'!$G$2:$G$6832,"PolicyResolvedNoChange") -> 820 | J7: =COUNTIFS('post-audit-active-backlog-statu'!$C$2:$C$6832,F7,'post-audit-active-backlog-statu'!$G$2:$G$6832,"BlocksOnlyThisDomain") -> 0 | K7: =H7/G7 -> 0.11821086 | M7: Static Gump Tool | N7: =COUNTIF('post-audit-active-backlog-statu'!$D$2:$D$6832,M7) -> 355 | O7: =COUNTIFS('post-audit-active-backlog-statu'!$D$2:$D$6832,M7,'post-audit-active-backlog-statu'!$G$2:$G$6832,"Fixed") -> 23 | P7: =COUNTIFS('post-audit-active-backlog-statu'!$D$2:$D$6832,M7,'post-audit-active-backlog-statu'!$G$2:$G$6832,"ReviewedNoChange")+COUNTIFS('post-audit-active-backlog-statu'!$D$2:$D$6832,M7,'post-audit-active-backlog-statu'!$G$2:$G$6832,"SafeNoChange")+COUNTIFS('post-audit-active-backlog-statu'!$D$2:$D$6832,M7,'post-audit-active-backlog-statu'!$G$2:$G$6832,"PolicyResolvedNoChange") -> 322 | Q7: =COUNTIFS('post-audit-active-backlog-statu'!$D$2:$D$6832,M7,'post-audit-active-backlog-statu'!$G$2:$G$6832,"BlocksOnlyThisDomain") -> 0 | R7: =O7/N7 -> 0.064788732 | T7: 46181 | U7: =COUNTIF('post-audit-active-backlog-statu'!$O$2:$O$6832,TEXT(T7,"yyyy-mm-dd")&"*")+COUNTIFS('post-audit-active-backlog-statu'!$O$2:$O$6832,">="&T7,'post-audit-active-backlog-statu'!$O$2:$O$6832,"<"&T7+1) -> 439 | A7: Fixed
B8: =COUNTIF('post-audit-active-backlog-statu'!$G$2:$G$6832,A8) -> 678 | C8: =B8/'Audit Dashboard'!$B$6 -> 0.099253404 | D8: Safe; no change | F8: Legacy compatibility | G8: =COUNTIF('post-audit-active-backlog-statu'!$C$2:$C$6832,F8) -> 659 | H8: =COUNTIFS('post-audit-active-backlog-statu'!$C$2:$C$6832,F8,'post-audit-active-backlog-statu'!$G$2:$G$6832,"Fixed") -> 0 | I8: =COUNTIFS('post-audit-active-backlog-statu'!$C$2:$C$6832,F8,'post-audit-active-backlog-statu'!$G$2:$G$6832,"ReviewedNoChange")+COUNTIFS('post-audit-active-backlog-statu'!$C$2:$C$6832,F8,'post-audit-active-backlog-statu'!$G$2:$G$6832,"SafeNoChange")+COUNTIFS('post-audit-active-backlog-statu'!$C$2:$C$6832,F8,'post-audit-active-backlog-statu'!$G$2:$G$6832,"PolicyResolvedNoChange") -> 0 | J8: =COUNTIFS('post-audit-active-backlog-statu'!$C$2:$C$6832,F8,'post-audit-active-backlog-statu'!$G$2:$G$6832,"BlocksOnlyThisDomain") -> 0 | K8: =H8/G8 -> 0 | M8: XMLSpawner | N8: =COUNTIF('post-audit-active-backlog-statu'!$D$2:$D$6832,M8) -> 284 | O8: =COUNTIFS('post-audit-active-backlog-statu'!$D$2:$D$6832,M8,'post-audit-active-backlog-statu'!$G$2:$G$6832,"Fixed") -> 72 | P8: =COUNTIFS('post-audit-active-backlog-statu'!$D$2:$D$6832,M8,'post-audit-active-backlog-statu'!$G$2:$G$6832,"ReviewedNoChange")+COUNTIFS('post-audit-active-backlog-statu'!$D$2:$D$6832,M8,'post-audit-active-backlog-statu'!$G$2:$G$6832,"SafeNoChange")+COUNTIFS('post-audit-active-backlog-statu'!$D$2:$D$6832,M8,'post-audit-active-backlog-statu'!$G$2:$G$6832,"PolicyResolvedNoChange") -> 183 | Q8: =COUNTIFS('post-audit-active-backlog-statu'!$D$2:$D$6832,M8,'post-audit-active-backlog-statu'!$G$2:$G$6832,"BlocksOnlyThisDomain") -> 1 | R8: =O8/N8 -> 0.25352113 | T8: 46182 | U8: =COUNTIF('post-audit-active-backlog-statu'!$O$2:$O$6832,TEXT(T8,"yyyy-mm-dd")&"*")+COUNTIFS('post-audit-active-backlog-statu'!$O$2:$O$6832,">="&T8,'post-audit-active-backlog-statu'!$O$2:$O$6832,"<"&T8+1) -> 274 | A8: SafeNoChange
B9: =COUNTIF('post-audit-active-backlog-statu'!$G$2:$G$6832,A9) -> 372 | C9: =B9/'Audit Dashboard'!$B$6 -> 0.05445762 | D9: Policy resolved; no change | F9: Command access | G9: =COUNTIF('post-audit-active-backlog-statu'!$C$2:$C$6832,F9) -> 499 | H9: =COUNTIFS('post-audit-active-backlog-statu'!$C$2:$C$6832,F9,'post-audit-active-backlog-statu'!$G$2:$G$6832,"Fixed") -> 0 | I9: =COUNTIFS('post-audit-active-backlog-statu'!$C$2:$C$6832,F9,'post-audit-active-backlog-statu'!$G$2:$G$6832,"ReviewedNoChange")+COUNTIFS('post-audit-active-backlog-statu'!$C$2:$C$6832,F9,'post-audit-active-backlog-statu'!$G$2:$G$6832,"SafeNoChange")+COUNTIFS('post-audit-active-backlog-statu'!$C$2:$C$6832,F9,'post-audit-active-backlog-statu'!$G$2:$G$6832,"PolicyResolvedNoChange") -> 484 | J9: =COUNTIFS('post-audit-active-backlog-statu'!$C$2:$C$6832,F9,'post-audit-active-backlog-statu'!$G$2:$G$6832,"BlocksOnlyThisDomain") -> 0 | K9: =H9/G9 -> 0 | M9: Items:Special | N9: =COUNTIF('post-audit-active-backlog-statu'!$D$2:$D$6832,M9) -> 282 | O9: =COUNTIFS('post-audit-active-backlog-statu'!$D$2:$D$6832,M9,'post-audit-active-backlog-statu'!$G$2:$G$6832,"Fixed") -> 5 | P9: =COUNTIFS('post-audit-active-backlog-statu'!$D$2:$D$6832,M9,'post-audit-active-backlog-statu'!$G$2:$G$6832,"ReviewedNoChange")+COUNTIFS('post-audit-active-backlog-statu'!$D$2:$D$6832,M9,'post-audit-active-backlog-statu'!$G$2:$G$6832,"SafeNoChange")+COUNTIFS('post-audit-active-backlog-statu'!$D$2:$D$6832,M9,'post-audit-active-backlog-statu'!$G$2:$G$6832,"PolicyResolvedNoChange") -> 72 | Q9: =COUNTIFS('post-audit-active-backlog-statu'!$D$2:$D$6832,M9,'post-audit-active-backlog-statu'!$G$2:$G$6832,"BlocksOnlyThisDomain") -> 0 | R9: =O9/N9 -> 0.017730496 | T9: 46186 | U9: =COUNTIF('post-audit-active-backlog-statu'!$O$2:$O$6832,TEXT(T9,"yyyy-mm-dd")&"*")+COUNTIFS('post-audit-active-backlog-statu'!$O$2:$O$6832,">="&T9,'post-audit-active-backlog-statu'!$O$2:$O$6832,"<"&T9+1) -> 86 | A9: PolicyResolvedNoChange
B10: =COUNTIF('post-audit-active-backlog-statu'!$G$2:$G$6832,A10) -> 352 | C10: =B10/'Audit Dashboard'!$B$6 -> 0.051529791 | D10: Documented outcome | F10: Pooled enumerables | G10: =COUNTIF('post-audit-active-backlog-statu'!$C$2:$C$6832,F10) -> 408 | H10: =COUNTIFS('post-audit-active-backlog-statu'!$C$2:$C$6832,F10,'post-audit-active-backlog-statu'!$G$2:$G$6832,"Fixed") -> 406 | I10: =COUNTIFS('post-audit-active-backlog-statu'!$C$2:$C$6832,F10,'post-audit-active-backlog-statu'!$G$2:$G$6832,"ReviewedNoChange")+COUNTIFS('post-audit-active-backlog-statu'!$C$2:$C$6832,F10,'post-audit-active-backlog-statu'!$G$2:$G$6832,"SafeNoChange")+COUNTIFS('post-audit-active-backlog-statu'!$C$2:$C$6832,F10,'post-audit-active-backlog-statu'!$G$2:$G$6832,"PolicyResolvedNoChange") -> 0 | J10: =COUNTIFS('post-audit-active-backlog-statu'!$C$2:$C$6832,F10,'post-audit-active-backlog-statu'!$G$2:$G$6832,"BlocksOnlyThisDomain") -> 0 | K10: =H10/G10 -> 0.99509804 | M10: System:Misc | N10: =COUNTIF('post-audit-active-backlog-statu'!$D$2:$D$6832,M10) -> 278 | O10: =COUNTIFS('post-audit-active-backlog-statu'!$D$2:$D$6832,M10,'post-audit-active-backlog-statu'!$G$2:$G$6832,"Fixed") -> 69 | P10: =COUNTIFS('post-audit-active-backlog-statu'!$D$2:$D$6832,M10,'post-audit-active-backlog-statu'!$G$2:$G$6832,"ReviewedNoChange")+COUNTIFS('post-audit-active-backlog-statu'!$D$2:$D$6832,M10,'post-audit-active-backlog-statu'!$G$2:$G$6832,"SafeNoChange")+COUNTIFS('post-audit-active-backlog-statu'!$D$2:$D$6832,M10,'post-audit-active-backlog-statu'!$G$2:$G$6832,"PolicyResolvedNoChange") -> 65 | Q10: =COUNTIFS('post-audit-active-backlog-statu'!$D$2:$D$6832,M10,'post-audit-active-backlog-statu'!$G$2:$G$6832,"BlocksOnlyThisDomain") -> 0 | R10: =O10/N10 -> 0.24820144 | T10: 46187 | U10: =COUNTIF('post-audit-active-backlog-statu'!$O$2:$O$6832,TEXT(T10,"yyyy-mm-dd")&"*")+COUNTIFS('post-audit-active-backlog-statu'!$O$2:$O$6832,">="&T10,'post-audit-active-backlog-statu'!$O$2:$O$6832,"<"&T10+1) -> 5170 | A10: Documented
B11: =COUNTIF('post-audit-active-backlog-statu'!$G$2:$G$6832,A11) -> 330 | C11: =B11/'Audit Dashboard'!$B$6 -> 0.048309179 | D11: False positive | F11: PlayerMobile coupling | G11: =COUNTIF('post-audit-active-backlog-statu'!$C$2:$C$6832,F11) -> 394 | H11: =COUNTIFS('post-audit-active-backlog-statu'!$C$2:$C$6832,F11,'post-audit-active-backlog-statu'!$G$2:$G$6832,"Fixed") -> 0 | I11: =COUNTIFS('post-audit-active-backlog-statu'!$C$2:$C$6832,F11,'post-audit-active-backlog-statu'!$G$2:$G$6832,"ReviewedNoChange")+COUNTIFS('post-audit-active-backlog-statu'!$C$2:$C$6832,F11,'post-audit-active-backlog-statu'!$G$2:$G$6832,"SafeNoChange")+COUNTIFS('post-audit-active-backlog-statu'!$C$2:$C$6832,F11,'post-audit-active-backlog-statu'!$G$2:$G$6832,"PolicyResolvedNoChange") -> 392 | J11: =COUNTIFS('post-audit-active-backlog-statu'!$C$2:$C$6832,F11,'post-audit-active-backlog-statu'!$G$2:$G$6832,"BlocksOnlyThisDomain") -> 0 | K11: =H11/G11 -> 0 | M11: Regions | N11: =COUNTIF('post-audit-active-backlog-statu'!$D$2:$D$6832,M11) -> 259 | O11: =COUNTIFS('post-audit-active-backlog-statu'!$D$2:$D$6832,M11,'post-audit-active-backlog-statu'!$G$2:$G$6832,"Fixed") -> 11 | P11: =COUNTIFS('post-audit-active-backlog-statu'!$D$2:$D$6832,M11,'post-audit-active-backlog-statu'!$G$2:$G$6832,"ReviewedNoChange")+COUNTIFS('post-audit-active-backlog-statu'!$D$2:$D$6832,M11,'post-audit-active-backlog-statu'!$G$2:$G$6832,"SafeNoChange")+COUNTIFS('post-audit-active-backlog-statu'!$D$2:$D$6832,M11,'post-audit-active-backlog-statu'!$G$2:$G$6832,"PolicyResolvedNoChange") -> 220 | Q11: =COUNTIFS('post-audit-active-backlog-statu'!$D$2:$D$6832,M11,'post-audit-active-backlog-statu'!$G$2:$G$6832,"BlocksOnlyThisDomain") -> 0 | R11: =O11/N11 -> 0.042471042 | T11: 46188 | U11: =COUNTIF('post-audit-active-backlog-statu'!$O$2:$O$6832,TEXT(T11,"yyyy-mm-dd")&"*")+COUNTIFS('post-audit-active-backlog-statu'!$O$2:$O$6832,">="&T11,'post-audit-active-backlog-statu'!$O$2:$O$6832,"<"&T11+1) -> 549 | A11: FalsePositive
B12: =COUNTIF('post-audit-active-backlog-statu'!$G$2:$G$6832,A12) -> 83 | C12: =B12/'Audit Dashboard'!$B$6 -> 0.01215049 | D12: Accepted boundary/fence | F12: XML/config schemas | G12: =COUNTIF('post-audit-active-backlog-statu'!$C$2:$C$6832,F12) -> 232 | H12: =COUNTIFS('post-audit-active-backlog-statu'!$C$2:$C$6832,F12,'post-audit-active-backlog-statu'!$G$2:$G$6832,"Fixed") -> 0 | I12: =COUNTIFS('post-audit-active-backlog-statu'!$C$2:$C$6832,F12,'post-audit-active-backlog-statu'!$G$2:$G$6832,"ReviewedNoChange")+COUNTIFS('post-audit-active-backlog-statu'!$C$2:$C$6832,F12,'post-audit-active-backlog-statu'!$G$2:$G$6832,"SafeNoChange")+COUNTIFS('post-audit-active-backlog-statu'!$C$2:$C$6832,F12,'post-audit-active-backlog-statu'!$G$2:$G$6832,"PolicyResolvedNoChange") -> 0 | J12: =COUNTIFS('post-audit-active-backlog-statu'!$C$2:$C$6832,F12,'post-audit-active-backlog-statu'!$G$2:$G$6832,"BlocksOnlyThisDomain") -> 0 | K12: =H12/G12 -> 0 | M12: Government | N12: =COUNTIF('post-audit-active-backlog-statu'!$D$2:$D$6832,M12) -> 252 | O12: =COUNTIFS('post-audit-active-backlog-statu'!$D$2:$D$6832,M12,'post-audit-active-backlog-statu'!$G$2:$G$6832,"Fixed") -> 8 | P12: =COUNTIFS('post-audit-active-backlog-statu'!$D$2:$D$6832,M12,'post-audit-active-backlog-statu'!$G$2:$G$6832,"ReviewedNoChange")+COUNTIFS('post-audit-active-backlog-statu'!$D$2:$D$6832,M12,'post-audit-active-backlog-statu'!$G$2:$G$6832,"SafeNoChange")+COUNTIFS('post-audit-active-backlog-statu'!$D$2:$D$6832,M12,'post-audit-active-backlog-statu'!$G$2:$G$6832,"PolicyResolvedNoChange") -> 237 | Q12: =COUNTIFS('post-audit-active-backlog-statu'!$D$2:$D$6832,M12,'post-audit-active-backlog-statu'!$G$2:$G$6832,"BlocksOnlyThisDomain") -> 1 | R12: =O12/N12 -> 0.031746032 | T12: 46312 | U12: =COUNTIF('post-audit-active-backlog-statu'!$O$2:$O$6832,TEXT(T12,"yyyy-mm-dd")&"*")+COUNTIFS('post-audit-active-backlog-statu'!$O$2:$O$6832,">="&T12,'post-audit-active-backlog-statu'!$O$2:$O$6832,"<"&T12+1) -> 6 | A12: AcceptedFence
B13: =COUNTIF('post-audit-active-backlog-statu'!$G$2:$G$6832,A13) -> 7 | C13: =B13/'Audit Dashboard'!$B$6 -> 0.0010247402 | D13: Domain-specific blocker | F13: Documentation contradictions | G13: =COUNTIF('post-audit-active-backlog-statu'!$C$2:$C$6832,F13) -> 158 | H13: =COUNTIFS('post-audit-active-backlog-statu'!$C$2:$C$6832,F13,'post-audit-active-backlog-statu'!$G$2:$G$6832,"Fixed") -> 25 | I13: =COUNTIFS('post-audit-active-backlog-statu'!$C$2:$C$6832,F13,'post-audit-active-backlog-statu'!$G$2:$G$6832,"ReviewedNoChange")+COUNTIFS('post-audit-active-backlog-statu'!$C$2:$C$6832,F13,'post-audit-active-backlog-statu'!$G$2:$G$6832,"SafeNoChange")+COUNTIFS('post-audit-active-backlog-statu'!$C$2:$C$6832,F13,'post-audit-active-backlog-statu'!$G$2:$G$6832,"PolicyResolvedNoChange") -> 7 | J13: =COUNTIFS('post-audit-active-backlog-statu'!$C$2:$C$6832,F13,'post-audit-active-backlog-statu'!$G$2:$G$6832,"BlocksOnlyThisDomain") -> 0 | K13: =H13/G13 -> 0.15822785 | M13: Invasion | N13: =COUNTIF('post-audit-active-backlog-statu'!$D$2:$D$6832,M13) -> 212 | O13: =COUNTIFS('post-audit-active-backlog-statu'!$D$2:$D$6832,M13,'post-audit-active-backlog-statu'!$G$2:$G$6832,"Fixed") -> 1 | P13: =COUNTIFS('post-audit-active-backlog-statu'!$D$2:$D$6832,M13,'post-audit-active-backlog-statu'!$G$2:$G$6832,"ReviewedNoChange")+COUNTIFS('post-audit-active-backlog-statu'!$D$2:$D$6832,M13,'post-audit-active-backlog-statu'!$G$2:$G$6832,"SafeNoChange")+COUNTIFS('post-audit-active-backlog-statu'!$D$2:$D$6832,M13,'post-audit-active-backlog-statu'!$G$2:$G$6832,"PolicyResolvedNoChange") -> 200 | Q13: =COUNTIFS('post-audit-active-backlog-statu'!$D$2:$D$6832,M13,'post-audit-active-backlog-statu'!$G$2:$G$6832,"BlocksOnlyThisDomain") -> 1 | R13: =O13/N13 -> 0.0047169811 | A13: BlocksOnlyThisDomain | T13: 46313 | U13: =COUNTIF('post-audit-active-backlog-statu'!$O$2:$O$6832,TEXT(T13,"yyyy-mm-dd")&"*")+COUNTIFS('post-audit-active-backlog-statu'!$O$2:$O$6832,">="&T13,'post-audit-active-backlog-statu'!$O$2:$O$6832,"<"&T13+1) -> 1
F14: WriteReadAlignment | B14: =COUNTIF('post-audit-active-backlog-statu'!$G$2:$G$6832,A14) -> 0 | C14: =B14/'Audit Dashboard'!B6 -> 0 | G14: =COUNTIF('post-audit-active-backlog-statu'!$C$2:$C$6832,F14) -> 153 | H14: =COUNTIFS('post-audit-active-backlog-statu'!$C$2:$C$6832,F14,'post-audit-active-backlog-statu'!$G$2:$G$6832,"Fixed") -> 4 | I14: =COUNTIFS('post-audit-active-backlog-statu'!$C$2:$C$6832,F14,'post-audit-active-backlog-statu'!$G$2:$G$6832,"ReviewedNoChange")+COUNTIFS('post-audit-active-backlog-statu'!$C$2:$C$6832,F14,'post-audit-active-backlog-statu'!$G$2:$G$6832,"SafeNoChange")+COUNTIFS('post-audit-active-backlog-statu'!$C$2:$C$6832,F14,'post-audit-active-backlog-statu'!$G$2:$G$6832,"PolicyResolvedNoChange") -> 101 | J14: =COUNTIFS('post-audit-active-backlog-statu'!$C$2:$C$6832,F14,'post-audit-active-backlog-statu'!$G$2:$G$6832,"BlocksOnlyThisDomain") -> 0 | K14: =H14/G14 -> 0.026143791 | M14: Items:Misc | N14: =COUNTIF('post-audit-active-backlog-statu'!$D$2:$D$6832,M14) -> 207 | O14: =COUNTIFS('post-audit-active-backlog-statu'!$D$2:$D$6832,M14,'post-audit-active-backlog-statu'!$G$2:$G$6832,"Fixed") -> 32 | P14: =COUNTIFS('post-audit-active-backlog-statu'!$D$2:$D$6832,M14,'post-audit-active-backlog-statu'!$G$2:$G$6832,"ReviewedNoChange")+COUNTIFS('post-audit-active-backlog-statu'!$D$2:$D$6832,M14,'post-audit-active-backlog-statu'!$G$2:$G$6832,"SafeNoChange")+COUNTIFS('post-audit-active-backlog-statu'!$D$2:$D$6832,M14,'post-audit-active-backlog-statu'!$G$2:$G$6832,"PolicyResolvedNoChange") -> 127 | Q14: =COUNTIFS('post-audit-active-backlog-statu'!$D$2:$D$6832,M14,'post-audit-active-backlog-statu'!$G$2:$G$6832,"BlocksOnlyThisDomain") -> 0 | R14: =O14/N14 -> 0.15458937 | T14: 46314 | U14: =COUNTIF('post-audit-active-backlog-statu'!$O$2:$O$6832,TEXT(T14,"yyyy-mm-dd")&"*")+COUNTIFS('post-audit-active-backlog-statu'!$O$2:$O$6832,">="&T14,'post-audit-active-backlog-statu'!$O$2:$O$6832,"<"&T14+1) -> 2 | A14: Deferred
A15: Open | B15: =COUNTIF('post-audit-active-backlog-statu'!$G$2:$G$6832,A15) -> 7 | C15: =B15/'Audit Dashboard'!B6 -> 0.0010247402 | D15: Work or required acceptance remains open | F15: Staff tooling | G15: =COUNTIF('post-audit-active-backlog-statu'!$C$2:$C$6832,F15) -> 125 | H15: =COUNTIFS('post-audit-active-backlog-statu'!$C$2:$C$6832,F15,'post-audit-active-backlog-statu'!$G$2:$G$6832,"Fixed") -> 86 | I15: =COUNTIFS('post-audit-active-backlog-statu'!$C$2:$C$6832,F15,'post-audit-active-backlog-statu'!$G$2:$G$6832,"ReviewedNoChange")+COUNTIFS('post-audit-active-backlog-statu'!$C$2:$C$6832,F15,'post-audit-active-backlog-statu'!$G$2:$G$6832,"SafeNoChange")+COUNTIFS('post-audit-active-backlog-statu'!$C$2:$C$6832,F15,'post-audit-active-backlog-statu'!$G$2:$G$6832,"PolicyResolvedNoChange") -> 6 | J15: =COUNTIFS('post-audit-active-backlog-statu'!$C$2:$C$6832,F15,'post-audit-active-backlog-statu'!$G$2:$G$6832,"BlocksOnlyThisDomain") -> 0 | K15: =H15/G15 -> 0.688 | M15: Spell Framework | N15: =COUNTIF('post-audit-active-backlog-statu'!$D$2:$D$6832,M15) -> 186 | O15: =COUNTIFS('post-audit-active-backlog-statu'!$D$2:$D$6832,M15,'post-audit-active-backlog-statu'!$G$2:$G$6832,"Fixed") -> 18 | P15: =COUNTIFS('post-audit-active-backlog-statu'!$D$2:$D$6832,M15,'post-audit-active-backlog-statu'!$G$2:$G$6832,"ReviewedNoChange")+COUNTIFS('post-audit-active-backlog-statu'!$D$2:$D$6832,M15,'post-audit-active-backlog-statu'!$G$2:$G$6832,"SafeNoChange")+COUNTIFS('post-audit-active-backlog-statu'!$D$2:$D$6832,M15,'post-audit-active-backlog-statu'!$G$2:$G$6832,"PolicyResolvedNoChange") -> 167 | Q15: =COUNTIFS('post-audit-active-backlog-statu'!$D$2:$D$6832,M15,'post-audit-active-backlog-statu'!$G$2:$G$6832,"BlocksOnlyThisDomain") -> 0 | R15: =O15/N15 -> 0.096774194 | T15: 46315 | U15: =COUNTIF('post-audit-active-backlog-statu'!$O$2:$O$6832,TEXT(T15,"yyyy-mm-dd")&"*")+COUNTIFS('post-audit-active-backlog-statu'!$O$2:$O$6832,">="&T15,'post-audit-active-backlog-statu'!$O$2:$O$6832,"<"&T15+1) -> 2
F16: Region and map assumptions | G16: =COUNTIF('post-audit-active-backlog-statu'!$C$2:$C$6832,F16) -> 112 | H16: =COUNTIFS('post-audit-active-backlog-statu'!$C$2:$C$6832,F16,'post-audit-active-backlog-statu'!$G$2:$G$6832,"Fixed") -> 0 | I16: =COUNTIFS('post-audit-active-backlog-statu'!$C$2:$C$6832,F16,'post-audit-active-backlog-statu'!$G$2:$G$6832,"ReviewedNoChange")+COUNTIFS('post-audit-active-backlog-statu'!$C$2:$C$6832,F16,'post-audit-active-backlog-statu'!$G$2:$G$6832,"SafeNoChange")+COUNTIFS('post-audit-active-backlog-statu'!$C$2:$C$6832,F16,'post-audit-active-backlog-statu'!$G$2:$G$6832,"PolicyResolvedNoChange") -> 88 | J16: =COUNTIFS('post-audit-active-backlog-statu'!$C$2:$C$6832,F16,'post-audit-active-backlog-statu'!$G$2:$G$6832,"BlocksOnlyThisDomain") -> 0 | K16: =H16/G16 -> 0 | M16: ServerCore | N16: =COUNTIF('post-audit-active-backlog-statu'!$D$2:$D$6832,M16) -> 183 | O16: =COUNTIFS('post-audit-active-backlog-statu'!$D$2:$D$6832,M16,'post-audit-active-backlog-statu'!$G$2:$G$6832,"Fixed") -> 1 | P16: =COUNTIFS('post-audit-active-backlog-statu'!$D$2:$D$6832,M16,'post-audit-active-backlog-statu'!$G$2:$G$6832,"ReviewedNoChange")+COUNTIFS('post-audit-active-backlog-statu'!$D$2:$D$6832,M16,'post-audit-active-backlog-statu'!$G$2:$G$6832,"SafeNoChange")+COUNTIFS('post-audit-active-backlog-statu'!$D$2:$D$6832,M16,'post-audit-active-backlog-statu'!$G$2:$G$6832,"PolicyResolvedNoChange") -> 102 | Q16: =COUNTIFS('post-audit-active-backlog-statu'!$D$2:$D$6832,M16,'post-audit-active-backlog-statu'!$G$2:$G$6832,"BlocksOnlyThisDomain") -> 0 | R16: =O16/N16 -> 0.0054644809 | T16: 46320 | U16: =COUNTIF('post-audit-active-backlog-statu'!$O$2:$O$6832,TEXT(T16,"yyyy-mm-dd")&"*")+COUNTIFS('post-audit-active-backlog-statu'!$O$2:$O$6832,">="&T16,'post-audit-active-backlog-statu'!$O$2:$O$6832,"<"&T16+1) -> 7
F17: Project include drift | G17: =COUNTIF('post-audit-active-backlog-statu'!$C$2:$C$6832,F17) -> 61 | H17: =COUNTIFS('post-audit-active-backlog-statu'!$C$2:$C$6832,F17,'post-audit-active-backlog-statu'!$G$2:$G$6832,"Fixed") -> 61 | I17: =COUNTIFS('post-audit-active-backlog-statu'!$C$2:$C$6832,F17,'post-audit-active-backlog-statu'!$G$2:$G$6832,"ReviewedNoChange")+COUNTIFS('post-audit-active-backlog-statu'!$C$2:$C$6832,F17,'post-audit-active-backlog-statu'!$G$2:$G$6832,"SafeNoChange")+COUNTIFS('post-audit-active-backlog-statu'!$C$2:$C$6832,F17,'post-audit-active-backlog-statu'!$G$2:$G$6832,"PolicyResolvedNoChange") -> 0 | J17: =COUNTIFS('post-audit-active-backlog-statu'!$C$2:$C$6832,F17,'post-audit-active-backlog-statu'!$G$2:$G$6832,"BlocksOnlyThisDomain") -> 0 | K17: =H17/G17 -> 1 | M17: Vendor Core | N17: =COUNTIF('post-audit-active-backlog-statu'!$D$2:$D$6832,M17) -> 151 | O17: =COUNTIFS('post-audit-active-backlog-statu'!$D$2:$D$6832,M17,'post-audit-active-backlog-statu'!$G$2:$G$6832,"Fixed") -> 4 | P17: =COUNTIFS('post-audit-active-backlog-statu'!$D$2:$D$6832,M17,'post-audit-active-backlog-statu'!$G$2:$G$6832,"ReviewedNoChange")+COUNTIFS('post-audit-active-backlog-statu'!$D$2:$D$6832,M17,'post-audit-active-backlog-statu'!$G$2:$G$6832,"SafeNoChange")+COUNTIFS('post-audit-active-backlog-statu'!$D$2:$D$6832,M17,'post-audit-active-backlog-statu'!$G$2:$G$6832,"PolicyResolvedNoChange") -> 132 | Q17: =COUNTIFS('post-audit-active-backlog-statu'!$D$2:$D$6832,M17,'post-audit-active-backlog-statu'!$G$2:$G$6832,"BlocksOnlyThisDomain") -> 0 | R17: =O17/N17 -> 0.026490066
A18: Data-quality check | B18: Count / gap | C18: Result | F18: BaseCallOrder | G18: =COUNTIF('post-audit-active-backlog-statu'!$C$2:$C$6832,F18) -> 27 | H18: =COUNTIFS('post-audit-active-backlog-statu'!$C$2:$C$6832,F18,'post-audit-active-backlog-statu'!$G$2:$G$6832,"Fixed") -> 0 | I18: =COUNTIFS('post-audit-active-backlog-statu'!$C$2:$C$6832,F18,'post-audit-active-backlog-statu'!$G$2:$G$6832,"ReviewedNoChange")+COUNTIFS('post-audit-active-backlog-statu'!$C$2:$C$6832,F18,'post-audit-active-backlog-statu'!$G$2:$G$6832,"SafeNoChange")+COUNTIFS('post-audit-active-backlog-statu'!$C$2:$C$6832,F18,'post-audit-active-backlog-statu'!$G$2:$G$6832,"PolicyResolvedNoChange") -> 4 | J18: =COUNTIFS('post-audit-active-backlog-statu'!$C$2:$C$6832,F18,'post-audit-active-backlog-statu'!$G$2:$G$6832,"BlocksOnlyThisDomain") -> 0 | K18: =H18/G18 -> 0 | M18: Custom:Mobiles | N18: =COUNTIF('post-audit-active-backlog-statu'!$D$2:$D$6832,M18) -> 148 | O18: =COUNTIFS('post-audit-active-backlog-statu'!$D$2:$D$6832,M18,'post-audit-active-backlog-statu'!$G$2:$G$6832,"Fixed") -> 0 | P18: =COUNTIFS('post-audit-active-backlog-statu'!$D$2:$D$6832,M18,'post-audit-active-backlog-statu'!$G$2:$G$6832,"ReviewedNoChange")+COUNTIFS('post-audit-active-backlog-statu'!$D$2:$D$6832,M18,'post-audit-active-backlog-statu'!$G$2:$G$6832,"SafeNoChange")+COUNTIFS('post-audit-active-backlog-statu'!$D$2:$D$6832,M18,'post-audit-active-backlog-statu'!$G$2:$G$6832,"PolicyResolvedNoChange") -> 148 | Q18: =COUNTIFS('post-audit-active-backlog-statu'!$D$2:$D$6832,M18,'post-audit-active-backlog-statu'!$G$2:$G$6832,"BlocksOnlyThisDomain") -> 0 | R18: =O18/N18 -> 0
A19: Status reconciliation | B19: =SUM(B5:B15)-'Audit Dashboard'!B6 -> 0 | C19: =IF(B19=0,"OK","REVIEW") -> OK | F19: Economy and reward loops | G19: =COUNTIF('post-audit-active-backlog-statu'!$C$2:$C$6832,F19) -> 30 | H19: =COUNTIFS('post-audit-active-backlog-statu'!$C$2:$C$6832,F19,'post-audit-active-backlog-statu'!$G$2:$G$6832,"Fixed") -> 0 | I19: =COUNTIFS('post-audit-active-backlog-statu'!$C$2:$C$6832,F19,'post-audit-active-backlog-statu'!$G$2:$G$6832,"ReviewedNoChange")+COUNTIFS('post-audit-active-backlog-statu'!$C$2:$C$6832,F19,'post-audit-active-backlog-statu'!$G$2:$G$6832,"SafeNoChange")+COUNTIFS('post-audit-active-backlog-statu'!$C$2:$C$6832,F19,'post-audit-active-backlog-statu'!$G$2:$G$6832,"PolicyResolvedNoChange") -> 0 | J19: =COUNTIFS('post-audit-active-backlog-statu'!$C$2:$C$6832,F19,'post-audit-active-backlog-statu'!$G$2:$G$6832,"BlocksOnlyThisDomain") -> 0 | K19: =H19/G19 -> 0 | M19: Items:Books | N19: =COUNTIF('post-audit-active-backlog-statu'!$D$2:$D$6832,M19) -> 128 | O19: =COUNTIFS('post-audit-active-backlog-statu'!$D$2:$D$6832,M19,'post-audit-active-backlog-statu'!$G$2:$G$6832,"Fixed") -> 19 | P19: =COUNTIFS('post-audit-active-backlog-statu'!$D$2:$D$6832,M19,'post-audit-active-backlog-statu'!$G$2:$G$6832,"ReviewedNoChange")+COUNTIFS('post-audit-active-backlog-statu'!$D$2:$D$6832,M19,'post-audit-active-backlog-statu'!$G$2:$G$6832,"SafeNoChange")+COUNTIFS('post-audit-active-backlog-statu'!$D$2:$D$6832,M19,'post-audit-active-backlog-statu'!$G$2:$G$6832,"PolicyResolvedNoChange") -> 78 | Q19: =COUNTIFS('post-audit-active-backlog-statu'!$D$2:$D$6832,M19,'post-audit-active-backlog-statu'!$G$2:$G$6832,"BlocksOnlyThisDomain") -> 0 | R19: =O19/N19 -> 0.1484375
A20: Category reconciliation | B20: =SUM(G5:G21)-'Audit Dashboard'!B6 -> 0 | C20: =IF(B20=0,"OK","REVIEW") -> OK | F20: Packet handlers | G20: =COUNTIF('post-audit-active-backlog-statu'!$C$2:$C$6832,F20) -> 17 | H20: =COUNTIFS('post-audit-active-backlog-statu'!$C$2:$C$6832,F20,'post-audit-active-backlog-statu'!$G$2:$G$6832,"Fixed") -> 3 | I20: =COUNTIFS('post-audit-active-backlog-statu'!$C$2:$C$6832,F20,'post-audit-active-backlog-statu'!$G$2:$G$6832,"ReviewedNoChange")+COUNTIFS('post-audit-active-backlog-statu'!$C$2:$C$6832,F20,'post-audit-active-backlog-statu'!$G$2:$G$6832,"SafeNoChange")+COUNTIFS('post-audit-active-backlog-statu'!$C$2:$C$6832,F20,'post-audit-active-backlog-statu'!$G$2:$G$6832,"PolicyResolvedNoChange") -> 14 | J20: =COUNTIFS('post-audit-active-backlog-statu'!$C$2:$C$6832,F20,'post-audit-active-backlog-statu'!$G$2:$G$6832,"BlocksOnlyThisDomain") -> 0 | K20: =H20/G20 -> 0.17647059 | M20: Housing | N20: =COUNTIF('post-audit-active-backlog-statu'!$D$2:$D$6832,M20) -> 123 | O20: =COUNTIFS('post-audit-active-backlog-statu'!$D$2:$D$6832,M20,'post-audit-active-backlog-statu'!$G$2:$G$6832,"Fixed") -> 40 | P20: =COUNTIFS('post-audit-active-backlog-statu'!$D$2:$D$6832,M20,'post-audit-active-backlog-statu'!$G$2:$G$6832,"ReviewedNoChange")+COUNTIFS('post-audit-active-backlog-statu'!$D$2:$D$6832,M20,'post-audit-active-backlog-statu'!$G$2:$G$6832,"SafeNoChange")+COUNTIFS('post-audit-active-backlog-statu'!$D$2:$D$6832,M20,'post-audit-active-backlog-statu'!$G$2:$G$6832,"PolicyResolvedNoChange") -> 69 | Q20: =COUNTIFS('post-audit-active-backlog-statu'!$D$2:$D$6832,M20,'post-audit-active-backlog-statu'!$G$2:$G$6832,"BlocksOnlyThisDomain") -> 0 | R20: =O20/N20 -> 0.32520325
A21: System reconciliation | B21: =SUM(N5:N209)-'Audit Dashboard'!B6 -> 0 | C21: =IF(B21=0,"OK","REVIEW") -> OK | F21: Folder and namespace cleanup | G21: =COUNTIF('post-audit-active-backlog-statu'!$C$2:$C$6832,F21) -> 14 | H21: =COUNTIFS('post-audit-active-backlog-statu'!$C$2:$C$6832,F21,'post-audit-active-backlog-statu'!$G$2:$G$6832,"Fixed") -> 8 | I21: =COUNTIFS('post-audit-active-backlog-statu'!$C$2:$C$6832,F21,'post-audit-active-backlog-statu'!$G$2:$G$6832,"ReviewedNoChange")+COUNTIFS('post-audit-active-backlog-statu'!$C$2:$C$6832,F21,'post-audit-active-backlog-statu'!$G$2:$G$6832,"SafeNoChange")+COUNTIFS('post-audit-active-backlog-statu'!$C$2:$C$6832,F21,'post-audit-active-backlog-statu'!$G$2:$G$6832,"PolicyResolvedNoChange") -> 0 | J21: =COUNTIFS('post-audit-active-backlog-statu'!$C$2:$C$6832,F21,'post-audit-active-backlog-statu'!$G$2:$G$6832,"BlocksOnlyThisDomain") -> 6 | K21: =H21/G21 -> 0.57142857 | M21: Mobiles:Civilized | N21: =COUNTIF('post-audit-active-backlog-statu'!$D$2:$D$6832,M21) -> 118 | O21: =COUNTIFS('post-audit-active-backlog-statu'!$D$2:$D$6832,M21,'post-audit-active-backlog-statu'!$G$2:$G$6832,"Fixed") -> 24 | P21: =COUNTIFS('post-audit-active-backlog-statu'!$D$2:$D$6832,M21,'post-audit-active-backlog-statu'!$G$2:$G$6832,"ReviewedNoChange")+COUNTIFS('post-audit-active-backlog-statu'!$D$2:$D$6832,M21,'post-audit-active-backlog-statu'!$G$2:$G$6832,"SafeNoChange")+COUNTIFS('post-audit-active-backlog-statu'!$D$2:$D$6832,M21,'post-audit-active-backlog-statu'!$G$2:$G$6832,"PolicyResolvedNoChange") -> 87 | Q21: =COUNTIFS('post-audit-active-backlog-statu'!$D$2:$D$6832,M21,'post-audit-active-backlog-statu'!$G$2:$G$6832,"BlocksOnlyThisDomain") -> 0 | R21: =O21/N21 -> 0.20338983
A22: Date reconciliation | B22: =SUM(U5:U16)-'Audit Dashboard'!B6 -> 0 | C22: =IF(B22=0,"OK","REVIEW") -> OK | M22: System:Obsolete | N22: =COUNTIF('post-audit-active-backlog-statu'!$D$2:$D$6832,M22) -> 110 | O22: =COUNTIFS('post-audit-active-backlog-statu'!$D$2:$D$6832,M22,'post-audit-active-backlog-statu'!$G$2:$G$6832,"Fixed") -> 13 | P22: =COUNTIFS('post-audit-active-backlog-statu'!$D$2:$D$6832,M22,'post-audit-active-backlog-statu'!$G$2:$G$6832,"ReviewedNoChange")+COUNTIFS('post-audit-active-backlog-statu'!$D$2:$D$6832,M22,'post-audit-active-backlog-statu'!$G$2:$G$6832,"SafeNoChange")+COUNTIFS('post-audit-active-backlog-statu'!$D$2:$D$6832,M22,'post-audit-active-backlog-statu'!$G$2:$G$6832,"PolicyResolvedNoChange") -> 37 | Q22: =COUNTIFS('post-audit-active-backlog-statu'!$D$2:$D$6832,M22,'post-audit-active-backlog-statu'!$G$2:$G$6832,"BlocksOnlyThisDomain") -> 0 | R22: =O22/N22 -> 0.11818182
A23: Repeated ID rows | B23: {=SUMPRODUCT(('post-audit-active-backlog-statu'!$A$2:$A$6832<>"")*(COUNTIF('post-audit-active-backlog-statu'!$A$2:$A$6832,'post-audit-active-backlog-statu'!$A$2:$A$6832)>1))} -> 0 | C23: =IF(B23=0,"OK","REVIEW") -> OK | M23: Items:Construction | N23: =COUNTIF('post-audit-active-backlog-statu'!$D$2:$D$6832,M23) -> 105 | O23: =COUNTIFS('post-audit-active-backlog-statu'!$D$2:$D$6832,M23,'post-audit-active-backlog-statu'!$G$2:$G$6832,"Fixed") -> 0 | P23: =COUNTIFS('post-audit-active-backlog-statu'!$D$2:$D$6832,M23,'post-audit-active-backlog-statu'!$G$2:$G$6832,"ReviewedNoChange")+COUNTIFS('post-audit-active-backlog-statu'!$D$2:$D$6832,M23,'post-audit-active-backlog-statu'!$G$2:$G$6832,"SafeNoChange")+COUNTIFS('post-audit-active-backlog-statu'!$D$2:$D$6832,M23,'post-audit-active-backlog-statu'!$G$2:$G$6832,"PolicyResolvedNoChange") -> 12 | Q23: =COUNTIFS('post-audit-active-backlog-statu'!$D$2:$D$6832,M23,'post-audit-active-backlog-statu'!$G$2:$G$6832,"BlocksOnlyThisDomain") -> 0 | R23: =O23/N23 -> 0
A24: Missing active status | B24: =COUNTIFS('post-audit-active-backlog-statu'!$A$2:$A$6832,"<>",'post-audit-active-backlog-statu'!$G$2:$G$6832,"") -> 0 | C24: =IF(B24=0,"OK","REVIEW") -> OK | M24: Items:Gifts | N24: =COUNTIF('post-audit-active-backlog-statu'!$D$2:$D$6832,M24) -> 93 | O24: =COUNTIFS('post-audit-active-backlog-statu'!$D$2:$D$6832,M24,'post-audit-active-backlog-statu'!$G$2:$G$6832,"Fixed") -> 14 | P24: =COUNTIFS('post-audit-active-backlog-statu'!$D$2:$D$6832,M24,'post-audit-active-backlog-statu'!$G$2:$G$6832,"ReviewedNoChange")+COUNTIFS('post-audit-active-backlog-statu'!$D$2:$D$6832,M24,'post-audit-active-backlog-statu'!$G$2:$G$6832,"SafeNoChange")+COUNTIFS('post-audit-active-backlog-statu'!$D$2:$D$6832,M24,'post-audit-active-backlog-statu'!$G$2:$G$6832,"PolicyResolvedNoChange") -> 52 | Q24: =COUNTIFS('post-audit-active-backlog-statu'!$D$2:$D$6832,M24,'post-audit-active-backlog-statu'!$G$2:$G$6832,"BlocksOnlyThisDomain") -> 0 | R24: =O24/N24 -> 0.15053763
A25: Missing review artifact | B25: =COUNTIFS('post-audit-active-backlog-statu'!$A$2:$A$6832,"<>",'post-audit-active-backlog-statu'!$L$2:$L$6832,"") -> 0 | C25: =IF(B25=0,"OK","REVIEW") -> OK | F25: Historical status | G25: Records | H25: Now fixed | I25: Domain blockers | M25: Custom:XMLSpawner | N25: =COUNTIF('post-audit-active-backlog-statu'!$D$2:$D$6832,M25) -> 92 | O25: =COUNTIFS('post-audit-active-backlog-statu'!$D$2:$D$6832,M25,'post-audit-active-backlog-statu'!$G$2:$G$6832,"Fixed") -> 13 | P25: =COUNTIFS('post-audit-active-backlog-statu'!$D$2:$D$6832,M25,'post-audit-active-backlog-statu'!$G$2:$G$6832,"ReviewedNoChange")+COUNTIFS('post-audit-active-backlog-statu'!$D$2:$D$6832,M25,'post-audit-active-backlog-statu'!$G$2:$G$6832,"SafeNoChange")+COUNTIFS('post-audit-active-backlog-statu'!$D$2:$D$6832,M25,'post-audit-active-backlog-statu'!$G$2:$G$6832,"PolicyResolvedNoChange") -> 33 | Q25: =COUNTIFS('post-audit-active-backlog-statu'!$D$2:$D$6832,M25,'post-audit-active-backlog-statu'!$G$2:$G$6832,"BlocksOnlyThisDomain") -> 0 | R25: =O25/N25 -> 0.14130435
A26: Missing source evidence | B26: =COUNTIFS('post-audit-active-backlog-statu'!$A$2:$A$6832,"<>",'post-audit-active-backlog-statu'!$M$2:$M$6832,"") -> 0 | C26: =IF(B26=0,"OK","REVIEW") -> OK | F26: Ready | G26: =COUNTIF('post-audit-active-backlog-statu'!$F$2:$F$6832,F26) -> 6601 | H26: =COUNTIFS('post-audit-active-backlog-statu'!$F$2:$F$6832,F26,'post-audit-active-backlog-statu'!$G$2:$G$6832,"Fixed") -> 939 | I26: =COUNTIFS('post-audit-active-backlog-statu'!$F$2:$F$6832,F26,'post-audit-active-backlog-statu'!$G$2:$G$6832,"BlocksOnlyThisDomain") -> 1 | M26: Items:Trades | N26: =COUNTIF('post-audit-active-backlog-statu'!$D$2:$D$6832,M26) -> 90 | O26: =COUNTIFS('post-audit-active-backlog-statu'!$D$2:$D$6832,M26,'post-audit-active-backlog-statu'!$G$2:$G$6832,"Fixed") -> 2 | P26: =COUNTIFS('post-audit-active-backlog-statu'!$D$2:$D$6832,M26,'post-audit-active-backlog-statu'!$G$2:$G$6832,"ReviewedNoChange")+COUNTIFS('post-audit-active-backlog-statu'!$D$2:$D$6832,M26,'post-audit-active-backlog-statu'!$G$2:$G$6832,"SafeNoChange")+COUNTIFS('post-audit-active-backlog-statu'!$D$2:$D$6832,M26,'post-audit-active-backlog-statu'!$G$2:$G$6832,"PolicyResolvedNoChange") -> 69 | Q26: =COUNTIFS('post-audit-active-backlog-statu'!$D$2:$D$6832,M26,'post-audit-active-backlog-statu'!$G$2:$G$6832,"BlocksOnlyThisDomain") -> 0 | R26: =O26/N26 -> 0.022222222
A27: Missing update time | B27: =COUNTIFS('post-audit-active-backlog-statu'!$A$2:$A$6832,"<>",'post-audit-active-backlog-statu'!$O$2:$O$6832,"") -> 0 | C27: =IF(B27=0,"OK","REVIEW") -> OK | F27: Open | G27: =COUNTIF('post-audit-active-backlog-statu'!$F$2:$F$6832,F27) -> 216 | H27: =COUNTIFS('post-audit-active-backlog-statu'!$F$2:$F$6832,F27,'post-audit-active-backlog-statu'!$G$2:$G$6832,"Fixed") -> 10 | I27: =COUNTIFS('post-audit-active-backlog-statu'!$F$2:$F$6832,F27,'post-audit-active-backlog-statu'!$G$2:$G$6832,"BlocksOnlyThisDomain") -> 0 | M27: System:Gumps | N27: =COUNTIF('post-audit-active-backlog-statu'!$D$2:$D$6832,M27) -> 89 | O27: =COUNTIFS('post-audit-active-backlog-statu'!$D$2:$D$6832,M27,'post-audit-active-backlog-statu'!$G$2:$G$6832,"Fixed") -> 16 | P27: =COUNTIFS('post-audit-active-backlog-statu'!$D$2:$D$6832,M27,'post-audit-active-backlog-statu'!$G$2:$G$6832,"ReviewedNoChange")+COUNTIFS('post-audit-active-backlog-statu'!$D$2:$D$6832,M27,'post-audit-active-backlog-statu'!$G$2:$G$6832,"SafeNoChange")+COUNTIFS('post-audit-active-backlog-statu'!$D$2:$D$6832,M27,'post-audit-active-backlog-statu'!$G$2:$G$6832,"PolicyResolvedNoChange") -> 69 | Q27: =COUNTIFS('post-audit-active-backlog-statu'!$D$2:$D$6832,M27,'post-audit-active-backlog-statu'!$G$2:$G$6832,"BlocksOnlyThisDomain") -> 0 | R27: =O27/N27 -> 0.17977528
F28: Deferred | G28: =COUNTIF('post-audit-active-backlog-statu'!$F$2:$F$6832,F28) -> 14 | H28: =COUNTIFS('post-audit-active-backlog-statu'!$F$2:$F$6832,F28,'post-audit-active-backlog-statu'!$G$2:$G$6832,"Fixed") -> 8 | I28: =COUNTIFS('post-audit-active-backlog-statu'!$F$2:$F$6832,F28,'post-audit-active-backlog-statu'!$G$2:$G$6832,"BlocksOnlyThisDomain") -> 6 | M28: Items:Decorations | N28: =COUNTIF('post-audit-active-backlog-statu'!$D$2:$D$6832,M28) -> 81 | O28: =COUNTIFS('post-audit-active-backlog-statu'!$D$2:$D$6832,M28,'post-audit-active-backlog-statu'!$G$2:$G$6832,"Fixed") -> 0 | P28: =COUNTIFS('post-audit-active-backlog-statu'!$D$2:$D$6832,M28,'post-audit-active-backlog-statu'!$G$2:$G$6832,"ReviewedNoChange")+COUNTIFS('post-audit-active-backlog-statu'!$D$2:$D$6832,M28,'post-audit-active-backlog-statu'!$G$2:$G$6832,"SafeNoChange")+COUNTIFS('post-audit-active-backlog-statu'!$D$2:$D$6832,M28,'post-audit-active-backlog-statu'!$G$2:$G$6832,"PolicyResolvedNoChange") -> 2 | Q28: =COUNTIFS('post-audit-active-backlog-statu'!$D$2:$D$6832,M28,'post-audit-active-backlog-statu'!$G$2:$G$6832,"BlocksOnlyThisDomain") -> 0 | R28: =O28/N28 -> 0
M29: Homestead | N29: =COUNTIF('post-audit-active-backlog-statu'!$D$2:$D$6832,M29) -> 58 | O29: =COUNTIFS('post-audit-active-backlog-statu'!$D$2:$D$6832,M29,'post-audit-active-backlog-statu'!$G$2:$G$6832,"Fixed") -> 3 | P29: =COUNTIFS('post-audit-active-backlog-statu'!$D$2:$D$6832,M29,'post-audit-active-backlog-statu'!$G$2:$G$6832,"ReviewedNoChange")+COUNTIFS('post-audit-active-backlog-statu'!$D$2:$D$6832,M29,'post-audit-active-backlog-statu'!$G$2:$G$6832,"SafeNoChange")+COUNTIFS('post-audit-active-backlog-statu'!$D$2:$D$6832,M29,'post-audit-active-backlog-statu'!$G$2:$G$6832,"PolicyResolvedNoChange") -> 46 | Q29: =COUNTIFS('post-audit-active-backlog-statu'!$D$2:$D$6832,M29,'post-audit-active-backlog-statu'!$G$2:$G$6832,"BlocksOnlyThisDomain") -> 1 | R29: =O29/N29 -> 0.051724138
A30: Quality flags indicate missing traceability or reconciliation gaps, not necessarily unresolved work. Status names are preserved verbatim. | M30: Items:Houses | N30: =COUNTIF('post-audit-active-backlog-statu'!$D$2:$D$6832,M30) -> 56 | O30: =COUNTIFS('post-audit-active-backlog-statu'!$D$2:$D$6832,M30,'post-audit-active-backlog-statu'!$G$2:$G$6832,"Fixed") -> 18 | P30: =COUNTIFS('post-audit-active-backlog-statu'!$D$2:$D$6832,M30,'post-audit-active-backlog-statu'!$G$2:$G$6832,"ReviewedNoChange")+COUNTIFS('post-audit-active-backlog-statu'!$D$2:$D$6832,M30,'post-audit-active-backlog-statu'!$G$2:$G$6832,"SafeNoChange")+COUNTIFS('post-audit-active-backlog-statu'!$D$2:$D$6832,M30,'post-audit-active-backlog-statu'!$G$2:$G$6832,"PolicyResolvedNoChange") -> 16 | Q30: =COUNTIFS('post-audit-active-backlog-statu'!$D$2:$D$6832,M30,'post-audit-active-backlog-statu'!$G$2:$G$6832,"BlocksOnlyThisDomain") -> 1 | R30: =O30/N30 -> 0.32142857
M31: System:Skills | N31: =COUNTIF('post-audit-active-backlog-statu'!$D$2:$D$6832,M31) -> 50 | O31: =COUNTIFS('post-audit-active-backlog-statu'!$D$2:$D$6832,M31,'post-audit-active-backlog-statu'!$G$2:$G$6832,"Fixed") -> 14 | P31: =COUNTIFS('post-audit-active-backlog-statu'!$D$2:$D$6832,M31,'post-audit-active-backlog-statu'!$G$2:$G$6832,"ReviewedNoChange")+COUNTIFS('post-audit-active-backlog-statu'!$D$2:$D$6832,M31,'post-audit-active-backlog-statu'!$G$2:$G$6832,"SafeNoChange")+COUNTIFS('post-audit-active-backlog-statu'!$D$2:$D$6832,M31,'post-audit-active-backlog-statu'!$G$2:$G$6832,"PolicyResolvedNoChange") -> 36 | Q31: =COUNTIFS('post-audit-active-backlog-statu'!$D$2:$D$6832,M31,'post-audit-active-backlog-statu'!$G$2:$G$6832,"BlocksOnlyThisDomain") -> 0 | R31: =O31/N31 -> 0.28
M32: Magic Schools | N32: =COUNTIF('post-audit-active-backlog-statu'!$D$2:$D$6832,M32) -> 50 | O32: =COUNTIFS('post-audit-active-backlog-statu'!$D$2:$D$6832,M32,'post-audit-active-backlog-statu'!$G$2:$G$6832,"Fixed") -> 2 | P32: =COUNTIFS('post-audit-active-backlog-statu'!$D$2:$D$6832,M32,'post-audit-active-backlog-statu'!$G$2:$G$6832,"ReviewedNoChange")+COUNTIFS('post-audit-active-backlog-statu'!$D$2:$D$6832,M32,'post-audit-active-backlog-statu'!$G$2:$G$6832,"SafeNoChange")+COUNTIFS('post-audit-active-backlog-statu'!$D$2:$D$6832,M32,'post-audit-active-backlog-statu'!$G$2:$G$6832,"PolicyResolvedNoChange") -> 35 | Q32: =COUNTIFS('post-audit-active-backlog-statu'!$D$2:$D$6832,M32,'post-audit-active-backlog-statu'!$G$2:$G$6832,"BlocksOnlyThisDomain") -> 0 | R32: =O32/N32 -> 0.04
M33: Unknown | N33: =COUNTIF('post-audit-active-backlog-statu'!$D$2:$D$6832,M33) -> 47 | O33: =COUNTIFS('post-audit-active-backlog-statu'!$D$2:$D$6832,M33,'post-audit-active-backlog-statu'!$G$2:$G$6832,"Fixed") -> 1 | P33: =COUNTIFS('post-audit-active-backlog-statu'!$D$2:$D$6832,M33,'post-audit-active-backlog-statu'!$G$2:$G$6832,"ReviewedNoChange")+COUNTIFS('post-audit-active-backlog-statu'!$D$2:$D$6832,M33,'post-audit-active-backlog-statu'!$G$2:$G$6832,"SafeNoChange")+COUNTIFS('post-audit-active-backlog-statu'!$D$2:$D$6832,M33,'post-audit-active-backlog-statu'!$G$2:$G$6832,"PolicyResolvedNoChange") -> 7 | Q33: =COUNTIFS('post-audit-active-backlog-statu'!$D$2:$D$6832,M33,'post-audit-active-backlog-statu'!$G$2:$G$6832,"BlocksOnlyThisDomain") -> 0 | R33: =O33/N33 -> 0.021276596
A34: Backlog ID | B34: System | C34: Restricted work | D34: Source record | M34: Bulk Orders | N34: =COUNTIF('post-audit-active-backlog-statu'!$D$2:$D$6832,M34) -> 47 | O34: =COUNTIFS('post-audit-active-backlog-statu'!$D$2:$D$6832,M34,'post-audit-active-backlog-statu'!$G$2:$G$6832,"Fixed") -> 31 | P34: =COUNTIFS('post-audit-active-backlog-statu'!$D$2:$D$6832,M34,'post-audit-active-backlog-statu'!$G$2:$G$6832,"ReviewedNoChange")+COUNTIFS('post-audit-active-backlog-statu'!$D$2:$D$6832,M34,'post-audit-active-backlog-statu'!$G$2:$G$6832,"SafeNoChange")+COUNTIFS('post-audit-active-backlog-statu'!$D$2:$D$6832,M34,'post-audit-active-backlog-statu'!$G$2:$G$6832,"PolicyResolvedNoChange") -> 8 | Q34: =COUNTIFS('post-audit-active-backlog-statu'!$D$2:$D$6832,M34,'post-audit-active-backlog-statu'!$G$2:$G$6832,"BlocksOnlyThisDomain") -> 0 | R34: =O34/N34 -> 0.65957447
A35: ='post-audit-active-backlog-statu'!A1620 -> RB-06806 | B35: ='post-audit-active-backlog-statu'!D1620 -> PvP Consent | C35: =IF('post-audit-active-backlog-statu'!J1620="BlockedForReorganizationOnly","Move/reorganization","Serializer migration") -> Move/reorganization | D35: =HYPERLINK("#'post-audit-active-backlog-statu'!A1620","Open source + approval notes") -> Open source + approval notes | M35: PvP Consent | N35: =COUNTIF('post-audit-active-backlog-statu'!$D$2:$D$6832,M35) -> 45 | O35: =COUNTIFS('post-audit-active-backlog-statu'!$D$2:$D$6832,M35,'post-audit-active-backlog-statu'!$G$2:$G$6832,"Fixed") -> 4 | P35: =COUNTIFS('post-audit-active-backlog-statu'!$D$2:$D$6832,M35,'post-audit-active-backlog-statu'!$G$2:$G$6832,"ReviewedNoChange")+COUNTIFS('post-audit-active-backlog-statu'!$D$2:$D$6832,M35,'post-audit-active-backlog-statu'!$G$2:$G$6832,"SafeNoChange")+COUNTIFS('post-audit-active-backlog-statu'!$D$2:$D$6832,M35,'post-audit-active-backlog-statu'!$G$2:$G$6832,"PolicyResolvedNoChange") -> 39 | Q35: =COUNTIFS('post-audit-active-backlog-statu'!$D$2:$D$6832,M35,'post-audit-active-backlog-statu'!$G$2:$G$6832,"BlocksOnlyThisDomain") -> 1 | R35: =O35/N35 -> 0.088888889
A36: ='post-audit-active-backlog-statu'!A1622 -> RB-06808 | B36: ='post-audit-active-backlog-statu'!D1622 -> Invasion | C36: =IF('post-audit-active-backlog-statu'!J1622="BlockedForReorganizationOnly","Move/reorganization","Serializer migration") -> Move/reorganization | D36: =HYPERLINK("#'post-audit-active-backlog-statu'!A1622","Open source + approval notes") -> Open source + approval notes | M36: Mobiles:Base | N36: =COUNTIF('post-audit-active-backlog-statu'!$D$2:$D$6832,M36) -> 48 | O36: =COUNTIFS('post-audit-active-backlog-statu'!$D$2:$D$6832,M36,'post-audit-active-backlog-statu'!$G$2:$G$6832,"Fixed") -> 22 | P36: =COUNTIFS('post-audit-active-backlog-statu'!$D$2:$D$6832,M36,'post-audit-active-backlog-statu'!$G$2:$G$6832,"ReviewedNoChange")+COUNTIFS('post-audit-active-backlog-statu'!$D$2:$D$6832,M36,'post-audit-active-backlog-statu'!$G$2:$G$6832,"SafeNoChange")+COUNTIFS('post-audit-active-backlog-statu'!$D$2:$D$6832,M36,'post-audit-active-backlog-statu'!$G$2:$G$6832,"PolicyResolvedNoChange") -> 19 | Q36: =COUNTIFS('post-audit-active-backlog-statu'!$D$2:$D$6832,M36,'post-audit-active-backlog-statu'!$G$2:$G$6832,"BlocksOnlyThisDomain") -> 0 | R36: =O36/N36 -> 0.45833333
A37: ='post-audit-active-backlog-statu'!A1623 -> RB-06813 | B37: ='post-audit-active-backlog-statu'!D1623 -> XMLSpawner | C37: =IF('post-audit-active-backlog-statu'!J1623="BlockedForReorganizationOnly","Move/reorganization","Serializer migration") -> Move/reorganization | D37: =HYPERLINK("#'post-audit-active-backlog-statu'!A1623","Open source + approval notes") -> Open source + approval notes | M37: Items:Containers | N37: =COUNTIF('post-audit-active-backlog-statu'!$D$2:$D$6832,M37) -> 40 | O37: =COUNTIFS('post-audit-active-backlog-statu'!$D$2:$D$6832,M37,'post-audit-active-backlog-statu'!$G$2:$G$6832,"Fixed") -> 2 | P37: =COUNTIFS('post-audit-active-backlog-statu'!$D$2:$D$6832,M37,'post-audit-active-backlog-statu'!$G$2:$G$6832,"ReviewedNoChange")+COUNTIFS('post-audit-active-backlog-statu'!$D$2:$D$6832,M37,'post-audit-active-backlog-statu'!$G$2:$G$6832,"SafeNoChange")+COUNTIFS('post-audit-active-backlog-statu'!$D$2:$D$6832,M37,'post-audit-active-backlog-statu'!$G$2:$G$6832,"PolicyResolvedNoChange") -> 27 | Q37: =COUNTIFS('post-audit-active-backlog-statu'!$D$2:$D$6832,M37,'post-audit-active-backlog-statu'!$G$2:$G$6832,"BlocksOnlyThisDomain") -> 0 | R37: =O37/N37 -> 0.05
A38: ='post-audit-active-backlog-statu'!A1624 -> RB-06807 | B38: ='post-audit-active-backlog-statu'!D1624 -> Government | C38: =IF('post-audit-active-backlog-statu'!J1624="BlockedForReorganizationOnly","Move/reorganization","Serializer migration") -> Move/reorganization | D38: =HYPERLINK("#'post-audit-active-backlog-statu'!A1624","Open source + approval notes") -> Open source + approval notes | M38: System:Chat | N38: =COUNTIF('post-audit-active-backlog-statu'!$D$2:$D$6832,M38) -> 36 | O38: =COUNTIFS('post-audit-active-backlog-statu'!$D$2:$D$6832,M38,'post-audit-active-backlog-statu'!$G$2:$G$6832,"Fixed") -> 11 | P38: =COUNTIFS('post-audit-active-backlog-statu'!$D$2:$D$6832,M38,'post-audit-active-backlog-statu'!$G$2:$G$6832,"ReviewedNoChange")+COUNTIFS('post-audit-active-backlog-statu'!$D$2:$D$6832,M38,'post-audit-active-backlog-statu'!$G$2:$G$6832,"SafeNoChange")+COUNTIFS('post-audit-active-backlog-statu'!$D$2:$D$6832,M38,'post-audit-active-backlog-statu'!$G$2:$G$6832,"PolicyResolvedNoChange") -> 7 | Q38: =COUNTIFS('post-audit-active-backlog-statu'!$D$2:$D$6832,M38,'post-audit-active-backlog-statu'!$G$2:$G$6832,"BlocksOnlyThisDomain") -> 0 | R38: =O38/N38 -> 0.30555556
A39: ='post-audit-active-backlog-statu'!A1625 -> RB-06803 | B39: ='post-audit-active-backlog-statu'!D1625 -> Offline Skill Training | C39: =IF('post-audit-active-backlog-statu'!J1625="BlockedForReorganizationOnly","Move/reorganization","Serializer migration") -> Move/reorganization | D39: =HYPERLINK("#'post-audit-active-backlog-statu'!A1625","Open source + approval notes") -> Open source + approval notes | M39: Custom:Vhaerun's CRL Homestead System [2.0] | N39: =COUNTIF('post-audit-active-backlog-statu'!$D$2:$D$6832,M39) -> 33 | O39: =COUNTIFS('post-audit-active-backlog-statu'!$D$2:$D$6832,M39,'post-audit-active-backlog-statu'!$G$2:$G$6832,"Fixed") -> 2 | P39: =COUNTIFS('post-audit-active-backlog-statu'!$D$2:$D$6832,M39,'post-audit-active-backlog-statu'!$G$2:$G$6832,"ReviewedNoChange")+COUNTIFS('post-audit-active-backlog-statu'!$D$2:$D$6832,M39,'post-audit-active-backlog-statu'!$G$2:$G$6832,"SafeNoChange")+COUNTIFS('post-audit-active-backlog-statu'!$D$2:$D$6832,M39,'post-audit-active-backlog-statu'!$G$2:$G$6832,"PolicyResolvedNoChange") -> 22 | Q39: =COUNTIFS('post-audit-active-backlog-statu'!$D$2:$D$6832,M39,'post-audit-active-backlog-statu'!$G$2:$G$6832,"BlocksOnlyThisDomain") -> 0 | R39: =O39/N39 -> 0.060606061
A40: ='post-audit-active-backlog-statu'!A1626 -> RB-06814 | B40: ='post-audit-active-backlog-statu'!D1626 -> Homestead | C40: =IF('post-audit-active-backlog-statu'!J1626="BlockedForReorganizationOnly","Move/reorganization","Serializer migration") -> Move/reorganization | D40: =HYPERLINK("#'post-audit-active-backlog-statu'!A1626","Open source + approval notes") -> Open source + approval notes | M40: Trades:Apiculture | N40: =COUNTIF('post-audit-active-backlog-statu'!$D$2:$D$6832,M40) -> 32 | O40: =COUNTIFS('post-audit-active-backlog-statu'!$D$2:$D$6832,M40,'post-audit-active-backlog-statu'!$G$2:$G$6832,"Fixed") -> 2 | P40: =COUNTIFS('post-audit-active-backlog-statu'!$D$2:$D$6832,M40,'post-audit-active-backlog-statu'!$G$2:$G$6832,"ReviewedNoChange")+COUNTIFS('post-audit-active-backlog-statu'!$D$2:$D$6832,M40,'post-audit-active-backlog-statu'!$G$2:$G$6832,"SafeNoChange")+COUNTIFS('post-audit-active-backlog-statu'!$D$2:$D$6832,M40,'post-audit-active-backlog-statu'!$G$2:$G$6832,"PolicyResolvedNoChange") -> 30 | Q40: =COUNTIFS('post-audit-active-backlog-statu'!$D$2:$D$6832,M40,'post-audit-active-backlog-statu'!$G$2:$G$6832,"BlocksOnlyThisDomain") -> 0 | R40: =O40/N40 -> 0.0625
A41: ='post-audit-active-backlog-statu'!A2137 -> RB-00724 | B41: ='post-audit-active-backlog-statu'!D2137 -> Items:Houses | C41: =IF('post-audit-active-backlog-statu'!J2137="BlockedForReorganizationOnly","Move/reorganization","Serializer migration") -> Serializer migration | D41: =HYPERLINK("#'post-audit-active-backlog-statu'!A2137","Open source + approval notes") -> Open source + approval notes | M41: Trades:Bulk Orders | N41: =COUNTIF('post-audit-active-backlog-statu'!$D$2:$D$6832,M41) -> 29 | O41: =COUNTIFS('post-audit-active-backlog-statu'!$D$2:$D$6832,M41,'post-audit-active-backlog-statu'!$G$2:$G$6832,"Fixed") -> 2 | P41: =COUNTIFS('post-audit-active-backlog-statu'!$D$2:$D$6832,M41,'post-audit-active-backlog-statu'!$G$2:$G$6832,"ReviewedNoChange")+COUNTIFS('post-audit-active-backlog-statu'!$D$2:$D$6832,M41,'post-audit-active-backlog-statu'!$G$2:$G$6832,"SafeNoChange")+COUNTIFS('post-audit-active-backlog-statu'!$D$2:$D$6832,M41,'post-audit-active-backlog-statu'!$G$2:$G$6832,"PolicyResolvedNoChange") -> 11 | Q41: =COUNTIFS('post-audit-active-backlog-statu'!$D$2:$D$6832,M41,'post-audit-active-backlog-statu'!$G$2:$G$6832,"BlocksOnlyThisDomain") -> 0 | R41: =O41/N41 -> 0.068965517
M42: Boats | N42: =COUNTIF('post-audit-active-backlog-statu'!$D$2:$D$6832,M42) -> 29 | O42: =COUNTIFS('post-audit-active-backlog-statu'!$D$2:$D$6832,M42,'post-audit-active-backlog-statu'!$G$2:$G$6832,"Fixed") -> 8 | P42: =COUNTIFS('post-audit-active-backlog-statu'!$D$2:$D$6832,M42,'post-audit-active-backlog-statu'!$G$2:$G$6832,"ReviewedNoChange")+COUNTIFS('post-audit-active-backlog-statu'!$D$2:$D$6832,M42,'post-audit-active-backlog-statu'!$G$2:$G$6832,"SafeNoChange")+COUNTIFS('post-audit-active-backlog-statu'!$D$2:$D$6832,M42,'post-audit-active-backlog-statu'!$G$2:$G$6832,"PolicyResolvedNoChange") -> 17 | Q42: =COUNTIFS('post-audit-active-backlog-statu'!$D$2:$D$6832,M42,'post-audit-active-backlog-statu'!$G$2:$G$6832,"BlocksOnlyThisDomain") -> 0 | R42: =O42/N42 -> 0.27586207
M43: System:Help | N43: =COUNTIF('post-audit-active-backlog-statu'!$D$2:$D$6832,M43) -> 29 | O43: =COUNTIFS('post-audit-active-backlog-statu'!$D$2:$D$6832,M43,'post-audit-active-backlog-statu'!$G$2:$G$6832,"Fixed") -> 8 | P43: =COUNTIFS('post-audit-active-backlog-statu'!$D$2:$D$6832,M43,'post-audit-active-backlog-statu'!$G$2:$G$6832,"ReviewedNoChange")+COUNTIFS('post-audit-active-backlog-statu'!$D$2:$D$6832,M43,'post-audit-active-backlog-statu'!$G$2:$G$6832,"SafeNoChange")+COUNTIFS('post-audit-active-backlog-statu'!$D$2:$D$6832,M43,'post-audit-active-backlog-statu'!$G$2:$G$6832,"PolicyResolvedNoChange") -> 17 | Q43: =COUNTIFS('post-audit-active-backlog-statu'!$D$2:$D$6832,M43,'post-audit-active-backlog-statu'!$G$2:$G$6832,"BlocksOnlyThisDomain") -> 0 | R43: =O43/N43 -> 0.27586207
A44: Update guidance: source-linked formulas recalculate on edits. After adding rows, extend source references and segment lists; sort category/system tables by Records descending to refresh chart rankings. Nonzero reconciliation checks flag incomplete summaries. | M44: Mobiles:Insects | N44: =COUNTIF('post-audit-active-backlog-statu'!$D$2:$D$6832,M44) -> 28 | O44: =COUNTIFS('post-audit-active-backlog-statu'!$D$2:$D$6832,M44,'post-audit-active-backlog-statu'!$G$2:$G$6832,"Fixed") -> 24 | P44: =COUNTIFS('post-audit-active-backlog-statu'!$D$2:$D$6832,M44,'post-audit-active-backlog-statu'!$G$2:$G$6832,"ReviewedNoChange")+COUNTIFS('post-audit-active-backlog-statu'!$D$2:$D$6832,M44,'post-audit-active-backlog-statu'!$G$2:$G$6832,"SafeNoChange")+COUNTIFS('post-audit-active-backlog-statu'!$D$2:$D$6832,M44,'post-audit-active-backlog-statu'!$G$2:$G$6832,"PolicyResolvedNoChange") -> 4 | Q44: =COUNTIFS('post-audit-active-backlog-statu'!$D$2:$D$6832,M44,'post-audit-active-backlog-statu'!$G$2:$G$6832,"BlocksOnlyThisDomain") -> 0 | R44: =O44/N44 -> 0.85714286
M45: Custom:Invasion System | N45: =COUNTIF('post-audit-active-backlog-statu'!$D$2:$D$6832,M45) -> 27 | O45: =COUNTIFS('post-audit-active-backlog-statu'!$D$2:$D$6832,M45,'post-audit-active-backlog-statu'!$G$2:$G$6832,"Fixed") -> 25 | P45: =COUNTIFS('post-audit-active-backlog-statu'!$D$2:$D$6832,M45,'post-audit-active-backlog-statu'!$G$2:$G$6832,"ReviewedNoChange")+COUNTIFS('post-audit-active-backlog-statu'!$D$2:$D$6832,M45,'post-audit-active-backlog-statu'!$G$2:$G$6832,"SafeNoChange")+COUNTIFS('post-audit-active-backlog-statu'!$D$2:$D$6832,M45,'post-audit-active-backlog-statu'!$G$2:$G$6832,"PolicyResolvedNoChange") -> 0 | Q45: =COUNTIFS('post-audit-active-backlog-statu'!$D$2:$D$6832,M45,'post-audit-active-backlog-statu'!$G$2:$G$6832,"BlocksOnlyThisDomain") -> 0 | R45: =O45/N45 -> 0.92592593
M46: Gardening | N46: =COUNTIF('post-audit-active-backlog-statu'!$D$2:$D$6832,M46) -> 27 | O46: =COUNTIFS('post-audit-active-backlog-statu'!$D$2:$D$6832,M46,'post-audit-active-backlog-statu'!$G$2:$G$6832,"Fixed") -> 2 | P46: =COUNTIFS('post-audit-active-backlog-statu'!$D$2:$D$6832,M46,'post-audit-active-backlog-statu'!$G$2:$G$6832,"ReviewedNoChange")+COUNTIFS('post-audit-active-backlog-statu'!$D$2:$D$6832,M46,'post-audit-active-backlog-statu'!$G$2:$G$6832,"SafeNoChange")+COUNTIFS('post-audit-active-backlog-statu'!$D$2:$D$6832,M46,'post-audit-active-backlog-statu'!$G$2:$G$6832,"PolicyResolvedNoChange") -> 24 | Q46: =COUNTIFS('post-audit-active-backlog-statu'!$D$2:$D$6832,M46,'post-audit-active-backlog-statu'!$G$2:$G$6832,"BlocksOnlyThisDomain") -> 0 | R46: =O46/N46 -> 0.074074074
M47: Custom:Champions | N47: =COUNTIF('post-audit-active-backlog-statu'!$D$2:$D$6832,M47) -> 25 | O47: =COUNTIFS('post-audit-active-backlog-statu'!$D$2:$D$6832,M47,'post-audit-active-backlog-statu'!$G$2:$G$6832,"Fixed") -> 8 | P47: =COUNTIFS('post-audit-active-backlog-statu'!$D$2:$D$6832,M47,'post-audit-active-backlog-statu'!$G$2:$G$6832,"ReviewedNoChange")+COUNTIFS('post-audit-active-backlog-statu'!$D$2:$D$6832,M47,'post-audit-active-backlog-statu'!$G$2:$G$6832,"SafeNoChange")+COUNTIFS('post-audit-active-backlog-statu'!$D$2:$D$6832,M47,'post-audit-active-backlog-statu'!$G$2:$G$6832,"PolicyResolvedNoChange") -> 1 | Q47: =COUNTIFS('post-audit-active-backlog-statu'!$D$2:$D$6832,M47,'post-audit-active-backlog-statu'!$G$2:$G$6832,"BlocksOnlyThisDomain") -> 0 | R47: =O47/N47 -> 0.32
M48: Mobiles:Unique | N48: =COUNTIF('post-audit-active-backlog-statu'!$D$2:$D$6832,M48) -> 24 | O48: =COUNTIFS('post-audit-active-backlog-statu'!$D$2:$D$6832,M48,'post-audit-active-backlog-statu'!$G$2:$G$6832,"Fixed") -> 16 | P48: =COUNTIFS('post-audit-active-backlog-statu'!$D$2:$D$6832,M48,'post-audit-active-backlog-statu'!$G$2:$G$6832,"ReviewedNoChange")+COUNTIFS('post-audit-active-backlog-statu'!$D$2:$D$6832,M48,'post-audit-active-backlog-statu'!$G$2:$G$6832,"SafeNoChange")+COUNTIFS('post-audit-active-backlog-statu'!$D$2:$D$6832,M48,'post-audit-active-backlog-statu'!$G$2:$G$6832,"PolicyResolvedNoChange") -> 8 | Q48: =COUNTIFS('post-audit-active-backlog-statu'!$D$2:$D$6832,M48,'post-audit-active-backlog-statu'!$G$2:$G$6832,"BlocksOnlyThisDomain") -> 0 | R48: =O48/N48 -> 0.66666667
M49: Trades:Guild | N49: =COUNTIF('post-audit-active-backlog-statu'!$D$2:$D$6832,M49) -> 24 | O49: =COUNTIFS('post-audit-active-backlog-statu'!$D$2:$D$6832,M49,'post-audit-active-backlog-statu'!$G$2:$G$6832,"Fixed") -> 13 | P49: =COUNTIFS('post-audit-active-backlog-statu'!$D$2:$D$6832,M49,'post-audit-active-backlog-statu'!$G$2:$G$6832,"ReviewedNoChange")+COUNTIFS('post-audit-active-backlog-statu'!$D$2:$D$6832,M49,'post-audit-active-backlog-statu'!$G$2:$G$6832,"SafeNoChange")+COUNTIFS('post-audit-active-backlog-statu'!$D$2:$D$6832,M49,'post-audit-active-backlog-statu'!$G$2:$G$6832,"PolicyResolvedNoChange") -> 11 | Q49: =COUNTIFS('post-audit-active-backlog-statu'!$D$2:$D$6832,M49,'post-audit-active-backlog-statu'!$G$2:$G$6832,"BlocksOnlyThisDomain") -> 0 | R49: =O49/N49 -> 0.54166667
M50: Custom:Voting | N50: =COUNTIF('post-audit-active-backlog-statu'!$D$2:$D$6832,M50) -> 23 | O50: =COUNTIFS('post-audit-active-backlog-statu'!$D$2:$D$6832,M50,'post-audit-active-backlog-statu'!$G$2:$G$6832,"Fixed") -> 2 | P50: =COUNTIFS('post-audit-active-backlog-statu'!$D$2:$D$6832,M50,'post-audit-active-backlog-statu'!$G$2:$G$6832,"ReviewedNoChange")+COUNTIFS('post-audit-active-backlog-statu'!$D$2:$D$6832,M50,'post-audit-active-backlog-statu'!$G$2:$G$6832,"SafeNoChange")+COUNTIFS('post-audit-active-backlog-statu'!$D$2:$D$6832,M50,'post-audit-active-backlog-statu'!$G$2:$G$6832,"PolicyResolvedNoChange") -> 10 | Q50: =COUNTIFS('post-audit-active-backlog-statu'!$D$2:$D$6832,M50,'post-audit-active-backlog-statu'!$G$2:$G$6832,"BlocksOnlyThisDomain") -> 0 | R50: =O50/N50 -> 0.086956522
M51: Custom:Government System | N51: =COUNTIF('post-audit-active-backlog-statu'!$D$2:$D$6832,M51) -> 21 | O51: =COUNTIFS('post-audit-active-backlog-statu'!$D$2:$D$6832,M51,'post-audit-active-backlog-statu'!$G$2:$G$6832,"Fixed") -> 14 | P51: =COUNTIFS('post-audit-active-backlog-statu'!$D$2:$D$6832,M51,'post-audit-active-backlog-statu'!$G$2:$G$6832,"ReviewedNoChange")+COUNTIFS('post-audit-active-backlog-statu'!$D$2:$D$6832,M51,'post-audit-active-backlog-statu'!$G$2:$G$6832,"SafeNoChange")+COUNTIFS('post-audit-active-backlog-statu'!$D$2:$D$6832,M51,'post-audit-active-backlog-statu'!$G$2:$G$6832,"PolicyResolvedNoChange") -> 4 | Q51: =COUNTIFS('post-audit-active-backlog-statu'!$D$2:$D$6832,M51,'post-audit-active-backlog-statu'!$G$2:$G$6832,"BlocksOnlyThisDomain") -> 0 | R51: =O51/N51 -> 0.66666667
M52: Items:Weapons | N52: =COUNTIF('post-audit-active-backlog-statu'!$D$2:$D$6832,M52) -> 21 | O52: =COUNTIFS('post-audit-active-backlog-statu'!$D$2:$D$6832,M52,'post-audit-active-backlog-statu'!$G$2:$G$6832,"Fixed") -> 5 | P52: =COUNTIFS('post-audit-active-backlog-statu'!$D$2:$D$6832,M52,'post-audit-active-backlog-statu'!$G$2:$G$6832,"ReviewedNoChange")+COUNTIFS('post-audit-active-backlog-statu'!$D$2:$D$6832,M52,'post-audit-active-backlog-statu'!$G$2:$G$6832,"SafeNoChange")+COUNTIFS('post-audit-active-backlog-statu'!$D$2:$D$6832,M52,'post-audit-active-backlog-statu'!$G$2:$G$6832,"PolicyResolvedNoChange") -> 0 | Q52: =COUNTIFS('post-audit-active-backlog-statu'!$D$2:$D$6832,M52,'post-audit-active-backlog-statu'!$G$2:$G$6832,"BlocksOnlyThisDomain") -> 0 | R52: =O52/N52 -> 0.23809524
M53: PlayerMobile Core | N53: =COUNTIF('post-audit-active-backlog-statu'!$D$2:$D$6832,M53) -> 21 | O53: =COUNTIFS('post-audit-active-backlog-statu'!$D$2:$D$6832,M53,'post-audit-active-backlog-statu'!$G$2:$G$6832,"Fixed") -> 1 | P53: =COUNTIFS('post-audit-active-backlog-statu'!$D$2:$D$6832,M53,'post-audit-active-backlog-statu'!$G$2:$G$6832,"ReviewedNoChange")+COUNTIFS('post-audit-active-backlog-statu'!$D$2:$D$6832,M53,'post-audit-active-backlog-statu'!$G$2:$G$6832,"SafeNoChange")+COUNTIFS('post-audit-active-backlog-statu'!$D$2:$D$6832,M53,'post-audit-active-backlog-statu'!$G$2:$G$6832,"PolicyResolvedNoChange") -> 11 | Q53: =COUNTIFS('post-audit-active-backlog-statu'!$D$2:$D$6832,M53,'post-audit-active-backlog-statu'!$G$2:$G$6832,"BlocksOnlyThisDomain") -> 0 | R53: =O53/N53 -> 0.047619048
M54: Items:Technology | N54: =COUNTIF('post-audit-active-backlog-statu'!$D$2:$D$6832,M54) -> 20 | O54: =COUNTIFS('post-audit-active-backlog-statu'!$D$2:$D$6832,M54,'post-audit-active-backlog-statu'!$G$2:$G$6832,"Fixed") -> 1 | P54: =COUNTIFS('post-audit-active-backlog-statu'!$D$2:$D$6832,M54,'post-audit-active-backlog-statu'!$G$2:$G$6832,"ReviewedNoChange")+COUNTIFS('post-audit-active-backlog-statu'!$D$2:$D$6832,M54,'post-audit-active-backlog-statu'!$G$2:$G$6832,"SafeNoChange")+COUNTIFS('post-audit-active-backlog-statu'!$D$2:$D$6832,M54,'post-audit-active-backlog-statu'!$G$2:$G$6832,"PolicyResolvedNoChange") -> 17 | Q54: =COUNTIFS('post-audit-active-backlog-statu'!$D$2:$D$6832,M54,'post-audit-active-backlog-statu'!$G$2:$G$6832,"BlocksOnlyThisDomain") -> 0 | R54: =O54/N54 -> 0.05
M55: Custom:AnimalSystem | N55: =COUNTIF('post-audit-active-backlog-statu'!$D$2:$D$6832,M55) -> 20 | O55: =COUNTIFS('post-audit-active-backlog-statu'!$D$2:$D$6832,M55,'post-audit-active-backlog-statu'!$G$2:$G$6832,"Fixed") -> 20 | P55: =COUNTIFS('post-audit-active-backlog-statu'!$D$2:$D$6832,M55,'post-audit-active-backlog-statu'!$G$2:$G$6832,"ReviewedNoChange")+COUNTIFS('post-audit-active-backlog-statu'!$D$2:$D$6832,M55,'post-audit-active-backlog-statu'!$G$2:$G$6832,"SafeNoChange")+COUNTIFS('post-audit-active-backlog-statu'!$D$2:$D$6832,M55,'post-audit-active-backlog-statu'!$G$2:$G$6832,"PolicyResolvedNoChange") -> 0 | Q55: =COUNTIFS('post-audit-active-backlog-statu'!$D$2:$D$6832,M55,'post-audit-active-backlog-statu'!$G$2:$G$6832,"BlocksOnlyThisDomain") -> 0 | R55: =O55/N55 -> 1
M56: Obsolete Scripts | N56: =COUNTIF('post-audit-active-backlog-statu'!$D$2:$D$6832,M56) -> 20 | O56: =COUNTIFS('post-audit-active-backlog-statu'!$D$2:$D$6832,M56,'post-audit-active-backlog-statu'!$G$2:$G$6832,"Fixed") -> 2 | P56: =COUNTIFS('post-audit-active-backlog-statu'!$D$2:$D$6832,M56,'post-audit-active-backlog-statu'!$G$2:$G$6832,"ReviewedNoChange")+COUNTIFS('post-audit-active-backlog-statu'!$D$2:$D$6832,M56,'post-audit-active-backlog-statu'!$G$2:$G$6832,"SafeNoChange")+COUNTIFS('post-audit-active-backlog-statu'!$D$2:$D$6832,M56,'post-audit-active-backlog-statu'!$G$2:$G$6832,"PolicyResolvedNoChange") -> 2 | Q56: =COUNTIFS('post-audit-active-backlog-statu'!$D$2:$D$6832,M56,'post-audit-active-backlog-statu'!$G$2:$G$6832,"BlocksOnlyThisDomain") -> 0 | R56: =O56/N56 -> 0.1
... M209: Quests:TriggerTile.cs | N209: =COUNTIF('post-audit-active-backlog-statu'!$D$2:$D$6832,M209) -> 1 | O209: =COUNTIFS('post-audit-active-backlog-statu'!$D$2:$D$6832,M209,'post-audit-active-backlog-statu'!$G$2:$G$6832,"Fixed") -> 1 | P209: =COUNTIFS('post-audit-active-backlog-statu'!$D$2:$D$6832,M209,'post-audit-active-backlog-statu'!$G$2:$G$6832,"ReviewedNoChange")+COUNTIFS('post-audit-active-backlog-statu'!$D$2:$D$6832,M209,'post-audit-active-backlog-statu'!$G$2:$G$6832,"SafeNoChange")+COUNTIFS('post-audit-active-backlog-statu'!$D$2:$D$6832,M209,'post-audit-active-backlog-statu'!$G$2:$G$6832,"PolicyResolvedNoChange") -> 0 | Q209: =COUNTIFS('post-audit-active-backlog-statu'!$D$2:$D$6832,M209,'post-audit-active-backlog-statu'!$G$2:$G$6832,"BlocksOnlyThisDomain") -> 0 | R209: =O209/N209 -> 1
